Workbook

Sheet 03_Historical_FS
A1: MWG - Historical Financial Statements (VND bn)
A2: Period: 2022A-2025A | Unit: VND bn ; Green = linked raw data ; Black = calculations
A4: Section | B4: Line Item | C4: Unit | D4: 2021A | E4: 2022A | F4: 2023A | G4: 2024A | H4: 2025A | I4: Source Sheet | J4: Source item_id
A5: INCOME STATEMENT
B6: Gross Revenue | C6: VND bn | D6: 124141.53 | E6: =IFERROR('90_Raw_IS_vnstock'!F2/1000000000,0) -> 134722.25 | F6: =IFERROR('90_Raw_IS_vnstock'!E2/1000000000,0) -> 119234.18 | G6: =IFERROR('90_Raw_IS_vnstock'!D2/1000000000,0) -> 135225.1 | H6: =IFERROR('90_Raw_IS_vnstock'!C2/1000000000,0) -> 156836.12 | I6: 90_Raw_IS_vnstock | J6: revenue
B7: Revenue | C7: VND bn | D7: 122958.11 | E7: =IFERROR('90_Raw_IS_vnstock'!F4/1000000000,0) -> 133404.78 | F7: =IFERROR('90_Raw_IS_vnstock'!E4/1000000000,0) -> 118279.79 | G7: =IFERROR('90_Raw_IS_vnstock'!D4/1000000000,0) -> 134341.15 | H7: =IFERROR('90_Raw_IS_vnstock'!C4/1000000000,0) -> 155928.15 | I7: 90_Raw_IS_vnstock | J7: revenue
B8: COGS | C8: VND bn | D8: 95325.974 | E8: =IFERROR('90_Raw_IS_vnstock'!F5/1000000000,0) -> 102542.74 | F8: =IFERROR('90_Raw_IS_vnstock'!E5/1000000000,0) -> 95759.175 | G8: =IFERROR('90_Raw_IS_vnstock'!D5/1000000000,0) -> 106841.94 | H8: =IFERROR('90_Raw_IS_vnstock'!C5/1000000000,0) -> 124926.27 | I8: 90_Raw_IS_vnstock | J8: cost_of_goods_sold
B9: Gross Profit | C9: VND bn | D9: 27632.132 | E9: =IFERROR('90_Raw_IS_vnstock'!F6/1000000000,0) -> 30862.042 | F9: =IFERROR('90_Raw_IS_vnstock'!E6/1000000000,0) -> 22520.613 | G9: =IFERROR('90_Raw_IS_vnstock'!D6/1000000000,0) -> 27499.21 | H9: =IFERROR('90_Raw_IS_vnstock'!C6/1000000000,0) -> 31001.877 | I9: 90_Raw_IS_vnstock | J9: gross_profit
B10: Gross Margin | C10: % | D10: 0.22472802 | E10: =IFERROR(E9/E7,0) -> 0.23134136 | F10: =IFERROR(F9/F7,0) -> 0.1904012 | G10: =IFERROR(G9/G7,0) -> 0.20469684 | H10: =IFERROR(H9/H7,0) -> 0.19882156 | I10: Formula
B11: Financial Income | C11: VND bn | D11: 1287.956 | E11: =IFERROR('90_Raw_IS_vnstock'!F8/1000000000,0) -> 1313.1373 | F11: =IFERROR('90_Raw_IS_vnstock'!E8/1000000000,0) -> 2166.9637 | G11: =IFERROR('90_Raw_IS_vnstock'!D8/1000000000,0) -> 2376.5026 | H11: =IFERROR('90_Raw_IS_vnstock'!C8/1000000000,0) -> 3107.3487 | I11: 90_Raw_IS_vnstock | J11: financial_income
B12: Finance Expenses | C12: VND bn | D12: 714.70723 | E12: =IFERROR('90_Raw_IS_vnstock'!F9/1000000000,0) -> 1382.6205 | F12: =IFERROR('90_Raw_IS_vnstock'!E9/1000000000,0) -> 1556.1461 | G12: =IFERROR('90_Raw_IS_vnstock'!D9/1000000000,0) -> 1188.4656 | H12: =IFERROR('90_Raw_IS_vnstock'!C9/1000000000,0) -> 1542.5187 | I12: 90_Raw_IS_vnstock | J12: finance_expenses
B13: Interest Expense | C13: VND bn | D13: 674.42775 | E13: =IFERROR('90_Raw_IS_vnstock'!F10/1000000000,0) -> 1362.1439 | F13: =IFERROR('90_Raw_IS_vnstock'!E10/1000000000,0) -> 1447.7184 | G13: =IFERROR('90_Raw_IS_vnstock'!D10/1000000000,0) -> 1137.2361 | H13: =IFERROR('90_Raw_IS_vnstock'!C10/1000000000,0) -> 1470.6756 | I13: 90_Raw_IS_vnstock | J13: of_which_interest_expense
B14: Selling Expenses | C14: VND bn | D14: 17914.173 | E14: =IFERROR('90_Raw_IS_vnstock'!F12/1000000000,0) -> 22336.838 | F14: =IFERROR('90_Raw_IS_vnstock'!E12/1000000000,0) -> 20916.711 | G14: =IFERROR('90_Raw_IS_vnstock'!D12/1000000000,0) -> 19849.838 | H14: =IFERROR('90_Raw_IS_vnstock'!C12/1000000000,0) -> 19330.904 | I14: 90_Raw_IS_vnstock | J14: selling_expenses
B15: G&A Expenses | C15: VND bn | D15: 3823.3901 | E15: =IFERROR('90_Raw_IS_vnstock'!F13/1000000000,0) -> 1881.0276 | F15: =IFERROR('90_Raw_IS_vnstock'!E13/1000000000,0) -> 1167.6517 | G15: =IFERROR('90_Raw_IS_vnstock'!D13/1000000000,0) -> 3565.7676 | H15: =IFERROR('90_Raw_IS_vnstock'!C13/1000000000,0) -> 4596.0745 | I15: 90_Raw_IS_vnstock | J15: admin_expenses
B16: Operating Expenses | C16: VND bn | D16: 21737.563 | E16: =E14+E15 -> 24217.866 | F16: =F14+F15 -> 22084.362 | G16: =G14+G15 -> 23415.605 | H16: =H14+H15 -> 23926.978 | I16: Formula
B17: EBIT | C17: VND bn | D17: 6465.6069 | E17: =IFERROR('90_Raw_IS_vnstock'!F14/1000000000,0) -> 6574.6937 | F17: =IFERROR('90_Raw_IS_vnstock'!E14/1000000000,0) -> 1047.0684 | G17: =IFERROR('90_Raw_IS_vnstock'!D14/1000000000,0) -> 5227.0454 | H17: =IFERROR('90_Raw_IS_vnstock'!C14/1000000000,0) -> 8664.0805 | I17: 90_Raw_IS_vnstock | J17: operating_profit
B18: EBIT Margin | C18: % | D18: 0.05258382 | E18: =IFERROR(E17/E7,0) -> 0.049283795 | F18: =IFERROR(F17/F7,0) -> 0.0088524706 | G18: =IFERROR(G17/G7,0) -> 0.038908743 | H18: =IFERROR(H17/H7,0) -> 0.055564571 | I18: Formula
B19: Other Profit | C19: VND bn | D19: 5.9768322 | E19: =IFERROR('90_Raw_IS_vnstock'!F17/1000000000,0) -> -518.33833 | F19: =IFERROR('90_Raw_IS_vnstock'!E17/1000000000,0) -> -357.37599 | G19: =IFERROR('90_Raw_IS_vnstock'!D17/1000000000,0) -> -401.28241 | H19: =IFERROR('90_Raw_IS_vnstock'!C17/1000000000,0) -> -31.012906 | I19: 90_Raw_IS_vnstock | J19: other_profit
B20: Profit Before Tax | C20: VND bn | D20: 6471.5838 | E20: =IFERROR('90_Raw_IS_vnstock'!F19/1000000000,0) -> 6056.3554 | F20: =IFERROR('90_Raw_IS_vnstock'!E19/1000000000,0) -> 689.69237 | G20: =IFERROR('90_Raw_IS_vnstock'!D19/1000000000,0) -> 4825.763 | H20: =IFERROR('90_Raw_IS_vnstock'!C19/1000000000,0) -> 8633.0676 | I20: 90_Raw_IS_vnstock | J20: profit_before_tax
B21: Current Tax Expense | C21: VND bn | D21: 1632.9757 | E21: =IFERROR('90_Raw_IS_vnstock'!F20/1000000000,0) -> 1792.9988 | F21: =IFERROR('90_Raw_IS_vnstock'!E20/1000000000,0) -> 433.25718 | G21: =IFERROR('90_Raw_IS_vnstock'!D20/1000000000,0) -> 1282.5371 | H21: =IFERROR('90_Raw_IS_vnstock'!C20/1000000000,0) -> 1721.5595 | I21: 90_Raw_IS_vnstock | J21: current_corporate_income_tax_expenses
B22: Deferred Tax Expense | C22: VND bn | D22: -62.818619 | E22: =IFERROR('90_Raw_IS_vnstock'!F21/1000000000,0) -> 161.64214 | F22: =IFERROR('90_Raw_IS_vnstock'!E21/1000000000,0) -> 88.606036 | G22: =IFERROR('90_Raw_IS_vnstock'!D21/1000000000,0) -> -190.06233 | H22: =IFERROR('90_Raw_IS_vnstock'!C21/1000000000,0) -> -161.11483 | I22: 90_Raw_IS_vnstock | J22: deferred_income_tax_expenses
B23: Total Tax Expense | C23: VND bn | D23: 1570.1571 | E23: =E21+E22 -> 1954.6409 | F23: =F21+F22 -> 521.86321 | G23: =G21+G22 -> 1092.4748 | H23: =H21+H22 -> 1560.4447 | I23: Formula
B24: NPAT | C24: VND bn | D24: 4901.4267 | E24: =IFERROR('90_Raw_IS_vnstock'!F22/1000000000,0) -> 4101.7144 | F24: =IFERROR('90_Raw_IS_vnstock'!E22/1000000000,0) -> 167.82915 | G24: =IFERROR('90_Raw_IS_vnstock'!D22/1000000000,0) -> 3733.2882 | H24: ='06_Revenue_Drivers_Hist'!H9 -> 7072.6229 | I24: 90_Raw_IS_vnstock | J24: net_profit
B25: Minority Interest - IS | C25: VND bn | D25: 2.5573957 | E25: =IFERROR('90_Raw_IS_vnstock'!F23/1000000000,0) -> 1.951398 | F25: =IFERROR('90_Raw_IS_vnstock'!E23/1000000000,0) -> 0.159762 | G25: =IFERROR('90_Raw_IS_vnstock'!D23/1000000000,0) -> 11.419787 | H25: =IFERROR('90_Raw_IS_vnstock'!C23/1000000000,0) -> 38.892116 | I25: 90_Raw_IS_vnstock | J25: minority_interest
B26: NPATMI | C26: VND bn | D26: 4898.8693 | E26: =IFERROR('90_Raw_IS_vnstock'!F24/1000000000,0) -> 4099.763 | F26: =IFERROR('90_Raw_IS_vnstock'!E24/1000000000,0) -> 167.66939 | G26: =IFERROR('90_Raw_IS_vnstock'!D24/1000000000,0) -> 3721.8684 | H26: =IFERROR('90_Raw_IS_vnstock'!C24/1000000000,0) -> 7033.7308 | I26: 90_Raw_IS_vnstock | J26: profit_after_tax_for_shareholders_of_parent_company
B27: NPATMI Margin | C27: % | D27: 0.039841776 | E27: =IFERROR(E26/E7,0) -> 0.030731756 | F27: =IFERROR(F26/F7,0) -> 0.0014175659 | G27: =IFERROR(G26/G7,0) -> 0.027704604 | H27: =IFERROR(H26/H7,0) -> 0.045108795 | I27: Formula
A28: BALANCE SHEET
B29: Cash & Cash Equivalents | C29: VND bn | D29: 4142.0158 | E29: =IFERROR('91_Raw_BS_vnstock'!F4/1000000000,0) -> 5061.0205 | F29: =IFERROR('91_Raw_BS_vnstock'!E4/1000000000,0) -> 5365.7049 | G29: =IFERROR('91_Raw_BS_vnstock'!D4/1000000000,0) -> 4897.3315 | H29: =IFERROR('91_Raw_BS_vnstock'!C4/1000000000,0) -> 4999.9257 | I29: 91_Raw_BS_vnstock | J29: cash_and_cash_equivalents
B30: Short-term Financial Investments | C30: VND bn | D30: 14236.626 | E30: =IFERROR('91_Raw_BS_vnstock'!F7/1000000000,0) -> 10069.25 | F30: =IFERROR('91_Raw_BS_vnstock'!E7/1000000000,0) -> 18937.008 | G30: =IFERROR('91_Raw_BS_vnstock'!D7/1000000000,0) -> 29324.442 | H30: =IFERROR('91_Raw_BS_vnstock'!C7/1000000000,0) -> 33874.27 | I30: 91_Raw_BS_vnstock | J30: short_term_financial_investments
B31: Receivables | C31: VND bn | D31: 3162.122 | E31: =IFERROR('91_Raw_BS_vnstock'!F14/1000000000,0) -> 3000.8175 | F31: =IFERROR('91_Raw_BS_vnstock'!E14/1000000000,0) -> 5158.8533 | G31: =IFERROR('91_Raw_BS_vnstock'!D14/1000000000,0) -> 8825.8962 | H31: =IFERROR('91_Raw_BS_vnstock'!C14/1000000000,0) -> 10182.836 | I31: 91_Raw_BS_vnstock | J31: short_term_receivables
B32: Inventory | C32: VND bn | D32: 29167.232 | E32: =IFERROR('91_Raw_BS_vnstock'!F23/1000000000,0) -> 25696.078 | F32: =IFERROR('91_Raw_BS_vnstock'!E23/1000000000,0) -> 21824.236 | G32: =IFERROR('91_Raw_BS_vnstock'!D23/1000000000,0) -> 22244.676 | H32: =IFERROR('91_Raw_BS_vnstock'!C23/1000000000,0) -> 27266.852 | I32: 91_Raw_BS_vnstock | J32: inventories
B33: Other Current Assets | C33: VND bn | D33: 1247.2614 | E33: =IFERROR('91_Raw_BS_vnstock'!F30/1000000000,0) -> 750.44187 | F33: =IFERROR('91_Raw_BS_vnstock'!E30/1000000000,0) -> 664.53608 | G33: =IFERROR('91_Raw_BS_vnstock'!D30/1000000000,0) -> 544.07677 | H33: =IFERROR('91_Raw_BS_vnstock'!C30/1000000000,0) -> 877.76701 | I33: 91_Raw_BS_vnstock | J33: other_short_term_assets
B34: Total Current Assets | C34: VND bn | D34: 51955.258 | E34: =IFERROR('91_Raw_BS_vnstock'!F3/1000000000,0) -> 44577.607 | F34: =IFERROR('91_Raw_BS_vnstock'!E3/1000000000,0) -> 51950.338 | G34: =IFERROR('91_Raw_BS_vnstock'!D3/1000000000,0) -> 65836.423 | H34: =IFERROR('91_Raw_BS_vnstock'!C3/1000000000,0) -> 77201.651 | I34: 91_Raw_BS_vnstock | J34: current_assets
B35: Fixed Assets | C35: VND bn | D35: 9647.1689 | E35: =IFERROR('91_Raw_BS_vnstock'!F45/1000000000,0) -> 9727.5029 | F35: =IFERROR('91_Raw_BS_vnstock'!E45/1000000000,0) -> 6500.1356 | G35: =IFERROR('91_Raw_BS_vnstock'!D45/1000000000,0) -> 3586.6287 | H35: =IFERROR('91_Raw_BS_vnstock'!C45/1000000000,0) -> 2598.1892 | I35: 91_Raw_BS_vnstock | J35: fixed_assets
B36: Long-term Financial Investments | C36: VND bn | D36: 0 | E36: =IFERROR('91_Raw_BS_vnstock'!F70/1000000000,0) -> 231.03484 | F36: =IFERROR('91_Raw_BS_vnstock'!E70/1000000000,0) -> 746.63225 | G36: =IFERROR('91_Raw_BS_vnstock'!D70/1000000000,0) -> 242.0358 | H36: =IFERROR('91_Raw_BS_vnstock'!C70/1000000000,0) -> 3136.3156 | I36: 91_Raw_BS_vnstock | J36: long_term_financial_investments
B37: Other Long-term Assets | C37: VND bn | D37: 806.89105 | E37: =IFERROR('91_Raw_BS_vnstock'!F78/1000000000,0) -> 670.59008 | F37: =IFERROR('91_Raw_BS_vnstock'!E78/1000000000,0) -> 452.06753 | G37: =IFERROR('91_Raw_BS_vnstock'!D78/1000000000,0) -> 358.45441 | H37: =IFERROR('91_Raw_BS_vnstock'!C78/1000000000,0) -> 514.74079 | I37: 91_Raw_BS_vnstock | J37: other_long_term_assets
B38: Total Assets | C38: VND bn | D38: 62971.405 | E38: =IFERROR('91_Raw_BS_vnstock'!F85/1000000000,0) -> 55834.096 | F38: =IFERROR('91_Raw_BS_vnstock'!E85/1000000000,0) -> 60111.237 | G38: =IFERROR('91_Raw_BS_vnstock'!D85/1000000000,0) -> 70437.776 | H38: =IFERROR('91_Raw_BS_vnstock'!C85/1000000000,0) -> 83945.62 | I38: 91_Raw_BS_vnstock | J38: total_assets
B39: Trade Payables | C39: VND bn | D39: 12179.775 | E39: =IFERROR('91_Raw_BS_vnstock'!F89/1000000000,0) -> 8745.8273 | F39: =IFERROR('91_Raw_BS_vnstock'!E89/1000000000,0) -> 7927.0697 | G39: =IFERROR('91_Raw_BS_vnstock'!D89/1000000000,0) -> 9179.6361 | H39: =IFERROR('91_Raw_BS_vnstock'!C89/1000000000,0) -> 13113.9 | I39: 91_Raw_BS_vnstock | J39: short_term_trade_accounts_payable
B40: Short-term Debt | C40: VND bn | D40: 24647.474 | E40: =IFERROR('91_Raw_BS_vnstock'!F99/1000000000,0) -> 10688.139 | F40: =IFERROR('91_Raw_BS_vnstock'!E99/1000000000,0) -> 19128.542 | G40: =IFERROR('91_Raw_BS_vnstock'!D99/1000000000,0) -> 27300.247 | H40: =IFERROR('91_Raw_BS_vnstock'!C99/1000000000,0) -> 29930.943 | I40: 91_Raw_BS_vnstock | J40: short_term_borrowings_and_financial_leases
B41: Current Liabilities | C41: VND bn | D41: 42593.159 | E41: =IFERROR('91_Raw_BS_vnstock'!F88/1000000000,0) -> 26000.264 | F41: =IFERROR('91_Raw_BS_vnstock'!E88/1000000000,0) -> 30765.261 | G41: =IFERROR('91_Raw_BS_vnstock'!D88/1000000000,0) -> 42316.199 | H41: =IFERROR('91_Raw_BS_vnstock'!C88/1000000000,0) -> 50769.502 | I41: 91_Raw_BS_vnstock | J41: current_liabilities
B42: Long-term Debt | C42: VND bn | D42: 0 | E42: =IFERROR('91_Raw_BS_vnstock'!F113/1000000000,0) -> 5901.25 | F42: =IFERROR('91_Raw_BS_vnstock'!E113/1000000000,0) -> 5985.25 | G42: =IFERROR('91_Raw_BS_vnstock'!D113/1000000000,0) -> 0 | H42: =IFERROR('91_Raw_BS_vnstock'!C113/1000000000,0) -> 0 | I42: 91_Raw_BS_vnstock | J42: long_term_borrowings_and_financial_leases
B43: Long-term Liabilities | C43: VND bn | D43: 0 | E43: =IFERROR('91_Raw_BS_vnstock'!F104/1000000000,0) -> 5901.25 | F43: =IFERROR('91_Raw_BS_vnstock'!E104/1000000000,0) -> 5986.4187 | G43: =IFERROR('91_Raw_BS_vnstock'!D104/1000000000,0) -> 0 | H43: =IFERROR('91_Raw_BS_vnstock'!C104/1000000000,0) -> 0 | I43: 91_Raw_BS_vnstock | J43: long_term_liabilities
B44: Total Liabilities | C44: VND bn | D44: 42593.159 | E44: =IFERROR('91_Raw_BS_vnstock'!F87/1000000000,0) -> 31901.514 | F44: =IFERROR('91_Raw_BS_vnstock'!E87/1000000000,0) -> 36751.679 | G44: =IFERROR('91_Raw_BS_vnstock'!D87/1000000000,0) -> 42316.199 | H44: =IFERROR('91_Raw_BS_vnstock'!C87/1000000000,0) -> 50769.502 | I44: 91_Raw_BS_vnstock | J44: total_liabilities
B45: Share Capital | C45: VND bn | D45: 7130.655 | E45: =IFERROR('91_Raw_BS_vnstock'!F122/1000000000,0) -> 14638.793 | F45: =IFERROR('91_Raw_BS_vnstock'!E122/1000000000,0) -> 14633.767 | G45: =IFERROR('91_Raw_BS_vnstock'!D122/1000000000,0) -> 14622.442 | H45: =IFERROR('91_Raw_BS_vnstock'!C122/1000000000,0) -> 14696.932 | I45: 91_Raw_BS_vnstock | J45: owners_capital
B46: Retained Earnings | C46: VND bn | D46: 12674.574 | E46: =IFERROR('91_Raw_BS_vnstock'!F134/1000000000,0) -> 8723.9342 | F46: =IFERROR('91_Raw_BS_vnstock'!E134/1000000000,0) -> 8160.3236 | G46: =IFERROR('91_Raw_BS_vnstock'!D134/1000000000,0) -> 12582.145 | H46: =IFERROR('91_Raw_BS_vnstock'!C134/1000000000,0) -> 18068.195 | I46: 91_Raw_BS_vnstock | J46: retained_earnings
B47: Minority Interest - BS | C47: VND bn | D47: 11.838029 | E47: =IFERROR('91_Raw_BS_vnstock'!F138/1000000000,0) -> 14.508097 | F47: =IFERROR('91_Raw_BS_vnstock'!E138/1000000000,0) -> 13.40103 | G47: =IFERROR('91_Raw_BS_vnstock'!D138/1000000000,0) -> 364.02065 | H47: =IFERROR('91_Raw_BS_vnstock'!C138/1000000000,0) -> 576.35099 | I47: 91_Raw_BS_vnstock | J47: minority_interest
B48: Total Equity | C48: VND bn | D48: 20378.246 | E48: =IFERROR('91_Raw_BS_vnstock'!F120/1000000000,0) -> 23932.582 | F48: =IFERROR('91_Raw_BS_vnstock'!E120/1000000000,0) -> 23359.558 | G48: =IFERROR('91_Raw_BS_vnstock'!D120/1000000000,0) -> 28121.577 | H48: =IFERROR('91_Raw_BS_vnstock'!C120/1000000000,0) -> 33176.117 | I48: 91_Raw_BS_vnstock | J48: owners_equity_2
B49: Total Liabilities + Equity | C49: VND bn | D49: 62971.405 | E49: =IFERROR('91_Raw_BS_vnstock'!F144/1000000000,0) -> 55834.096 | F49: =IFERROR('91_Raw_BS_vnstock'!E144/1000000000,0) -> 60111.237 | G49: =IFERROR('91_Raw_BS_vnstock'!D144/1000000000,0) -> 70437.776 | H49: =IFERROR('91_Raw_BS_vnstock'!C144/1000000000,0) -> 83945.62 | I49: 91_Raw_BS_vnstock | J49: total_owners_equity_and_liabilities
B50: Total Debt | C50: VND bn | D50: 24647.474 | E50: =E40+E42 -> 16589.389 | F50: =F40+F42 -> 25113.792 | G50: =G40+G42 -> 27300.247 | H50: =H40+H42 -> 29930.943 | I50: Formula
B51: Net Debt | C51: VND bn | D51: 6268.8322 | E51: =E50-E29-E30 -> 1459.1185 | F51: =F50-F29-F30 -> 811.07889 | G51: =G50-G29-G30 -> -6921.5266 | H51: =H50-H29-H30 -> -8943.2529 | I51: Formula
B52: Net Working Capital | C52: VND bn | D52: 20149.579 | E52: =E31+E32-E39 -> 19951.068 | F52: =F31+F32-F39 -> 19056.019 | G52: =G31+G32-G39 -> 21890.936 | H52: =H31+H32-H39 -> 24335.788 | I52: Formula
A53: CASH FLOW
B54: CF Profit Before Tax | C54: VND bn | D54: 6471.5838 | E54: =IFERROR('92_Raw_CF_vnstock'!F3/1000000000,0) -> 6056.3554 | F54: =IFERROR('92_Raw_CF_vnstock'!E3/1000000000,0) -> 689.69237 | G54: =IFERROR('92_Raw_CF_vnstock'!D3/1000000000,0) -> 4825.763 | H54: =IFERROR('92_Raw_CF_vnstock'!C3/1000000000,0) -> 8633.0676 | I54: 92_Raw_CF_vnstock | J54: profit_before_tax
B55: D&A | C55: VND bn | D55: 2920.7136 | E55: =IFERROR('92_Raw_CF_vnstock'!F5/1000000000,0) -> 3540.3247 | F55: =IFERROR('92_Raw_CF_vnstock'!E5/1000000000,0) -> 3351.3143 | G55: =IFERROR('92_Raw_CF_vnstock'!D5/1000000000,0) -> 2913.4191 | H55: =IFERROR('92_Raw_CF_vnstock'!C5/1000000000,0) -> 1890.8821 | I55: 92_Raw_CF_vnstock | J55: depreciation_of_fixed_assets_and_investment_properties
B56: Interest Paid | C56: VND bn | D56: -585.13604 | E56: =IFERROR('92_Raw_CF_vnstock'!F20/1000000000,0) -> -1322.3811 | F56: =IFERROR('92_Raw_CF_vnstock'!E20/1000000000,0) -> -1435.7319 | G56: =IFERROR('92_Raw_CF_vnstock'!D20/1000000000,0) -> -1141.5215 | H56: =IFERROR('92_Raw_CF_vnstock'!C20/1000000000,0) -> -1396.4603 | I56: 92_Raw_CF_vnstock | J56: interest_expenses_paid
B57: Tax Paid | C57: VND bn | D57: -1533.1021 | E57: =IFERROR('92_Raw_CF_vnstock'!F21/1000000000,0) -> -1805.3408 | F57: =IFERROR('92_Raw_CF_vnstock'!E21/1000000000,0) -> -860.4296 | G57: =IFERROR('92_Raw_CF_vnstock'!D21/1000000000,0) -> -958.91498 | H57: =IFERROR('92_Raw_CF_vnstock'!C21/1000000000,0) -> -1546.4595 | I57: 92_Raw_CF_vnstock | J57: corporate_income_tax_paid
B58: CFO | C58: VND bn | D58: 171.39044 | E58: =IFERROR('92_Raw_CF_vnstock'!F24/1000000000,0) -> 7976.2988 | F58: =IFERROR('92_Raw_CF_vnstock'!E24/1000000000,0) -> 3435.8272 | G58: =IFERROR('92_Raw_CF_vnstock'!D24/1000000000,0) -> 8517.3327 | H58: =IFERROR('92_Raw_CF_vnstock'!C24/1000000000,0) -> 6096.1407 | I58: 92_Raw_CF_vnstock | J58: operating_cash_flow
B59: Capex | C59: VND bn | D59: -4976.8766 | E59: =IFERROR('92_Raw_CF_vnstock'!F26/1000000000,0) -> -4465.3595 | F59: =IFERROR('92_Raw_CF_vnstock'!E26/1000000000,0) -> -523.38333 | G59: =IFERROR('92_Raw_CF_vnstock'!D26/1000000000,0) -> -303.74783 | H59: =IFERROR('92_Raw_CF_vnstock'!C26/1000000000,0) -> -888.46189 | I59: 92_Raw_CF_vnstock | J59: payment_for_fixed_assets_constructions_and_other_long_term_assets
B60: CFI | C60: VND bn | D60: -11254.87 | E60: =IFERROR('92_Raw_CF_vnstock'!F37/1000000000,0) -> 1549.1114 | F60: =IFERROR('92_Raw_CF_vnstock'!E37/1000000000,0) -> -10831.295 | G60: =IFERROR('92_Raw_CF_vnstock'!D37/1000000000,0) -> -11743.286 | H60: =IFERROR('92_Raw_CF_vnstock'!C37/1000000000,0) -> -6660.7754 | I60: 92_Raw_CF_vnstock | J60: investing_cash_flow
B61: Debt Proceeds | C61: VND bn | D61: 63936.208 | E61: =IFERROR('92_Raw_CF_vnstock'!F41/1000000000,0) -> 65251.648 | F61: =IFERROR('92_Raw_CF_vnstock'!E41/1000000000,0) -> 70373.733 | G61: =IFERROR('92_Raw_CF_vnstock'!D41/1000000000,0) -> 74756.279 | H61: =IFERROR('92_Raw_CF_vnstock'!C41/1000000000,0) -> 98550.109 | I61: 92_Raw_CF_vnstock | J61: proceeds_from_borrowings
B62: Debt Repayments | C62: VND bn | D62: -56045.131 | E62: =IFERROR('92_Raw_CF_vnstock'!F42/1000000000,0) -> -73313.739 | F62: =IFERROR('92_Raw_CF_vnstock'!E42/1000000000,0) -> -61933.33 | G62: =IFERROR('92_Raw_CF_vnstock'!D42/1000000000,0) -> -73030.338 | H62: =IFERROR('92_Raw_CF_vnstock'!C42/1000000000,0) -> -95872.138 | I62: 92_Raw_CF_vnstock | J62: principal_repayments
B63: Dividends Paid | C63: VND bn | D63: -239.51944 | E63: =IFERROR('92_Raw_CF_vnstock'!F44/1000000000,0) -> -731.85482 | F63: =IFERROR('92_Raw_CF_vnstock'!E44/1000000000,0) -> -731.28002 | G63: =IFERROR('92_Raw_CF_vnstock'!D44/1000000000,0) -> -730.95769 | H63: =IFERROR('92_Raw_CF_vnstock'!C44/1000000000,0) -> -1478.4568 | I63: 92_Raw_CF_vnstock | J63: dividends_paid_profits_distributed_to_owners
B64: CFF | C64: VND bn | D64: 7877.4909 | E64: =IFERROR('92_Raw_CF_vnstock'!F47/1000000000,0) -> -8606.3435 | F64: =IFERROR('92_Raw_CF_vnstock'!E47/1000000000,0) -> 7699.7831 | G64: =IFERROR('92_Raw_CF_vnstock'!D47/1000000000,0) -> 2757.4755 | H64: =IFERROR('92_Raw_CF_vnstock'!C47/1000000000,0) -> 667.17175 | I64: 92_Raw_CF_vnstock | J64: financing_cash_flow
B65: Net Change in Cash | C65: VND bn | D65: -3205.9883 | E65: =IFERROR('92_Raw_CF_vnstock'!F48/1000000000,0) -> 919.0667 | F65: =IFERROR('92_Raw_CF_vnstock'!E48/1000000000,0) -> 304.31558 | G65: =IFERROR('92_Raw_CF_vnstock'!D48/1000000000,0) -> -468.47745 | H65: =IFERROR('92_Raw_CF_vnstock'!C48/1000000000,0) -> 102.53704 | I65: 92_Raw_CF_vnstock | J65: net_cash_flows_during_the_period
B66: Beginning Cash | C66: VND bn | D66: 7347.8574 | E66: =IFERROR('92_Raw_CF_vnstock'!F49/1000000000,0) -> 4142.0158 | F66: =IFERROR('92_Raw_CF_vnstock'!E49/1000000000,0) -> 5061.0205 | G66: =IFERROR('92_Raw_CF_vnstock'!D49/1000000000,0) -> 5365.7049 | H66: =IFERROR('92_Raw_CF_vnstock'!C49/1000000000,0) -> 4897.3315 | I66: 92_Raw_CF_vnstock | J66: cash_and_cash_equivalents_at_beginning_of_the_period
B67: FX Effect on Cash | C67: VND bn | D67: 0.14665399 | E67: =IFERROR('92_Raw_CF_vnstock'!F50/1000000000,0) -> -0.061919 | F67: =IFERROR('92_Raw_CF_vnstock'!E50/1000000000,0) -> 0.368728 | G67: =IFERROR('92_Raw_CF_vnstock'!D50/1000000000,0) -> 0.104134 | H67: =IFERROR('92_Raw_CF_vnstock'!C50/1000000000,0) -> 0.057132 | I67: 92_Raw_CF_vnstock | J67: exchange_difference_due_to_re_valuation_of_ending_balances
B68: Ending Cash | C68: VND bn | D68: 4142.0158 | E68: =IFERROR('92_Raw_CF_vnstock'!F51/1000000000,0) -> 5061.0205 | F68: =IFERROR('92_Raw_CF_vnstock'!E51/1000000000,0) -> 5365.7049 | G68: =IFERROR('92_Raw_CF_vnstock'!D51/1000000000,0) -> 4897.3315 | H68: =IFERROR('92_Raw_CF_vnstock'!C51/1000000000,0) -> 4999.9257 | I68: 92_Raw_CF_vnstock | J68: cash_and_cash_equivalents_at_end_of_the_period
B69: EBITDA | C69: VND bn | D69: 9386.3205 | E69: =E17+E55 -> 10115.018 | F69: =F17+F55 -> 4398.3826 | G69: =G17+G55 -> 8140.4645 | H69: =H17+H55 -> 10554.963 | I69: Formula
B70: FCFF Proxy | C70: VND bn | D70: -5019.5829 | E70: =(E17*(1-IFERROR(E23/E20,0)))+E55+E59 -> 3527.7283 | F70: =(F17*(1-IFERROR(F23/F20,0)))+F55+F59-(F52-E52) -> 3977.7723 | G70: =(G17*(1-IFERROR(G23/G20,0)))+G55+G59-(G52-F52) -> 3818.4808 | H70: =(H17*(1-IFERROR(H23/H20,0)))+H55+H59-(H52-G52) -> 5655.5986 | I70: Formula
A71: MODEL CHECKS
B72: Gross Profit Check | C72: VND bn | D72: 0 | E72: =E7-E8-E9 -> 9.9998942e-07 | F72: =F7-F8-F9 -> -9.999967e-07 | G72: =G7-G8-G9 -> 0 | H72: =H7-H8-H9 -> -1.0000113e-06 | I72: Formula | K72: Revenue - COGS - Gross Profit; should be 0
B73: Balance Sheet Check | C73: VND bn | D73: -3.6379788e-12 | E73: =E38-E44-E48 -> 0 | F73: =F38-F44-F48 -> 1.0000003e-06 | G73: =G38-G44-G48 -> 0 | H73: =H38-H44-H48 -> 0 | I73: Formula | K73: Total Assets - Total Liabilities - Total Equity; should be 0
B74: Liabilities + Equity Check | C74: VND bn | D74: 0 | E74: =E38-E49 -> 0 | F74: =F38-F49 -> 0 | G74: =G38-G49 -> 0 | H74: =H38-H49 -> 0 | I74: Formula | K74: Total Assets - Total Liabilities + Equity; should be 0
B75: Cash Flow Tie Check | C75: VND bn | D75: 9.094947e-13 | E75: =E66+E65+E67-E68 -> 1.0000003e-06 | F75: =F66+F65+F67-F68 -> 0 | G75: =G66+G65+G67-G68 -> 0 | H75: =H66+H65+H67-H68 -> 0 | I75: Formula | K75: Beginning Cash + Net Change + FX - Ending Cash; should be 0

Sheet 04_Q1_Historical_FS
A1: MWG - Q1 Historical Financial Statements and LTM Bridge
A2: Unit: VND bn; Green = workbook link ; Black = formula ;LTM Mar-26 = FY2025 - Q1 2025 + Q1 2026 for flow items.
E3: 100_Raw_Peer_Metrics!A1
A4: Section | B4: Line Item | C4: Unit | D4: Q1 2025A | E4: Q1 2026A | F4: YoY / Change | G4: LTM Mar-26 / Q1 BS | H4: Source
A5: INCOME STATEMENT
B6: Gross Revenue | C6: VND bn | D6: =IFERROR('93_Raw_IS_Q_BCTC'!C4/1000000000,0) -> 36332.913 | E6: =IFERROR('93_Raw_IS_Q_BCTC'!D4/1000000000,0) -> 46709.163 | F6: =IFERROR(E6/D6-1,"") -> 0.28558816 | G6: ='03_Historical_FS'!H6-D6+E6 -> 167212.36 | H6: 93_Raw_IS_Q_BCTC:gross_revenue
B7: Revenue | C7: VND bn | D7: =IFERROR('93_Raw_IS_Q_BCTC'!C6/1000000000,0) -> 36134.958 | E7: =IFERROR('93_Raw_IS_Q_BCTC'!D6/1000000000,0) -> 46461.952 | F7: =IFERROR(E7/D7-1,"") -> 0.28578955 | G7: ='03_Historical_FS'!H7-D7+E7 -> 166255.14 | H7: Raw_IS_Q_vnstock:revenue
B8: COGS | C8: VND bn | D8: =IFERROR('93_Raw_IS_Q_BCTC'!C7/1000000000,0) -> 28934.548 | E8: =IFERROR('93_Raw_IS_Q_BCTC'!D7/1000000000,0) -> 36751.851 | F8: =IFERROR(E8/D8-1,"") -> 0.27017194 | G8: ='03_Historical_FS'!H8-D8+E8 -> 132743.57 | H8: Raw_IS_Q_vnstock:cogs
B9: Gross Profit | C9: VND bn | D9: =IFERROR('93_Raw_IS_Q_BCTC'!C8/1000000000,0) -> 7200.4106 | E9: =IFERROR('93_Raw_IS_Q_BCTC'!D8/1000000000,0) -> 9710.1014 | F9: =IFERROR(E9/D9-1,"") -> 0.34854829 | G9: ='03_Historical_FS'!H9-D9+E9 -> 33511.568 | H9: Raw_IS_Q_vnstock:gross_profit
B10: Gross Margin | C10: % | D10: =IFERROR(D9/D7,"") -> 0.19926439 | E10: =IFERROR(E9/E7,"") -> 0.20899039 | F10: =IFERROR(E10-D10,"") -> 0.0097259946 | G10: =IFERROR(G9/G7,"") -> 0.20156711 | H10: Formula
B11: Financial Income | C11: VND bn | D11: =IFERROR('93_Raw_IS_Q_BCTC'!C9/1000000000,0) -> 693.29367 | E11: =IFERROR('93_Raw_IS_Q_BCTC'!D9/1000000000,0) -> 857.86659 | F11: =IFERROR(E11/D11-1,"") -> 0.23737837 | G11: ='03_Historical_FS'!H11-D11+E11 -> 3271.9217 | H11: Raw_IS_Q_vnstock:financial_income
B12: Finance Expenses | C12: VND bn | D12: =IFERROR('93_Raw_IS_Q_BCTC'!C10/1000000000,0) -> 339.02316 | E12: =IFERROR('93_Raw_IS_Q_BCTC'!D10/1000000000,0) -> 421.76736 | F12: =IFERROR(E12/D12-1,"") -> 0.2440665 | G12: ='03_Historical_FS'!H12-D12+E12 -> 1625.2629 | H12: Raw_IS_Q_vnstock:finance_expenses
B13: Interest Expense | C13: VND bn | D13: =IFERROR('93_Raw_IS_Q_BCTC'!C11/1000000000,0) -> 322.79285 | E13: =IFERROR('93_Raw_IS_Q_BCTC'!D11/1000000000,0) -> 415.4489 | F13: =IFERROR(E13/D13-1,"") -> 0.28704494 | G13: ='03_Historical_FS'!H13-D13+E13 -> 1563.3316 | H13: Raw_IS_Q_vnstock:interest_expense
B14: Selling Expenses | C14: VND bn | D14: =IFERROR('93_Raw_IS_Q_BCTC'!C13/1000000000,0) -> 4403.0063 | E14: =IFERROR('93_Raw_IS_Q_BCTC'!D13/1000000000,0) -> 5284.9089 | F14: =IFERROR(E14/D14-1,"") -> 0.20029554 | G14: ='03_Historical_FS'!H14-D14+E14 -> 20212.806 | H14: Raw_IS_Q_vnstock:selling_expenses
B15: G&A Expenses | C15: VND bn | D15: =IFERROR('93_Raw_IS_Q_BCTC'!C14/1000000000,0) -> 1214.5998 | E15: =IFERROR('93_Raw_IS_Q_BCTC'!D14/1000000000,0) -> 1523.1801 | F15: =IFERROR(E15/D15-1,"") -> 0.25405926 | G15: ='03_Historical_FS'!H15-D15+E15 -> 4904.6548 | H15: Raw_IS_Q_vnstock:admin_expenses
B16: Operating Expenses | C16: VND bn | D16: =D14+D15 -> 5617.6061 | E16: =E14+E15 -> 6808.089 | F16: =IFERROR(E16/D16-1,"") -> 0.21191996 | G16: =G14+G15 -> 25117.461 | H16: Formula
B17: EBIT | C17: VND bn | D17: =IFERROR('93_Raw_IS_Q_BCTC'!C15/1000000000,0) -> 1940.2048 | E17: =IFERROR('93_Raw_IS_Q_BCTC'!D15/1000000000,0) -> 3347.1234 | F17: =IFERROR(E17/D17-1,"") -> 0.72513926 | G17: ='03_Historical_FS'!H17-D17+E17 -> 10070.999 | H17: Raw_IS_Q_vnstock:ebit
B18: EBIT Margin | C18: % | D18: =IFERROR(D17/D7,"") -> 0.053693289 | E18: =IFERROR(E17/E7,"") -> 0.072040095 | F18: =IFERROR(E18-D18,"") -> 0.018346806 | G18: =IFERROR(G17/G7,"") -> 0.060575566 | H18: Formula
B19: Other Profit | C19: VND bn | D19: =IFERROR('93_Raw_IS_Q_BCTC'!C18/1000000000,0) -> -5.5433771 | E19: =IFERROR('93_Raw_IS_Q_BCTC'!D18/1000000000,0) -> -19.539118 | F19: =IFERROR(E19/D19-1,"") -> 2.5247679 | G19: ='03_Historical_FS'!H19-D19+E19 -> -45.008647 | H19: Raw_IS_Q_vnstock:other_profit
B20: Profit Before Tax | C20: VND bn | D20: =IFERROR('93_Raw_IS_Q_BCTC'!C19/1000000000,0) -> 1934.6614 | E20: =IFERROR('93_Raw_IS_Q_BCTC'!D19/1000000000,0) -> 3327.5843 | F20: =IFERROR(E20/D20-1,"") -> 0.71998279 | G20: ='03_Historical_FS'!H20-D20+E20 -> 10025.99 | H20: Raw_IS_Q_vnstock:pbt
B21: Current Tax Expense | C21: VND bn | D21: =IFERROR('93_Raw_IS_Q_BCTC'!C20/1000000000,0) -> 397.72242 | E21: =IFERROR('93_Raw_IS_Q_BCTC'!D20/1000000000,0) -> 797.0122 | F21: =IFERROR(E21/D21-1,"") -> 1.0039409 | G21: ='03_Historical_FS'!H21-D21+E21 -> 2120.8493 | H21: Raw_IS_Q_vnstock:current_tax
B22: Deferred Tax Expense | C22: VND bn | D22: =IFERROR('93_Raw_IS_Q_BCTC'!C21/1000000000,0) -> -10.894797 | E22: =IFERROR('93_Raw_IS_Q_BCTC'!D21/1000000000,0) -> -226.98492 | F22: =IFERROR(E22/D22-1,"") -> 19.83425 | G22: ='03_Historical_FS'!H22-D22+E22 -> -377.20495 | H22: Raw_IS_Q_vnstock:deferred_tax
B23: Total Tax Expense | C23: VND bn | D23: =IFERROR('93_Raw_IS_Q_BCTC'!C22/1000000000,0) -> 386.82762 | E23: =IFERROR('93_Raw_IS_Q_BCTC'!D22/1000000000,0) -> 570.02728 | F23: =IFERROR(E23/D23-1,"") -> 0.47359509 | G23: ='03_Historical_FS'!H23-D23+E23 -> 1743.6444 | H23: Raw_IS_Q_vnstock:total_tax
B24: NPAT | C24: VND bn | D24: =IFERROR('93_Raw_IS_Q_BCTC'!C23/1000000000,0) -> 1547.8338 | E24: =IFERROR('93_Raw_IS_Q_BCTC'!D23/1000000000,0) -> 2757.557 | F24: =IFERROR(E24/D24-1,"") -> 0.7815589 | G24: ='03_Historical_FS'!H24-D24+E24 -> 8282.3461 | H24: Raw_IS_Q_vnstock:npat
B25: Minority Interest - IS | C25: VND bn | D25: =IFERROR('93_Raw_IS_Q_BCTC'!C24/1000000000,0) -> 1.8966777 | E25: =IFERROR('93_Raw_IS_Q_BCTC'!D24/1000000000,0) -> 43.126168 | F25: =IFERROR(E25/D25-1,"") -> 21.737742 | G25: ='03_Historical_FS'!H25-D25+E25 -> 80.121607 | H25: Raw_IS_Q_vnstock:minority_interest_is
B26: NPATMI | C26: VND bn | D26: =IFERROR('93_Raw_IS_Q_BCTC'!C25/1000000000,0) -> 1545.9371 | E26: =IFERROR('93_Raw_IS_Q_BCTC'!D25/1000000000,0) -> 2714.4309 | F26: =IFERROR(E26/D26-1,"") -> 0.7558482 | G26: ='03_Historical_FS'!H26-D26+E26 -> 8202.2245 | H26: Raw_IS_Q_vnstock:npatmi
B27: NPATMI Margin | C27: % | D27: =IFERROR(D26/D7,"") -> 0.042782313 | E27: =IFERROR(E26/E7,"") -> 0.058422661 | F27: =IFERROR(E27-D27,"") -> 0.015640348 | G27: =IFERROR(G26/G7,"") -> 0.049335164 | H27: Formula
A28: BALANCE SHEET
B29: Cash & Cash Equivalents | C29: VND bn | D29: =IFERROR('94_Raw_BS_Q_BCTC'!C5/1000000000,0) -> 2658.2181 | E29: =IFERROR('94_Raw_BS_Q_BCTC'!D5/1000000000,0) -> 4553.6526 | F29: =IFERROR(E29/D29-1,"") -> 0.71304699 | G29: =E29 -> 4553.6526 | H29: Raw_BS_Q_vnstock:cash
B30: Short-term Financial Investments | C30: VND bn | D30: =IFERROR('94_Raw_BS_Q_BCTC'!C6/1000000000,0) -> 32390.515 | E30: =IFERROR('94_Raw_BS_Q_BCTC'!D6/1000000000,0) -> 41831.154 | F30: =IFERROR(E30/D30-1,"") -> 0.29146306 | G30: =E30 -> 41831.154 | H30: Raw_BS_Q_vnstock:short_term_investments
B31: Receivables | C31: VND bn | D31: =IFERROR('94_Raw_BS_Q_BCTC'!C7/1000000000,0) -> 9862.5322 | E31: =IFERROR('94_Raw_BS_Q_BCTC'!D7/1000000000,0) -> 2121.016 | F31: =IFERROR(E31/D31-1,"") -> -0.78494205 | G31: =E31 -> 2121.016 | H31: Raw_BS_Q_vnstock:receivables
B32: Inventory | C32: VND bn | D32: =IFERROR('94_Raw_BS_Q_BCTC'!C8/1000000000,0) -> 22808.478 | E32: =IFERROR('94_Raw_BS_Q_BCTC'!D8/1000000000,0) -> 27600.708 | F32: =IFERROR(E32/D32-1,"") -> 0.21010738 | G32: =E32 -> 27600.708 | H32: Raw_BS_Q_vnstock:inventory
B33: Other Current Assets | C33: VND bn | D33: =IFERROR('94_Raw_BS_Q_BCTC'!C9/1000000000,0) -> 630.45865 | E33: =IFERROR('94_Raw_BS_Q_BCTC'!D9/1000000000,0) -> 728.08177 | F33: =IFERROR(E33/D33-1,"") -> 0.1548446 | G33: =E33 -> 728.08177 | H33: Raw_BS_Q_vnstock:other_current_assets
B34: Total Current Assets | C34: VND bn | D34: =IFERROR('94_Raw_BS_Q_BCTC'!C4/1000000000,0) -> 68350.202 | E34: =IFERROR('94_Raw_BS_Q_BCTC'!D4/1000000000,0) -> 76834.612 | F34: =IFERROR(E34/D34-1,"") -> 0.12413145 | G34: =E34 -> 76834.612 | H34: Raw_BS_Q_vnstock:current_assets
B35: Fixed Assets | C35: VND bn | D35: =IFERROR('94_Raw_BS_Q_BCTC'!C11/1000000000,0) -> 3233.9016 | E35: =IFERROR('94_Raw_BS_Q_BCTC'!D11/1000000000,0) -> 2418.4474 | F35: =IFERROR(E35/D35-1,"") -> -0.25215802 | G35: =E35 -> 2418.4474 | H35: Raw_BS_Q_vnstock:fixed_assets
B36: Long-term Financial Investments | C36: VND bn | D36: =IFERROR('94_Raw_BS_Q_BCTC'!C12/1000000000,0) -> 245.16557 | E36: =IFERROR('94_Raw_BS_Q_BCTC'!D12/1000000000,0) -> 3466.7225 | F36: =IFERROR(E36/D36-1,"") -> 13.140332 | G36: =E36 -> 3466.7225 | H36: Raw_BS_Q_vnstock:long_term_investments
B37: Other Long-term Assets | C37: VND bn | D37: =IFERROR('94_Raw_BS_Q_BCTC'!C13/1000000000,0) -> 395.22353 | E37: =IFERROR('94_Raw_BS_Q_BCTC'!D13/1000000000,0) -> 723.1644 | F37: =IFERROR(E37/D37-1,"") -> 0.82976047 | G37: =E37 -> 723.1644 | H37: Raw_BS_Q_vnstock:other_long_term_assets
B38: Total Assets | C38: VND bn | D38: =IFERROR('94_Raw_BS_Q_BCTC'!C14/1000000000,0) -> 72679.225 | E38: =IFERROR('94_Raw_BS_Q_BCTC'!D14/1000000000,0) -> 83994.558 | F38: =IFERROR(E38/D38-1,"") -> 0.1556887 | G38: =E38 -> 83994.558 | H38: Raw_BS_Q_vnstock:total_assets
B39: Trade Payables | C39: VND bn | D39: =IFERROR('94_Raw_BS_Q_BCTC'!C15/1000000000,0) -> 11308.959 | E39: =IFERROR('94_Raw_BS_Q_BCTC'!D15/1000000000,0) -> 11892.522 | F39: =IFERROR(E39/D39-1,"") -> 0.051601815 | G39: =E39 -> 11892.522 | H39: Raw_BS_Q_vnstock:trade_payables
B40: Short-term Debt | C40: VND bn | D40: =IFERROR('94_Raw_BS_Q_BCTC'!C16/1000000000,0) -> 26222.186 | E40: =IFERROR('94_Raw_BS_Q_BCTC'!D16/1000000000,0) -> 28100.653 | F40: =IFERROR(E40/D40-1,"") -> 0.071636558 | G40: =E40 -> 28100.653 | H40: Raw_BS_Q_vnstock:short_term_debt
B41: Current Liabilities | C41: VND bn | D41: =IFERROR('94_Raw_BS_Q_BCTC'!C17/1000000000,0) -> 43010.091 | E41: =IFERROR('94_Raw_BS_Q_BCTC'!D17/1000000000,0) -> 48061.216 | F41: =IFERROR(E41/D41-1,"") -> 0.11744047 | G41: =E41 -> 48061.216 | H41: Raw_BS_Q_vnstock:current_liabilities
B42: Long-term Debt | C42: VND bn | D42: =IFERROR('94_Raw_BS_Q_BCTC'!C18/1000000000,0) -> 0 | E42: =IFERROR('94_Raw_BS_Q_BCTC'!D18/1000000000,0) -> 0 | F42: =IFERROR(E42/D42-1,"") | G42: =E42 -> 0 | H42: Raw_BS_Q_vnstock:long_term_debt
B43: Long-term Liabilities | C43: VND bn | D43: =IFERROR('94_Raw_BS_Q_BCTC'!C19/1000000000,0) -> 0 | E43: =IFERROR('94_Raw_BS_Q_BCTC'!D19/1000000000,0) -> 0 | F43: =IFERROR(E43/D43-1,"") | G43: =E43 -> 0 | H43: Raw_BS_Q_vnstock:long_term_liabilities
B44: Total Liabilities | C44: VND bn | D44: =IFERROR('94_Raw_BS_Q_BCTC'!C20/1000000000,0) -> 43010.091 | E44: =IFERROR('94_Raw_BS_Q_BCTC'!D20/1000000000,0) -> 48061.216 | F44: =IFERROR(E44/D44-1,"") -> 0.11744047 | G44: =E44 -> 48061.216 | H44: Raw_BS_Q_vnstock:total_liabilities
B45: Share Capital | C45: VND bn | D45: =IFERROR('94_Raw_BS_Q_BCTC'!C21/1000000000,0) -> 14622.442 | E45: =IFERROR('94_Raw_BS_Q_BCTC'!D21/1000000000,0) -> 14696.932 | F45: =IFERROR(E45/D45-1,"") -> 0.0050942244 | G45: =E45 -> 14696.932 | H45: Raw_BS_Q_vnstock:share_capital
B46: Retained Earnings | C46: VND bn | D46: =IFERROR('94_Raw_BS_Q_BCTC'!C22/1000000000,0) -> 14128.082 | E46: =IFERROR('94_Raw_BS_Q_BCTC'!D22/1000000000,0) -> 20782.625 | F46: =IFERROR(E46/D46-1,"") -> 0.4710153 | G46: =E46 -> 20782.625 | H46: Raw_BS_Q_vnstock:retained_earnings
... B49: Total Liabilities + Equity | C49: VND bn | D49: =IFERROR('94_Raw_BS_Q_BCTC'!C25/1000000000,0) -> 72679.225 | E49: =IFERROR('94_Raw_BS_Q_BCTC'!D25/1000000000,0) -> 83994.558 | F49: =IFERROR(E49/D49-1,"") -> 0.1556887 | G49: =E49 -> 83994.558 | H49: Raw_BS_Q_vnstock:liabilities_and_equity
B50: Total Debt | C50: VND bn | D50: =D40+D42 -> 26222.186 | E50: =E40+E42 -> 28100.653 | F50: =IFERROR(E50/D50-1,"") -> 0.071636558 | G50: =E50 -> 28100.653 | H50: Formula
B51: Net Debt | C51: VND bn | D51: =D50-D29-D30 -> -8826.5471 | E51: =E50-E29-E30 -> -18284.153 | F51: =IFERROR(E51/D51-1,"") -> 1.0714956 | G51: =E51 -> -18284.153 | H51: Formula
B52: Net Working Capital | C52: VND bn | D52: =D31+D32-D39 -> 21362.052 | E52: =E31+E32-E39 -> 17829.202 | F52: =IFERROR(E52/D52-1,"") -> -0.16537969 | G52: =E52 -> 17829.202 | H52: Formula
A53: CASH FLOW
B54: CF Profit Before Tax | C54: VND bn | D54: =IFERROR('95_Raw_CF_Q_BCTC'!C4/1000000000,0) -> 1934.6614 | E54: =IFERROR('95_Raw_CF_Q_BCTC'!D4/1000000000,0) -> 3327.5843 | F54: =IFERROR(E54/D54-1,"") -> 0.71998279 | G54: ='03_Historical_FS'!H54-D54+E54 -> 10025.99 | H54: Raw_CF_Q_vnstock:pbt
B55: D&A | C55: VND bn | D55: =IFERROR('95_Raw_CF_Q_BCTC'!C5/1000000000,0) -> 508.91947 | E55: =IFERROR('95_Raw_CF_Q_BCTC'!D5/1000000000,0) -> 393.92998 | F55: =IFERROR(E55/D55-1,"") -> -0.22594831 | G55: ='03_Historical_FS'!H55-D55+E55 -> 1775.8926 | H55: Raw_CF_Q_vnstock:da
B56: Interest Paid | C56: VND bn | D56: =IFERROR('95_Raw_CF_Q_BCTC'!C15/1000000000,0) -> -325.48564 | E56: =IFERROR('95_Raw_CF_Q_BCTC'!D15/1000000000,0) -> -438.52449 | F56: =IFERROR(E56/D56-1,"") -> 0.34729292 | G56: ='03_Historical_FS'!H56-D56+E56 -> -1509.4992 | H56: Raw_CF_Q_vnstock:interest_paid
B57: Tax Paid | C57: VND bn | D57: =IFERROR('95_Raw_CF_Q_BCTC'!C16/1000000000,0) -> -456.80041 | E57: =IFERROR('95_Raw_CF_Q_BCTC'!D16/1000000000,0) -> -796.27246 | F57: =IFERROR(E57/D57-1,"") -> 0.7431518 | G57: ='03_Historical_FS'!H57-D57+E57 -> -1885.9315 | H57: Raw_CF_Q_vnstock:tax_paid
B58: CFO | C58: VND bn | D58: =IFERROR('95_Raw_CF_Q_BCTC'!C17/1000000000,0) -> 2489.5253 | E58: =IFERROR('95_Raw_CF_Q_BCTC'!D17/1000000000,0) -> 1193.2546 | F58: =IFERROR(E58/D58-1,"") -> -0.52068993 | G58: ='03_Historical_FS'!H58-D58+E58 -> 4799.8699 | H58: Raw_CF_Q_vnstock:cfo
B59: Capex | C59: VND bn | D59: =IFERROR('95_Raw_CF_Q_BCTC'!C18/1000000000,0) -> -163.05495 | E59: =IFERROR('95_Raw_CF_Q_BCTC'!D18/1000000000,0) -> -350.14257 | F59: =IFERROR(E59/D59-1,"") -> 1.1473901 | G59: ='03_Historical_FS'!H59-D59+E59 -> -1075.5495 | H59: Raw_CF_Q_vnstock:capex
B60: CFI | C60: VND bn | D60: =IFERROR('95_Raw_CF_Q_BCTC'!C25/1000000000,0) -> -3697.9013 | E60: =IFERROR('95_Raw_CF_Q_BCTC'!D25/1000000000,0) -> 190.05593 | F60: =IFERROR(E60/D60-1,"") -> -1.0513956 | G60: ='03_Historical_FS'!H60-D60+E60 -> -2772.8182 | H60: Raw_CF_Q_vnstock:cfi
B61: Debt Proceeds | C61: VND bn | D61: =IFERROR('95_Raw_CF_Q_BCTC'!C27/1000000000,0) -> 19644.969 | E61: =IFERROR('95_Raw_CF_Q_BCTC'!D27/1000000000,0) -> 27840.348 | F61: =IFERROR(E61/D61-1,"") -> 0.41717447 | G61: ='03_Historical_FS'!H61-D61+E61 -> 106745.49 | H61: Raw_CF_Q_vnstock:debt_proceeds
B62: Debt Repayments | C62: VND bn | D62: =IFERROR('95_Raw_CF_Q_BCTC'!C28/1000000000,0) -> -20675.754 | E62: =IFERROR('95_Raw_CF_Q_BCTC'!D28/1000000000,0) -> -29670.638 | F62: =IFERROR(E62/D62-1,"") -> 0.435045 | G62: ='03_Historical_FS'!H62-D62+E62 -> -104867.02 | H62: Raw_CF_Q_vnstock:debt_repayments
B63: Dividends Paid | C63: VND bn | D63: =IFERROR('95_Raw_CF_Q_BCTC'!C29/1000000000,0) -> 0 | E63: =IFERROR('95_Raw_CF_Q_BCTC'!D29/1000000000,0) -> 0 | F63: =IFERROR(E63/D63-1,"") | G63: ='03_Historical_FS'!H63-D63+E63 -> -1478.4568 | H63: Raw_CF_Q_vnstock:dividends_paid
B64: CFF | C64: VND bn | D64: =IFERROR('95_Raw_CF_Q_BCTC'!C30/1000000000,0) -> -1030.7857 | E64: =IFERROR('95_Raw_CF_Q_BCTC'!D30/1000000000,0) -> -1830.6221 | F64: =IFERROR(E64/D64-1,"") -> 0.77594833 | G64: ='03_Historical_FS'!H64-D64+E64 -> -132.66469 | H64: Raw_CF_Q_vnstock:cff
B65: Net Change in Cash | C65: VND bn | D65: =IFERROR('95_Raw_CF_Q_BCTC'!C31/1000000000,0) -> -2239.1616 | E65: =IFERROR('95_Raw_CF_Q_BCTC'!D31/1000000000,0) -> -447.31163 | F65: =IFERROR(E65/D65-1,"") -> -0.80023254 | G65: ='03_Historical_FS'!H65-D65+E65 -> 1894.3871 | H65: Raw_CF_Q_vnstock:net_change_cash
B66: Beginning Cash | C66: VND bn | D66: =IFERROR('95_Raw_CF_Q_BCTC'!C32/1000000000,0) -> 4897.3315 | E66: =IFERROR('95_Raw_CF_Q_BCTC'!D32/1000000000,0) -> 4999.9257 | F66: =IFERROR(E66/D66-1,"") -> 0.020948996 | G66: =E66 -> 4999.9257 | H66: Raw_CF_Q_vnstock:beginning_cash
B67: FX Effect on Cash | C67: VND bn | D67: =IFERROR('95_Raw_CF_Q_BCTC'!C33/1000000000,0) -> 0.048240903 | E67: =IFERROR('95_Raw_CF_Q_BCTC'!D33/1000000000,0) -> 1.0384956 | F67: =IFERROR(E67/D67-1,"") -> 20.527283 | G67: ='03_Historical_FS'!H67-D67+E67 -> 1.0473867 | H67: Raw_CF_Q_vnstock:fx_effect_cash
B68: Ending Cash | C68: VND bn | D68: =IFERROR('95_Raw_CF_Q_BCTC'!C34/1000000000,0) -> 2658.2181 | E68: =IFERROR('95_Raw_CF_Q_BCTC'!D34/1000000000,0) -> 4553.6526 | F68: =IFERROR(E68/D68-1,"") -> 0.71304699 | G68: =E68 -> 4553.6526 | H68: Raw_CF_Q_vnstock:ending_cash
B69: EBITDA | C69: VND bn | D69: =D17+D55 -> 2449.1242 | E69: =E17+E55 -> 3741.0534 | F69: =IFERROR(E69/D69-1,"") -> 0.52750659 | G69: =G17+G55 -> 11846.892 | H69: Formula
B70: FCFF Proxy | C70: VND bn | D70: =D58+D59-D56*(1-IFERROR(D23/D20,0)) -> 2586.8765 | E70: =E58+E59-E56*(1-IFERROR(E23/E20,0)) -> 1206.5157 | F70: =IFERROR(E70/D70-1,"") -> -0.53360137 | G70: =G58+G59-G56*(1-IFERROR(G23/G20,0)) -> 4971.2989 | H70: Formula
A71: MODEL CHECKS
B72: Gross Profit Check | C72: VND bn | D72: =D7-D8-D9 -> 0 | E72: =E7-E8-E9 -> 0 | G72: =G7-G8-G9 -> -1.0000222e-06 | H72: Formula
B73: Balance Sheet Check | C73: VND bn | D73: =D38-D44-D48 -> 0 | E73: =E38-E44-E48 -> 0 | G73: =G38-G44-G48 -> 0 | H73: Formula
B74: Liabilities + Equity Check | C74: VND bn | D74: =D38-D49 -> 0 | E74: =E38-E49 -> 0 | G74: =G38-G49 -> 0 | H74: Formula
B75: Cash Flow Tie Check | C75: VND bn | D75: =D66+D65+D67-D68 -> 0 | E75: =E66+E65+E67-E68 -> 0 | H75: Formula

Sheet 05_Ratio_Analysis
A1: MWG - Ratio Analysis
A4: Section | B4: Metric | C4: Unit | D4: 2021A | E4: 2022A | F4: 2023A | G4: 2024A | H4: 2025A | I4: Q1 2025A | J4: Q1 2026A | K4: LTM Mar-26 | M4: ROIC tax rate | N4: 0.2
A5: KEY DATA | M5: Q1 annualization factor | N5: 4
B6: Revenue | C6: VND bn | D6: =IFERROR('03_Historical_FS'!D7,"") -> 122958.11 | E6: =IFERROR('03_Historical_FS'!E7,"") -> 133404.78 | F6: =IFERROR('03_Historical_FS'!F7,"") -> 118279.79 | G6: =IFERROR('03_Historical_FS'!G7,"") -> 134341.15 | H6: =IFERROR('03_Historical_FS'!H7,"") -> 155928.15 | I6: =IFERROR('04_Q1_Historical_FS'!D7,"") -> 36134.958 | J6: =IFERROR('04_Q1_Historical_FS'!E7,"") -> 46461.952 | K6: =IFERROR('04_Q1_Historical_FS'!G7,"") -> 166255.14 | M6: Days per year | N6: 365
B7: NPATMI | C7: VND bn | D7: =IFERROR('03_Historical_FS'!D26,"") -> 4898.8693 | E7: =IFERROR('03_Historical_FS'!E26,"") -> 4099.763 | F7: =IFERROR('03_Historical_FS'!F26,"") -> 167.66939 | G7: =IFERROR('03_Historical_FS'!G26,"") -> 3721.8684 | H7: =IFERROR('03_Historical_FS'!H26,"") -> 7033.7308 | I7: =IFERROR('04_Q1_Historical_FS'!D26,"") -> 1545.9371 | J7: =IFERROR('04_Q1_Historical_FS'!E26,"") -> 2714.4309 | K7: =IFERROR('04_Q1_Historical_FS'!G26,"") -> 8202.2245 | M7: Q1 day factor | N7: =N6/N5 -> 91.25
B8: EBITDA | C8: VND bn | D8: =IFERROR('03_Historical_FS'!D69,"") -> 9386.3205 | E8: =IFERROR('03_Historical_FS'!E69,"") -> 10115.018 | F8: =IFERROR('03_Historical_FS'!F69,"") -> 4398.3826 | G8: =IFERROR('03_Historical_FS'!G69,"") -> 8140.4645 | H8: =IFERROR('03_Historical_FS'!H69,"") -> 10554.963 | I8: =IFERROR('04_Q1_Historical_FS'!D69,"") -> 2449.1242 | J8: =IFERROR('04_Q1_Historical_FS'!E69,"") -> 3741.0534 | K8: =IFERROR('04_Q1_Historical_FS'!G69,"") -> 11846.892
B9: EBIT | C9: VND bn | D9: =IFERROR('03_Historical_FS'!D17,"") -> 6465.6069 | E9: =IFERROR('03_Historical_FS'!E17,"") -> 6574.6937 | F9: =IFERROR('03_Historical_FS'!F17,"") -> 1047.0684 | G9: =IFERROR('03_Historical_FS'!G17,"") -> 5227.0454 | H9: =IFERROR('03_Historical_FS'!H17,"") -> 8664.0805 | I9: =IFERROR('04_Q1_Historical_FS'!D17,"") -> 1940.2048 | J9: =IFERROR('04_Q1_Historical_FS'!E17,"") -> 3347.1234 | K9: =IFERROR('04_Q1_Historical_FS'!G17,"") -> 10070.999
B10: Interest Expense | C10: VND bn | D10: =IFERROR('03_Historical_FS'!D13,"") -> 674.42775 | E10: =IFERROR('03_Historical_FS'!E13,"") -> 1362.1439 | F10: =IFERROR('03_Historical_FS'!F13,"") -> 1447.7184 | G10: =IFERROR('03_Historical_FS'!G13,"") -> 1137.2361 | H10: =IFERROR('03_Historical_FS'!H13,"") -> 1470.6756 | I10: =IFERROR('04_Q1_Historical_FS'!D13,"") -> 322.79285 | J10: =IFERROR('04_Q1_Historical_FS'!E13,"") -> 415.4489 | K10: =IFERROR('04_Q1_Historical_FS'!G13,"") -> 1563.3316
B11: Net Debt | C11: VND bn | D11: =IFERROR('03_Historical_FS'!D51,"") -> 6268.8322 | E11: =IFERROR('03_Historical_FS'!E51,"") -> 1459.1185 | F11: =IFERROR('03_Historical_FS'!F51,"") -> 811.07889 | G11: =IFERROR('03_Historical_FS'!G51,"") -> -6921.5266 | H11: =IFERROR('03_Historical_FS'!H51,"") -> -8943.2529 | I11: =IFERROR('04_Q1_Historical_FS'!D51,"") -> -8826.5471 | J11: =IFERROR('04_Q1_Historical_FS'!E51,"") -> -18284.153 | K11: =IFERROR('04_Q1_Historical_FS'!G51,"") -> -18284.153
B12: Cash + ST Investments | C12: VND bn | D12: =IFERROR('03_Historical_FS'!D29+'03_Historical_FS'!D30,"") -> 18378.642 | E12: =IFERROR('03_Historical_FS'!E29+'03_Historical_FS'!E30,"") -> 15130.27 | F12: =IFERROR('03_Historical_FS'!F29+'03_Historical_FS'!F30,"") -> 24302.713 | G12: =IFERROR('03_Historical_FS'!G29+'03_Historical_FS'!G30,"") -> 34221.773 | H12: =IFERROR('03_Historical_FS'!H29+'03_Historical_FS'!H30,"") -> 38874.196 | I12: =IFERROR('04_Q1_Historical_FS'!D29+'04_Q1_Historical_FS'!D30,"") -> 35048.733 | J12: =IFERROR('04_Q1_Historical_FS'!E29+'04_Q1_Historical_FS'!E30,"") -> 46384.806 | K12: =IFERROR('04_Q1_Historical_FS'!G29+'04_Q1_Historical_FS'!G30,"") -> 46384.806
A13: PROFITABILITY
B14: Gross Margin | C14: % | D14: =IFERROR('03_Historical_FS'!D10,"") -> 0.22472802 | E14: =IFERROR('03_Historical_FS'!E10,"") -> 0.23134136 | F14: =IFERROR('03_Historical_FS'!F10,"") -> 0.1904012 | G14: =IFERROR('03_Historical_FS'!G10,"") -> 0.20469684 | H14: =IFERROR('03_Historical_FS'!H10,"") -> 0.19882156 | I14: =IFERROR('04_Q1_Historical_FS'!D10,"") -> 0.19926439 | J14: =IFERROR('04_Q1_Historical_FS'!E10,"") -> 0.20899039 | K14: =IFERROR('04_Q1_Historical_FS'!G10,"") -> 0.20156711
B15: EBIT Margin | C15: % | D15: =IFERROR('03_Historical_FS'!D18,"") -> 0.05258382 | E15: =IFERROR('03_Historical_FS'!E18,"") -> 0.049283795 | F15: =IFERROR('03_Historical_FS'!F18,"") -> 0.0088524706 | G15: =IFERROR('03_Historical_FS'!G18,"") -> 0.038908743 | H15: =IFERROR('03_Historical_FS'!H18,"") -> 0.055564571 | I15: =IFERROR('04_Q1_Historical_FS'!D18,"") -> 0.053693289 | J15: =IFERROR('04_Q1_Historical_FS'!E18,"") -> 0.072040095 | K15: =IFERROR('04_Q1_Historical_FS'!G18,"") -> 0.060575566
B16: NPATMI Margin | C16: % | D16: =IFERROR('03_Historical_FS'!D27,"") -> 0.039841776 | E16: =IFERROR('03_Historical_FS'!E27,"") -> 0.030731756 | F16: =IFERROR('03_Historical_FS'!F27,"") -> 0.0014175659 | G16: =IFERROR('03_Historical_FS'!G27,"") -> 0.027704604 | H16: =IFERROR('03_Historical_FS'!H27,"") -> 0.045108795 | I16: =IFERROR('04_Q1_Historical_FS'!D27,"") -> 0.042782313 | J16: =IFERROR('04_Q1_Historical_FS'!E27,"") -> 0.058422661 | K16: =IFERROR('04_Q1_Historical_FS'!G27,"") -> 0.049335164
B17: ROE | C17: % | D17: =IFERROR('03_Historical_FS'!D26/'03_Historical_FS'!D48,"") -> 0.240397 | E17: =IFERROR('03_Historical_FS'!E26/AVERAGE('03_Historical_FS'!D48,'03_Historical_FS'!E48),"") -> 0.18504565 | F17: =IFERROR('03_Historical_FS'!F26/AVERAGE('03_Historical_FS'!E48,'03_Historical_FS'!F48),"") -> 0.0070907933 | G17: =IFERROR('03_Historical_FS'!G26/AVERAGE('03_Historical_FS'!F48,'03_Historical_FS'!G48),"") -> 0.14459155 | H17: =IFERROR('03_Historical_FS'!H26/AVERAGE('03_Historical_FS'!G48,'03_Historical_FS'!H48),"") -> 0.22949414 | I17: =IFERROR(('04_Q1_Historical_FS'!D26*$N$5)/AVERAGE('03_Historical_FS'!G48,'04_Q1_Historical_FS'!D48),"") -> 0.21400493 | J17: =IFERROR(('04_Q1_Historical_FS'!E26*$N$5)/AVERAGE('03_Historical_FS'!H48,'04_Q1_Historical_FS'!E48),"") -> 0.31421815 | K17: =IFERROR('04_Q1_Historical_FS'!G26/AVERAGE('03_Historical_FS'!H48,'04_Q1_Historical_FS'!E48),"") -> 0.23736908
B18: ROA | C18: % | D18: =IFERROR('03_Historical_FS'!D24/'03_Historical_FS'!D38,"") -> 0.077835752 | E18: =IFERROR('03_Historical_FS'!E24/AVERAGE('03_Historical_FS'!D38,'03_Historical_FS'!E38),"") -> 0.069049234 | F18: =IFERROR('03_Historical_FS'!F24/AVERAGE('03_Historical_FS'!E38,'03_Historical_FS'!F38),"") -> 0.0028949704 | G18: =IFERROR('03_Historical_FS'!G24/AVERAGE('03_Historical_FS'!F38,'03_Historical_FS'!G38),"") -> 0.057193665 | H18: =IFERROR('03_Historical_FS'!H24/AVERAGE('03_Historical_FS'!G38,'03_Historical_FS'!H38),"") -> 0.09162414 | I18: =IFERROR(('04_Q1_Historical_FS'!D24*$N$5)/AVERAGE('03_Historical_FS'!G38,'04_Q1_Historical_FS'!D38),"") -> 0.086521309 | J18: =IFERROR(('04_Q1_Historical_FS'!E24*$N$5)/AVERAGE('03_Historical_FS'!H38,'04_Q1_Historical_FS'!E38),"") -> 0.13135901 | K18: =IFERROR('04_Q1_Historical_FS'!G24/AVERAGE('03_Historical_FS'!H38,'04_Q1_Historical_FS'!E38),"") -> 0.098634481
B19: ROIC | C19: % | D19: =IFERROR(('03_Historical_FS'!D17*(1-$N$4))/('03_Historical_FS'!D50+'03_Historical_FS'!D48-'03_Historical_FS'!D29-'03_Historical_FS'!D30),"") -> 0.1941108 | E19: =IFERROR(('03_Historical_FS'!E17*(1-$N$4))/AVERAGE(('03_Historical_FS'!D50+'03_Historical_FS'!D48-'03_Historical_FS'!D29-'03_Historical_FS'!D30),('03_Historical_FS'!E50+'03_Historical_FS'!E48-'03_Historical_FS'!E29-'03_Historical_FS'!E30)),"") -> 0.20214752 | F19: =IFERROR(('03_Historical_FS'!F17*(1-$N$4))/AVERAGE(('03_Historical_FS'!E50+'03_Historical_FS'!E48-'03_Historical_FS'!E29-'03_Historical_FS'!E30),('03_Historical_FS'!F50+'03_Historical_FS'!F48-'03_Historical_FS'!F29-'03_Historical_FS'!F30)),"") -> 0.033802066 | G19: =IFERROR(('03_Historical_FS'!G17*(1-$N$4))/AVERAGE(('03_Historical_FS'!F50+'03_Historical_FS'!F48-'03_Historical_FS'!F29-'03_Historical_FS'!F30),('03_Historical_FS'!G50+'03_Historical_FS'!G48-'03_Historical_FS'!G29-'03_Historical_FS'!G30)),"") -> 0.18433207 | H19: =IFERROR(('03_Historical_FS'!H17*(1-$N$4))/AVERAGE(('03_Historical_FS'!G50+'03_Historical_FS'!G48-'03_Historical_FS'!G29-'03_Historical_FS'!G30),('03_Historical_FS'!H50+'03_Historical_FS'!H48-'03_Historical_FS'!H29-'03_Historical_FS'!H30)),"") -> 0.30512083 | I19: =IFERROR((('04_Q1_Historical_FS'!D17*$N$5)*(1-$N$4))/AVERAGE(('03_Historical_FS'!G50+'03_Historical_FS'!G48-'03_Historical_FS'!G29-'03_Historical_FS'!G30),('04_Q1_Historical_FS'!D50+'04_Q1_Historical_FS'!D48-'04_Q1_Historical_FS'!D29-'04_Q1_Historical_FS'!D30)),"") -> 0.29535042 | J19: =IFERROR((('04_Q1_Historical_FS'!E17*$N$5)*(1-$N$4))/AVERAGE(('03_Historical_FS'!H50+'03_Historical_FS'!H48-'03_Historical_FS'!H29-'03_Historical_FS'!H30),('04_Q1_Historical_FS'!E50+'04_Q1_Historical_FS'!E48-'04_Q1_Historical_FS'!E29-'04_Q1_Historical_FS'!E30)),"") -> 0.5114742 | K19: =IFERROR(('04_Q1_Historical_FS'!G17*(1-$N$4))/AVERAGE(('03_Historical_FS'!H50+'03_Historical_FS'!H48-'03_Historical_FS'!H29-'03_Historical_FS'!H30),('04_Q1_Historical_FS'!E50+'04_Q1_Historical_FS'!E48-'04_Q1_Historical_FS'!E29-'04_Q1_Historical_FS'!E30)),"") -> 0.38473755
A20: WORKING CAPITAL
B21: Inventory Days | C21: days | D21: =IFERROR('03_Historical_FS'!D32/'03_Historical_FS'!D8*$N$6,"") -> 111.68037 | E21: =IFERROR(AVERAGE('03_Historical_FS'!D32,'03_Historical_FS'!E32)/'03_Historical_FS'!E8*$N$6,"") -> 97.642744 | F21: =IFERROR(AVERAGE('03_Historical_FS'!E32,'03_Historical_FS'!F32)/'03_Historical_FS'!F8*$N$6,"") -> 90.565287 | G21: =IFERROR(AVERAGE('03_Historical_FS'!F32,'03_Historical_FS'!G32)/'03_Historical_FS'!G8*$N$6,"") -> 75.27546 | H21: =IFERROR(AVERAGE('03_Historical_FS'!G32,'03_Historical_FS'!H32)/'03_Historical_FS'!H8*$N$6,"") -> 72.329495 | I21: =IFERROR(AVERAGE('03_Historical_FS'!G32,'04_Q1_Historical_FS'!D32)/('04_Q1_Historical_FS'!D8*$N$5)*$N$6,"") -> 71.041379 | J21: =IFERROR(AVERAGE('03_Historical_FS'!H32,'04_Q1_Historical_FS'!E32)/('04_Q1_Historical_FS'!E8*$N$5)*$N$6,"") -> 68.114459 | K21: =IFERROR(AVERAGE('03_Historical_FS'!H32,'04_Q1_Historical_FS'!E32)/'04_Q1_Historical_FS'!G8*$N$6,"") -> 75.433632
B22: Receivable Days | C22: days | D22: =IFERROR('03_Historical_FS'!D31/'03_Historical_FS'!D7*$N$6,"") -> 9.3867298 | E22: =IFERROR(AVERAGE('03_Historical_FS'!D31,'03_Historical_FS'!E31)/'03_Historical_FS'!E7*$N$6,"") -> 8.4310058 | F22: =IFERROR(AVERAGE('03_Historical_FS'!E31,'03_Historical_FS'!F31)/'03_Historical_FS'!F7*$N$6,"") -> 12.589978 | G22: =IFERROR(AVERAGE('03_Historical_FS'!F31,'03_Historical_FS'!G31)/'03_Historical_FS'!G7*$N$6,"") -> 18.998027 | H22: =IFERROR(AVERAGE('03_Historical_FS'!G31,'03_Historical_FS'!H31)/'03_Historical_FS'!H7*$N$6,"") -> 22.248027 | I22: =IFERROR(AVERAGE('03_Historical_FS'!G31,'04_Q1_Historical_FS'!D31)/('04_Q1_Historical_FS'!D7*$N$5)*$N$6,"") -> 23.596528 | J22: =IFERROR(AVERAGE('03_Historical_FS'!H31,'04_Q1_Historical_FS'!E31)/('04_Q1_Historical_FS'!E7*$N$5)*$N$6,"") -> 12.082214 | K22: =IFERROR(AVERAGE('03_Historical_FS'!H31,'04_Q1_Historical_FS'!E31)/'04_Q1_Historical_FS'!G7*$N$6,"") -> 13.506067
B23: Payable Days | C23: days | D23: =IFERROR('03_Historical_FS'!D39/'03_Historical_FS'!D8*$N$6,"") -> 46.635955 | E23: =IFERROR(AVERAGE('03_Historical_FS'!D39,'03_Historical_FS'!E39)/'03_Historical_FS'!E8*$N$6,"") -> 37.242252 | F23: =IFERROR(AVERAGE('03_Historical_FS'!E39,'03_Historical_FS'!F39)/'03_Historical_FS'!F8*$N$6,"") -> 31.775584 | G23: =IFERROR(AVERAGE('03_Historical_FS'!F39,'03_Historical_FS'!G39)/'03_Historical_FS'!G8*$N$6,"") -> 29.220489 | H23: =IFERROR(AVERAGE('03_Historical_FS'!G39,'03_Historical_FS'!H39)/'03_Historical_FS'!H8*$N$6,"") -> 32.567772 | I23: =IFERROR(AVERAGE('03_Historical_FS'!G39,'04_Q1_Historical_FS'!D39)/('04_Q1_Historical_FS'!D8*$N$5)*$N$6,"") -> 32.307128 | J23: =IFERROR(AVERAGE('03_Historical_FS'!H39,'04_Q1_Historical_FS'!E39)/('04_Q1_Historical_FS'!E8*$N$5)*$N$6,"") -> 31.043824 | K23: =IFERROR(AVERAGE('03_Historical_FS'!H39,'04_Q1_Historical_FS'!E39)/'04_Q1_Historical_FS'!G8*$N$6,"") -> 34.379608
B24: Cash Conversion Cycle | C24: days | D24: =IFERROR(D21+D22-D23,"") -> 74.431142 | E24: =IFERROR(E21+E22-E23,"") -> 68.831498 | F24: =IFERROR(F21+F22-F23,"") -> 71.379681 | G24: =IFERROR(G21+G22-G23,"") -> 65.052998 | H24: =IFERROR(H21+H22-H23,"") -> 62.00975 | I24: =IFERROR(I21+I22-I23,"") -> 62.330779 | J24: =IFERROR(J21+J22-J23,"") -> 49.152849 | K24: =IFERROR(K21+K22-K23,"") -> 54.560091
A25: LEVERAGE / LIQUIDITY
B26: Current Ratio | C26: x | D26: =IFERROR('03_Historical_FS'!D34/'03_Historical_FS'!D41,"") -> 1.2198029 | E26: =IFERROR('03_Historical_FS'!E34/'03_Historical_FS'!E41,"") -> 1.7145059 | F26: =IFERROR('03_Historical_FS'!F34/'03_Historical_FS'!F41,"") -> 1.6886039 | G26: =IFERROR('03_Historical_FS'!G34/'03_Historical_FS'!G41,"") -> 1.5558208 | H26: =IFERROR('03_Historical_FS'!H34/'03_Historical_FS'!H41,"") -> 1.5206304 | I26: =IFERROR('04_Q1_Historical_FS'!D34/'04_Q1_Historical_FS'!D41,"") -> 1.5891666 | J26: =IFERROR('04_Q1_Historical_FS'!E34/'04_Q1_Historical_FS'!E41,"") -> 1.5986822 | K26: =IFERROR('04_Q1_Historical_FS'!G34/'04_Q1_Historical_FS'!G41,"") -> 1.5986822
B27: Quick Ratio | C27: x | D27: =IFERROR(('03_Historical_FS'!D29+'03_Historical_FS'!D30+'03_Historical_FS'!D31)/'03_Historical_FS'!D41,"") -> 0.50573295 | E27: =IFERROR(('03_Historical_FS'!E29+'03_Historical_FS'!E30+'03_Historical_FS'!E31)/'03_Historical_FS'!E41,"") -> 0.69734244 | F27: =IFERROR(('03_Historical_FS'!F29+'03_Historical_FS'!F30+'03_Historical_FS'!F31)/'03_Historical_FS'!F41,"") -> 0.95762447 | G27: =IFERROR(('03_Historical_FS'!G29+'03_Historical_FS'!G30+'03_Historical_FS'!G31)/'03_Historical_FS'!G41,"") -> 1.0172858 | H27: =IFERROR(('03_Historical_FS'!H29+'03_Historical_FS'!H30+'03_Historical_FS'!H31)/'03_Historical_FS'!H41,"") -> 0.9662697 | I27: =IFERROR(('04_Q1_Historical_FS'!D29+'04_Q1_Historical_FS'!D30+'04_Q1_Historical_FS'!D31)/'04_Q1_Historical_FS'!D41,"") -> 1.044203 | J27: =IFERROR(('04_Q1_Historical_FS'!E29+'04_Q1_Historical_FS'!E30+'04_Q1_Historical_FS'!E31)/'04_Q1_Historical_FS'!E41,"") -> 1.0092508 | K27: =IFERROR(('04_Q1_Historical_FS'!G29+'04_Q1_Historical_FS'!G30+'04_Q1_Historical_FS'!G31)/'04_Q1_Historical_FS'!G41,"") -> 1.0092508
B28: Net Debt / EBITDA | C28: x | D28: =IFERROR('03_Historical_FS'!D51/'03_Historical_FS'!D69,"") -> 0.66786897 | E28: =IFERROR('03_Historical_FS'!E51/'03_Historical_FS'!E69,"") -> 0.14425268 | F28: =IFERROR('03_Historical_FS'!F51/'03_Historical_FS'!F69,"") -> 0.18440389 | G28: =IFERROR('03_Historical_FS'!G51/'03_Historical_FS'!G69,"") -> -0.85026187 | H28: =IFERROR('03_Historical_FS'!H51/'03_Historical_FS'!H69,"") -> -0.84730313 | I28: =IFERROR('04_Q1_Historical_FS'!D51/('04_Q1_Historical_FS'!D69*$N$5),"") -> -0.90099014 | J28: =IFERROR('04_Q1_Historical_FS'!E51/('04_Q1_Historical_FS'!E69*$N$5),"") -> -1.2218586 | K28: =IFERROR('04_Q1_Historical_FS'!G51/'04_Q1_Historical_FS'!G69,"") -> -1.5433713
B29: Interest Coverage | C29: x | D29: =IFERROR('03_Historical_FS'!D17/'03_Historical_FS'!D13,"") -> 9.5868044 | E29: =IFERROR('03_Historical_FS'!E17/'03_Historical_FS'!E13,"") -> 4.8267247 | F29: =IFERROR('03_Historical_FS'!F17/'03_Historical_FS'!F13,"") -> 0.72325418 | G29: =IFERROR('03_Historical_FS'!G17/'03_Historical_FS'!G13,"") -> 4.596271 | H29: =IFERROR('03_Historical_FS'!H17/'03_Historical_FS'!H13,"") -> 5.8912248 | I29: =IFERROR('04_Q1_Historical_FS'!D17/'04_Q1_Historical_FS'!D13,"") -> 6.0106807 | J29: =IFERROR('04_Q1_Historical_FS'!E17/'04_Q1_Historical_FS'!E13,"") -> 8.0566428 | K29: =IFERROR('04_Q1_Historical_FS'!G17/'04_Q1_Historical_FS'!G13,"") -> 6.4420107

Sheet 06_Revenue_Drivers_Hist
A1: MWG - 06_Revenue_Drivers_Hist
A2: Unit: VND bn unless otherwise stated | Blue = hardcoded input from source | Black = formula/calculation ;Green =Linked rawsource
A4: Section | B4: Line Item | C4: Unit | D4: 2021A | E4: 2022A | F4: 2023A | G4: 2024A | H4: 2025A | I4: 3M2026 | J4: 5M2026 | K4: 2021-25 CAGR / Avg | L4: 2026E Anchor
A5: GROUP SUMMARY
B6: Months represented | C6: months | D6: 12 | E6: 12 | F6: 12 | G6: 12 | H6: 12 | I6: 3 | J6: =IFERROR(INDEX('96_Raw_Phase4_Drivers'!$E$4:$G$180,MATCH("latest_months",'96_Raw_Phase4_Drivers'!$B$4:$B$180,0),MATCH("Base",'96_Raw_Phase4_Drivers'!$E$3:$G$3,0)),"") -> 5 | K6: =IFERROR(AVERAGE(D6:H6),"") -> 12 | L6: =12 -> 12
B7: Total Revenue | C7: VND bn | D7: 122958 | E7: 133405 | F7: 118280 | G7: 134341 | H7: 155928 | I7: 46462 | J7: =IFERROR(INDEX('96_Raw_Phase4_Drivers'!$E$4:$G$180,MATCH("group_revenue_5m_2026",'96_Raw_Phase4_Drivers'!$B$4:$B$180,0),MATCH("Base",'96_Raw_Phase4_Drivers'!$E$3:$G$3,0)),"") -> 79159 | K7: =IFERROR(IF(AND(D7>0,H7>0),(H7/D7)^(1/4)-1,""),"") -> 0.061186776 | L7: ='07_Revenue_Drivers'!G8 -> 185000
B8: YoY Revenue Growth | C8: % | E8: =IFERROR(E7/D7-1,"") -> 0.084963971 | F8: =IFERROR(F7/E7-1,"") -> -0.11337656 | G8: =IFERROR(G7/F7-1,"") -> 0.13578796 | H8: =IFERROR(H7/G7-1,"") -> 0.1606881 | J8: =IFERROR(IFERROR(INDEX('96_Raw_Phase4_Drivers'!$E$4:$G$180,MATCH("group_revenue_5m_2026",'96_Raw_Phase4_Drivers'!$B$4:$B$180,0),MATCH("Base",'96_Raw_Phase4_Drivers'!$E$3:$G$3,0)),"")/IFERROR(INDEX('96_Raw_Phase4_Drivers'!$E$4:$G$180,MATCH("group_revenue_5m_2025",'96_Raw_Phase4_Drivers'!$B$4:$B$180,0),MATCH("Base",'96_Raw_Phase4_Drivers'!$E$3:$G$3,0)),"")-1,"") -> 0.29283509 | K8: =IFERROR(AVERAGE(E8:H8),"") -> 0.067015868 | L8: =IFERROR(L7/H7-1,"") -> 0.18644503
B9: NPAT | C9: VND bn | D9: 4901 | E9: 4102 | F9: 168 | G9: 3733 | H9: =IFERROR('90_Raw_IS_vnstock'!C22/1000000000,0) -> 7072.6229 | I9: 2757.6 | K9: =IFERROR(IF(AND(D9>0,H9>0),(H9/D9)^(1/4)-1,""),"") -> 0.096033806 | L9: =IFERROR(INDEX('96_Raw_Phase4_Drivers'!$E$4:$G$180,MATCH("npat_target_2026",'96_Raw_Phase4_Drivers'!$B$4:$B$180,0),MATCH("Base",'96_Raw_Phase4_Drivers'!$E$3:$G$3,0)),"") -> 9200
B10: Online Revenue | C10: VND bn | D10: 14370 | E10: 18930 | F10: 16899 | G10: 9600 | H10: 9200 | I10: 3000 | J10: =IFERROR(INDEX('96_Raw_Phase4_Drivers'!$E$4:$G$180,MATCH("superapp_online_revenue_5m_2026",'96_Raw_Phase4_Drivers'!$B$4:$B$180,0),MATCH("Base",'96_Raw_Phase4_Drivers'!$E$3:$G$3,0)),"") -> 6000 | K10: =IFERROR(IF(AND(D10>0,H10>0),(H10/D10)^(1/4)-1,""),"") -> -0.10549502 | L10: ='07_Revenue_Drivers'!G11 -> 12950
B11: Online Mix | C11: % | D11: =IF(D10="","",IFERROR(D10/D7,"")) -> 0.11686917 | E11: =IF(E10="","",IFERROR(E10/E7,"")) -> 0.14189873 | F11: =IF(F10="","",IFERROR(F10/F7,"")) -> 0.14287284 | G11: =IF(G10="","",IFERROR(G10/G7,"")) -> 0.071459941 | H11: =IF(H10="","",IFERROR(H10/H7,"")) -> 0.05900159 | I11: =IF(I10="","",IFERROR(I10/I7,"")) -> 0.064568895 | J11: =IFERROR(J10/J7,"") -> 0.075796814 | K11: =IFERROR(AVERAGE(D11:H11),"") -> 0.10642046 | L11: =IFERROR(L10/L7,"") -> 0.07
A12: REVENUE BY CHAIN
B13: TGDĐ / TopZone Revenue | C13: VND bn | D13: 31600.206 | E13: 35000 | F13: 28000 | G13: 30000 | H13: 37300 | I13: 10872 | J13: =IFERROR(J7*IFERROR(INDEX('96_Raw_Phase4_Drivers'!$E$4:$G$180,MATCH("tgd_mix_5m_2026",'96_Raw_Phase4_Drivers'!$B$4:$B$180,0),MATCH("Base",'96_Raw_Phase4_Drivers'!$E$3:$G$3,0)),""),"") -> 17810.775 | K13: =IFERROR(IF(AND(D13>0,H13>0),(H13/D13)^(1/4)-1,""),"") -> 0.04232878 | L13: ='07_Revenue_Drivers'!G15 -> 39325.945
B14: ĐMX Revenue | C14: VND bn | D14: 62708.58 | E14: 69000 | F14: 55000 | G14: 59500 | H14: 68400 | I14: 21512 | J14: =IFERROR(J7*IFERROR(INDEX('96_Raw_Phase4_Drivers'!$E$4:$G$180,MATCH("dmx_mix_5m_2026",'96_Raw_Phase4_Drivers'!$B$4:$B$180,0),MATCH("Base",'96_Raw_Phase4_Drivers'!$E$3:$G$3,0)),""),"") -> 36650.617 | K14: =IFERROR(IF(AND(D14>0,H14>0),(H14/D14)^(1/4)-1,""),"") -> 0.021956202 | L14: ='07_Revenue_Drivers'!G16 -> 80924.055
B15: BHX Revenue | C15: VND bn | D15: 28200 | E15: 27000 | F15: 31600 | G15: 41100 | H15: 46900 | I15: 13100 | J15: =IFERROR(J7*IFERROR(INDEX('96_Raw_Phase4_Drivers'!$E$4:$G$180,MATCH("bhx_mix_5m_2026",'96_Raw_Phase4_Drivers'!$B$4:$B$180,0),MATCH("Base",'96_Raw_Phase4_Drivers'!$E$3:$G$3,0)),""),"") -> 23114.428 | K15: =IFERROR(IF(AND(D15>0,H15>0),(H15/D15)^(1/4)-1,""),"") -> 0.13561451 | L15: ='07_Revenue_Drivers'!G17 -> 55500
B16: An Khang Revenue | C16: VND bn | E16: 1500 | F16: 2200 | G16: 2300 | H16: 2200 | K16: =IFERROR(IF(AND(E16>0,H16>0),(H16/E16)^(1/3)-1,""),"") -> 0.13617128 | L16: ='07_Revenue_Drivers'!G18 -> 2860
B17: AVAKids Revenue | C17: VND bn | E17: 600 | F17: 900 | G17: 1200 | H17: 1400 | K17: =IFERROR(IF(AND(E17>0,H17>0),(H17/E17)^(1/3)-1,""),"") -> 0.3263524 | L17: ='07_Revenue_Drivers'!G19 -> 1680
B18: EraBlue Revenue | C18: VND bn
B19: Other / Unallocated / Rounding | C19: VND bn | D19: =IFERROR(D7-SUM(D13:D18),"") -> 449.214 | E19: =IFERROR(E7-SUM(E13:E18),"") -> 305 | F19: =IFERROR(F7-SUM(F13:F18),"") -> 580 | G19: =IFERROR(G7-SUM(G13:G18),"") -> 241 | H19: =IFERROR(H7-SUM(H13:H18),"") -> -272 | I19: =IFERROR(I7-SUM(I13:I18),"") -> 978 | J19: =IFERROR(J7-SUM(J13:J18),"") -> 1583.18 | K19: =IFERROR(AVERAGE(D19:H19),"") -> 260.6428 | L19: ='07_Revenue_Drivers'!G20 -> 4710
B20: Revenue Check: Segment Sum - Total Revenue | C20: VND bn | D20: =IFERROR(SUM(D13:D19)-D7,"") -> 0 | E20: =IFERROR(SUM(E13:E19)-E7,"") -> 0 | F20: =IFERROR(SUM(F13:F19)-F7,"") -> 0 | G20: =IFERROR(SUM(G13:G19)-G7,"") -> 0 | H20: =IFERROR(SUM(H13:H19)-H7,"") -> 0 | I20: =IFERROR(SUM(I13:I19)-I7,"") -> 0 | J20: =IFERROR(SUM(J13:J19)-J7,"") -> 0 | K20: =IFERROR(AVERAGE(D20:H20),"") -> 0 | L20: =IFERROR(SUM(L13:L19)-L7,"") -> 0
A21: REVENUE MIX BY CHAIN
B22: TGDĐ / TopZone Mix | C22: % | D22: =IF(D13="","",IFERROR(D13/D7,"")) -> 0.257 | E22: =IF(E13="","",IFERROR(E13/E7,"")) -> 0.26235898 | F22: =IF(F13="","",IFERROR(F13/F7,"")) -> 0.23672641 | G22: =IF(G13="","",IFERROR(G13/G7,"")) -> 0.22331232 | H22: =IF(H13="","",IFERROR(H13/H7,"")) -> 0.23921297 | I22: =IF(I13="","",IFERROR(I13/I7,"")) -> 0.23399768 | J22: =IF(J13<>"",IFERROR(J13/J$7,""),"") -> 0.225 | K22: =IFERROR(AVERAGE(D22:H22),"") -> 0.24372214 | L22: =IF(L13<>"",IFERROR(L13/L$7,""),"") -> 0.21257267
B23: ĐMX Mix | C23: % | D23: =IF(D14="","",IFERROR(D14/D7,"")) -> 0.51 | E23: =IF(E14="","",IFERROR(E14/E7,"")) -> 0.51722199 | F23: =IF(F14="","",IFERROR(F14/F7,"")) -> 0.46499831 | G23: =IF(G14="","",IFERROR(G14/G7,"")) -> 0.44290276 | H23: =IF(H14="","",IFERROR(H14/H7,"")) -> 0.438664 | I23: =IF(I14="","",IFERROR(I14/I7,"")) -> 0.46300202 | J23: =IF(J14<>"",IFERROR(J14/J$7,""),"") -> 0.463 | K23: =IFERROR(AVERAGE(D23:H23),"") -> 0.47475741 | L23: =IF(L14<>"",IFERROR(L14/L$7,""),"") -> 0.43742733
B24: BHX Mix | C24: % | D24: =IF(D15="","",IFERROR(D15/D7,"")) -> 0.22934661 | E24: =IF(E15="","",IFERROR(E15/E7,"")) -> 0.20239121 | F24: =IF(F15="","",IFERROR(F15/F7,"")) -> 0.26716266 | G24: =IF(G15="","",IFERROR(G15/G7,"")) -> 0.30593787 | H24: =IF(H15="","",IFERROR(H15/H7,"")) -> 0.30077985 | I24: =IF(I15="","",IFERROR(I15/I7,"")) -> 0.28195084 | J24: =IF(J15<>"",IFERROR(J15/J$7,""),"") -> 0.292 | K24: =IFERROR(AVERAGE(D24:H24),"") -> 0.26112364 | L24: =IF(L15<>"",IFERROR(L15/L$7,""),"") -> 0.3
B25: An Khang Mix | C25: % | D25: =IF(D16="","",IFERROR(D16/D7,"")) | E25: =IF(E16="","",IFERROR(E16/E7,"")) -> 0.011243956 | F25: =IF(F16="","",IFERROR(F16/F7,"")) -> 0.018599932 | G25: =IF(G16="","",IFERROR(G16/G7,"")) -> 0.017120611 | H25: =IF(H16="","",IFERROR(H16/H7,"")) -> 0.014109076 | I25: =IF(I16="","",IFERROR(I16/I7,"")) | J25: =IF(J16<>"",IFERROR(J16/J$7,""),"") | K25: =IFERROR(AVERAGE(D25:H25),"") -> 0.015268394 | L25: =IF(L16<>"",IFERROR(L16/L$7,""),"") -> 0.015459459
B26: AVAKids Mix | C26: % | D26: =IF(D17="","",IFERROR(D17/D7,"")) | E26: =IF(E17="","",IFERROR(E17/E7,"")) -> 0.0044975825 | F26: =IF(F17="","",IFERROR(F17/F7,"")) -> 0.0076090632 | G26: =IF(G17="","",IFERROR(G17/G7,"")) -> 0.0089324927 | H26: =IF(H17="","",IFERROR(H17/H7,"")) -> 0.0089785029 | I26: =IF(I17="","",IFERROR(I17/I7,"")) | J26: =IF(J17<>"",IFERROR(J17/J$7,""),"") | K26: =IFERROR(AVERAGE(D26:H26),"") -> 0.0075044103 | L26: =IF(L17<>"",IFERROR(L17/L$7,""),"") -> 0.0090810811
B27: Other / Rounding Mix | C27: % | D27: =IF(D19="","",IFERROR(D19/D7,"")) -> 0.0036533938 | E27: =IF(E19="","",IFERROR(E19/E7,"")) -> 0.0022862711 | F27: =IF(F19="","",IFERROR(F19/F7,"")) -> 0.0049036185 | G27: =IF(G19="","",IFERROR(G19/G7,"")) -> 0.0017939423 | H27: =IF(H19="","",IFERROR(H19/H7,"")) -> -0.0017443948 | I27: =IF(I19="","",IFERROR(I19/I7,"")) -> 0.02104946 | J27: =IF(J18<>"",IFERROR(J18/J$7,""),"") | K27: =IFERROR(AVERAGE(D27:H27),"") -> 0.0021785662 | L27: =IF(L18<>"",IFERROR(L18/L$7,""),"")
A28: ENDING STORE COUNT BY CHAIN
B29: TGDĐ / TopZone Stores | C29: stores | D29: 970 | E29: 1190 | F29: 1078 | G29: 1021 | H29: 1012 | I29: 1014 | J29: =IFERROR(INDEX('96_Raw_Phase4_Drivers'!$E$4:$G$180,MATCH("tgd_stores_5m_2026",'96_Raw_Phase4_Drivers'!$B$4:$B$180,0),MATCH("Base",'96_Raw_Phase4_Drivers'!$E$3:$G$3,0)),"") -> 1012 | K29: =IFERROR(IF(AND(D29>0,H29>0),(H29/D29)^(1/4)-1,""),"") -> 0.010653291 | L29: ='07_Revenue_Drivers'!G32 -> 1012
B30: ĐMX Stores | C30: stores | D30: 1992 | E30: 2284 | F30: 2190 | G30: 2026 | H30: 2008 | I30: 2006 | J30: =IFERROR(INDEX('96_Raw_Phase4_Drivers'!$E$4:$G$180,MATCH("dmx_stores_5m_2026",'96_Raw_Phase4_Drivers'!$B$4:$B$180,0),MATCH("Base",'96_Raw_Phase4_Drivers'!$E$3:$G$3,0)),"") -> 2004 | K30: =IFERROR(IF(AND(D30>0,H30>0),(H30/D30)^(1/4)-1,""),"") -> 0.002002012 | L30: ='07_Revenue_Drivers'!G33 -> 2004
B31: BHX Stores | C31: stores | D31: 2106 | E31: 1728 | F31: 1698 | G31: 1770 | H31: 2559 | I31: 2839 | J31: =IFERROR(INDEX('96_Raw_Phase4_Drivers'!$E$4:$G$180,MATCH("bhx_stores_5m_2026",'96_Raw_Phase4_Drivers'!$B$4:$B$180,0),MATCH("Base",'96_Raw_Phase4_Drivers'!$E$3:$G$3,0)),"") -> 3051 | K31: =IFERROR(IF(AND(D31>0,H31>0),(H31/D31)^(1/4)-1,""),"") -> 0.049912194 | L31: ='07_Revenue_Drivers'!G34 -> 3559
B32: An Khang Stores | C32: stores | D32: 178 | E32: 500 | F32: 527 | G32: 326 | H32: 382 | I32: 409 | J32: =IFERROR(INDEX('96_Raw_Phase4_Drivers'!$E$4:$G$180,MATCH("ak_stores_5m_2026",'96_Raw_Phase4_Drivers'!$B$4:$B$180,0),MATCH("Base",'96_Raw_Phase4_Drivers'!$E$3:$G$3,0)),"") -> 416 | K32: =IFERROR(IF(AND(D32>0,H32>0),(H32/D32)^(1/4)-1,""),"") -> 0.21034963 | L32: ='07_Revenue_Drivers'!G35 -> 482
B33: AVAKids Stores | C33: stores | D33: 0 | E33: 64 | F33: 64 | G33: 62 | H33: 83 | I33: 95 | J33: =IFERROR(INDEX('96_Raw_Phase4_Drivers'!$E$4:$G$180,MATCH("ava_stores_5m_2026",'96_Raw_Phase4_Drivers'!$B$4:$B$180,0),MATCH("Base",'96_Raw_Phase4_Drivers'!$E$3:$G$3,0)),"") -> 95 | K33: =IFERROR(IF(AND(E33>0,H33>0),(H33/E33)^(1/3)-1,""),"") -> 0.090517668 | L33: ='07_Revenue_Drivers'!G36 -> 95
B34: EraBlue Stores | C34: stores | D34: 0 | E34: 5 | F34: 38 | G34: 87 | H34: 181 | I34: 212 | J34: =IFERROR(INDEX('96_Raw_Phase4_Drivers'!$E$4:$G$180,MATCH("erablue_stores_5m_2026",'96_Raw_Phase4_Drivers'!$B$4:$B$180,0),MATCH("Base",'96_Raw_Phase4_Drivers'!$E$3:$G$3,0)),"") -> 245 | K34: =IFERROR(IF(AND(E34>0,H34>0),(H34/E34)^(1/3)-1,""),"") -> 2.3080306 | L34: ='07_Revenue_Drivers'!G37 -> 300
B35: Total Stores - Modeled Chains | C35: stores | D35: =SUM(D29:D34) -> 5246 | E35: =SUM(E29:E34) -> 5771 | F35: =SUM(F29:F34) -> 5595 | G35: =SUM(G29:G34) -> 5292 | H35: =SUM(H29:H34) -> 6225 | I35: =SUM(I29:I34) -> 6575 | J35: =SUM(J29:J34) -> 6823 | K35: =IFERROR(IF(AND(D35>0,H35>0),(H35/D35)^(1/4)-1,""),"") -> 0.043705008 | L35: =SUM(L29:L34) -> 7452
A36: REVENUE / STORE / MONTH
B37: TGDĐ / TopZone Rev/Store/Month | C37: VND bn/store/month | D37: =IF(OR(D13="",D29=0),"",IFERROR(D13/D29/D6,"")) -> 2.7147943 | E37: =IF(OR(E13="",E29=0),"",IFERROR(E13/AVERAGE(D29,E29)/E6,"")) -> 2.7006173 | F37: =IF(OR(F13="",F29=0),"",IFERROR(F13/AVERAGE(E29,F29)/F6,"")) -> 2.0576132 | G37: =IF(OR(G13="",G29=0),"",IFERROR(G13/AVERAGE(F29,G29)/G6,"")) -> 2.3820867 | H37: =IF(OR(H13="",H29=0),"",IFERROR(H13/AVERAGE(G29,H29)/H6,"")) -> 3.0578783 | I37: =IF(OR(I13="",I29=0),"",IFERROR(I13/AVERAGE(H29,I29)/I6,"")) -> 3.5774926 | J37: =IF(OR(J13="",J29=0),"",IFERROR(J13/AVERAGE(H29,J29)/J$6,"")) -> 3.519916 | K37: =IFERROR(IF(AND(D37>0,H37>0),(H37/D37)^(1/4)-1,""),"") -> 0.030198273 | L37: ='07_Revenue_Drivers'!G48 -> 3.2383024
B38: ĐMX Rev/Store/Month | C38: VND bn/store/month | D38: =IF(OR(D14="",D30=0),"",IFERROR(D14/D30/D6,"")) -> 2.6233509 | E38: =IF(OR(E14="",E30=0),"",IFERROR(E14/AVERAGE(D30,E30)/E6,"")) -> 2.6894294 | F38: =IF(OR(F14="",F30=0),"",IFERROR(F14/AVERAGE(E30,F30)/F6,"")) -> 2.048875 | G38: =IF(OR(G14="",G30=0),"",IFERROR(G14/AVERAGE(F30,G30)/G6,"")) -> 2.3521505 | H38: =IF(OR(H14="",H30=0),"",IFERROR(H14/AVERAGE(G30,H30)/H6,"")) -> 2.8259792 | I38: =IF(OR(I14="",I30=0),"",IFERROR(I14/AVERAGE(H30,I30)/I6,"")) -> 3.5728284 | J38: =IF(OR(J14="",J30=0),"",IFERROR(J14/AVERAGE(H30,J30)/J$6,"")) -> 3.6540994 | K38: =IFERROR(IF(AND(D38>0,H38>0),(H38/D38)^(1/4)-1,""),"") -> 0.01877468 | L38: ='07_Revenue_Drivers'!G49 -> 3.3617504
B39: BHX Rev/Store/Month | C39: VND bn/store/month | D39: =IF(OR(D15="",D31=0),"",IFERROR(D15/D31/D6,"")) -> 1.1158594 | E39: =IF(OR(E15="",E31=0),"",IFERROR(E15/AVERAGE(D31,E31)/E6,"")) -> 1.1737089 | F39: =IF(OR(F15="",F31=0),"",IFERROR(F15/AVERAGE(E31,F31)/F6,"")) -> 1.5372641 | G39: =IF(OR(G15="",G31=0),"",IFERROR(G15/AVERAGE(F31,G31)/G6,"")) -> 1.9752018 | H39: =IF(OR(H15="",H31=0),"",IFERROR(H15/AVERAGE(G31,H31)/H6,"")) -> 1.8056518 | I39: =IF(OR(I15="",I31=0),"",IFERROR(I15/AVERAGE(H31,I31)/I6,"")) -> 1.6178832 | J39: =IF(OR(J15="",J31=0),"",IFERROR(J15/AVERAGE(H31,J31)/J$6,"")) -> 1.6480876 | K39: =IFERROR(IF(AND(D39>0,H39>0),(H39/D39)^(1/4)-1,""),"") -> 0.12786242 | L39: ='07_Revenue_Drivers'!G50 -> 1.511932
B40: An Khang Rev/Store/Month | C40: VND bn/store/month | D40: =IF(OR(D16="",D32=0),"",IFERROR(D16/D32/D6,"")) | E40: =IF(OR(E16="",E32=0),"",IFERROR(E16/AVERAGE(D32,E32)/E6,"")) -> 0.36873156 | F40: =IF(OR(F16="",F32=0),"",IFERROR(F16/AVERAGE(E32,F32)/F6,"")) -> 0.35702694 | G40: =IF(OR(G16="",G32=0),"",IFERROR(G16/AVERAGE(F32,G32)/G6,"")) -> 0.44939429 | H40: =IF(OR(H16="",H32=0),"",IFERROR(H16/AVERAGE(G32,H32)/H6,"")) -> 0.51789077 | I40: =IF(OR(I16="",I32=0),"",IFERROR(I16/AVERAGE(H32,I32)/I6,"")) | J40: =IF(OR(J16="",J32=0),"",IFERROR(J16/AVERAGE(H32,J32)/J$6,"")) | K40: =IFERROR(IF(AND(E40>0,H40>0),(H40/E40)^(1/3)-1,""),"") -> 0.11989151 | L40: ='07_Revenue_Drivers'!G51 -> 0.55169753
B41: AVAKids Rev/Store/Month | C41: VND bn/store/month | D41: =IF(OR(D17="",D33=0),"",IFERROR(D17/D33/D6,"")) | E41: =IF(OR(E17="",E33=0),"",IFERROR(E17/AVERAGE(D33,E33)/E6,"")) -> 1.5625 | F41: =IF(OR(F17="",F33=0),"",IFERROR(F17/AVERAGE(E33,F33)/F6,"")) -> 1.171875 | G41: =IF(OR(G17="",G33=0),"",IFERROR(G17/AVERAGE(F33,G33)/G6,"")) -> 1.5873016 | H41: =IF(OR(H17="",H33=0),"",IFERROR(H17/AVERAGE(G33,H33)/H6,"")) -> 1.6091954 | I41: =IF(OR(I17="",I33=0),"",IFERROR(I17/AVERAGE(H33,I33)/I6,"")) | J41: =IF(OR(J17="",J33=0),"",IFERROR(J17/AVERAGE(H33,J33)/J$6,"")) | K41: =IFERROR(IF(AND(E41>0,H41>0),(H41/E41)^(1/3)-1,""),"") -> 0.0098640661 | L41: ='07_Revenue_Drivers'!G52 -> 1.5730337
A42: ONLINE & KEY OPERATING METRICS
B43: TGDĐ/ĐMX Online Revenue | C43: VND bn | D43: 13405 | E43: 18000 | F43: 16000 | G43: 8700 | H43: 6100 | I43: 2000 | J43: =IFERROR(INDEX('96_Raw_Phase4_Drivers'!$E$4:$G$180,MATCH("superapp_online_revenue_5m_2026",'96_Raw_Phase4_Drivers'!$B$4:$B$180,0),MATCH("Base",'96_Raw_Phase4_Drivers'!$E$3:$G$3,0)),"") -> 6000 | K43: =IFERROR(IF(AND(D43>0,H43>0),(H43/D43)^(1/4)-1,""),"") -> -0.17867365 | L43: ='07_Revenue_Drivers'!G11 -> 12950
B44: BHX Online Revenue | C44: VND bn | D44: 1000 | E44: 900 | F44: 900 | G44: 925 | H44: 2300 | I44: 1000 | K44: =IFERROR(IF(AND(D44>0,H44>0),(H44/D44)^(1/4)-1,""),"") -> 0.23149303
B45: AVAKids Online Revenue | C45: VND bn | F45: 270 | G45: 600 | H45: 700 | K45: =IFERROR(IF(AND(F45>0,H45>0),(H45/F45)^(1/2)-1,""),"") -> 0.61015297
B46: TGDĐ/ĐMX Online Mix | C46: % | D46: =IF(D43="","",IFERROR(D43/(D13+D14),"")) -> 0.14213946 | E46: =IF(E43="","",IFERROR(E43/(E13+E14),"")) -> 0.17307692 | F46: =IF(F43="","",IFERROR(F43/(F13+F14),"")) -> 0.19277108 | G46: =IF(G43="","",IFERROR(G43/(G13+G14),"")) -> 0.097206704 | H46: =IF(H43="","",IFERROR(H43/(H13+H14),"")) -> 0.057710501 | I46: =IF(I43<>"",IFERROR(I43/(I13+I14),""),"") -> 0.061758893 | J46: =IF(J43<>"",IFERROR(J43/(J13+J14),""),"") -> 0.11016979 | K46: =IFERROR(AVERAGE(D46:H46),"") -> 0.13258093 | L46: =IF(L43<>"",IFERROR(L43/(L13+L14),""),"") -> 0.10769231
B47: BHX Online Mix | C47: % | D47: =IF(D44="","",IFERROR(D44/D15,"")) -> 0.035460993 | E47: =IF(E44="","",IFERROR(E44/E15,"")) -> 0.033333333 | F47: =IF(F44="","",IFERROR(F44/F15,"")) -> 0.028481013 | G47: =IF(G44="","",IFERROR(G44/G15,"")) -> 0.022506083 | H47: =IF(H44="","",IFERROR(H44/H15,"")) -> 0.049040512 | I47: =IF(I44<>"",IFERROR(I44/I15,""),"") -> 0.076335878 | K47: =IFERROR(AVERAGE(D47:H47),"") -> 0.033764387
B48: AVAKids Online Mix | C48: % | D48: =IF(D45="","",IFERROR(D45/D17,"")) | E48: =IF(E45="","",IFERROR(E45/E17,"")) | F48: =IF(F45="","",IFERROR(F45/F17,"")) -> 0.3 | G48: =IF(G45="","",IFERROR(G45/G17,"")) -> 0.5 | H48: =IF(H45="","",IFERROR(H45/H17,"")) -> 0.5 | I48: =IF(I45="","",IFERROR(I45/I17,"")) | K48: =IFERROR(AVERAGE(D48:H48),"") -> 0.43333333
B49: DMX Investment / Core ICT+CE Revenue | C49: VND bn | I49: 32400 | J49: =IFERROR(INDEX('96_Raw_Phase4_Drivers'!$E$4:$G$180,MATCH("core_revenue_5m_2026",'96_Raw_Phase4_Drivers'!$B$4:$B$180,0),MATCH("Base",'96_Raw_Phase4_Drivers'!$E$3:$G$3,0)),"") -> 54500 | L49: ='07_Revenue_Drivers'!G55 -> 0
B50: Core ICT+CE SSSG / Same-store growth | C50: % | G50: 0.1 | H50: 0.2 | I50: 0.34 | J50: =IFERROR(INDEX('96_Raw_Phase4_Drivers'!$E$4:$G$180,MATCH("core_sssg_5m_2026",'96_Raw_Phase4_Drivers'!$B$4:$B$180,0),MATCH("Base",'96_Raw_Phase4_Drivers'!$E$3:$G$3,0)),"") -> 0.33 | K50: =IFERROR(AVERAGE(G50:H50),"") -> 0.15 | L50: ='07_Revenue_Drivers'!G56 -> 0
B51: BHX New Stores in Period | C51: stores | H51: 789 | I51: 280 | J51: =IFERROR(INDEX('96_Raw_Phase4_Drivers'!$E$4:$G$180,MATCH("bhx_new_stores_5m_2026",'96_Raw_Phase4_Drivers'!$B$4:$B$180,0),MATCH("Base",'96_Raw_Phase4_Drivers'!$E$3:$G$3,0)),"") -> 532 | K51: =IFERROR(AVERAGE(D51:H51),"") -> 789 | L51: ='07_Revenue_Drivers'!G57 -> 0
B52: EraBlue Stores Opened in Period | C52: stores | E52: 5 | F52: 33 | G52: 49 | H52: 94 | I52: 31 | J52: =IFERROR(INDEX('96_Raw_Phase4_Drivers'!$E$4:$G$180,MATCH("erablue_new_stores_5m_2026",'96_Raw_Phase4_Drivers'!$B$4:$B$180,0),MATCH("Base",'96_Raw_Phase4_Drivers'!$E$3:$G$3,0)),"") -> 64 | K52: =IFERROR(AVERAGE(E52:H52),"") -> 45.25 | L52: ='07_Revenue_Drivers'!G61 -> 0
B53: EraBlue Revenue (IDR bn) | C53: IDR bn | J53: =IFERROR(INDEX('96_Raw_Phase4_Drivers'!$E$4:$G$180,MATCH("erablue_revenue_idr_5m_2026",'96_Raw_Phase4_Drivers'!$B$4:$B$180,0),MATCH("Base",'96_Raw_Phase4_Drivers'!$E$3:$G$3,0)),"") -> 1560

Sheet 07_Revenue_Drivers
A1: MWG - Revenue Driver Forecast
A2: Forecast period: 2026E-2030E | Unit: VND bn unless stated | Green = linked history/raw source | Blue = scenario selector/source inputs | Black = formulas. 2026E Base is calibrated to company guidance; 2027E+ uses store count x revenue/store/month drivers.
B3: Selected Scenario | D3: Base
A5: Section | B5: Line Item | C5: Unit | D5: 2025A | E5: 3M2026A | F5: 5M2026A | G5: 2026E | H5: 2027E | I5: 2028E | J5: 2029E | K5: 2030E
A6: GROUP SUMMARY
A7: GROUP SUMMARY | B7: Months represented | C7: months | D7: ='06_Revenue_Drivers_Hist'!H6 -> 12 | E7: ='06_Revenue_Drivers_Hist'!I6 -> 3 | F7: =IFERROR(INDEX('96_Raw_Phase4_Drivers'!$E$4:$G$180,MATCH("latest_months",'96_Raw_Phase4_Drivers'!$B$4:$B$180,0),MATCH($D$3,'96_Raw_Phase4_Drivers'!$E$3:$G$3,0)),"") -> 5 | G7: =12 -> 12 | H7: =12 -> 12 | I7: =12 -> 12 | J7: =12 -> 12 | K7: =12 -> 12
A8: GROUP SUMMARY | B8: Total Revenue | C8: VND bn | D8: ='06_Revenue_Drivers_Hist'!H7 -> 155928 | E8: ='06_Revenue_Drivers_Hist'!I7 -> 46462 | F8: =IFERROR(INDEX('96_Raw_Phase4_Drivers'!$E$4:$G$180,MATCH("group_revenue_5m_2026",'96_Raw_Phase4_Drivers'!$B$4:$B$180,0),MATCH($D$3,'96_Raw_Phase4_Drivers'!$E$3:$G$3,0)),"") -> 79159 | G8: =IFERROR(INDEX('96_Raw_Phase4_Drivers'!$E$4:$G$180,MATCH("group_revenue_target_2026",'96_Raw_Phase4_Drivers'!$B$4:$B$180,0),MATCH($D$3,'96_Raw_Phase4_Drivers'!$E$3:$G$3,0)),"") -> 185000 | H8: =SUM(H15:H20) -> 210702.27 | I8: =SUM(I15:I20) -> 232016.74 | J8: =SUM(J15:J20) -> 250797.07 | K8: =SUM(K15:K20) -> 267230.44
A9: GROUP SUMMARY | B9: YoY Revenue Growth | C9: % | D9: =IFERROR(D8/'06_Revenue_Drivers_Hist'!G7-1,"") -> 0.1606881 | F9: =IFERROR(F8/INDEX('96_Raw_Phase4_Drivers'!$E$4:$G$180,MATCH("group_revenue_5m_2025",'96_Raw_Phase4_Drivers'!$B$4:$B$180,0),MATCH($D$3,'96_Raw_Phase4_Drivers'!$E$3:$G$3,0))-1,"") -> 0.29283509 | G9: =IFERROR(G8/D8-1,"") -> 0.18644503 | H9: =IFERROR(H8/G8-1,"") -> 0.13893119 | I9: =IFERROR(I8/H8-1,"") -> 0.10115916 | J9: =IFERROR(J8/I8-1,"") -> 0.08094389 | K9: =IFERROR(K8/J8-1,"") -> 0.065524566
A10: GROUP SUMMARY | B10: 2026 target completion | C10: % | F10: =IFERROR(F8/INDEX('96_Raw_Phase4_Drivers'!$E$4:$G$180,MATCH("group_revenue_target_2026",'96_Raw_Phase4_Drivers'!$B$4:$B$180,0),MATCH($D$3,'96_Raw_Phase4_Drivers'!$E$3:$G$3,0)),"") -> 0.42788649 | G10: =1 -> 1
A11: GROUP SUMMARY | B11: Online / Super App Revenue | C11: VND bn | D11: ='06_Revenue_Drivers_Hist'!H10 -> 9200 | E11: ='06_Revenue_Drivers_Hist'!I10 -> 3000 | F11: =IFERROR(INDEX('96_Raw_Phase4_Drivers'!$E$4:$G$180,MATCH("superapp_online_revenue_5m_2026",'96_Raw_Phase4_Drivers'!$B$4:$B$180,0),MATCH($D$3,'96_Raw_Phase4_Drivers'!$E$3:$G$3,0)),"") -> 6000 | G11: =G8*INDEX('96_Raw_Phase4_Drivers'!$E$4:$G$180,MATCH("online_mix_2026",'96_Raw_Phase4_Drivers'!$B$4:$B$180,0),MATCH($D$3,'96_Raw_Phase4_Drivers'!$E$3:$G$3,0)) -> 12950 | H11: =H8*INDEX('96_Raw_Phase4_Drivers'!$E$4:$G$180,MATCH("online_mix_2027",'96_Raw_Phase4_Drivers'!$B$4:$B$180,0),MATCH($D$3,'96_Raw_Phase4_Drivers'!$E$3:$G$3,0)) -> 15802.67 | I11: =I8*INDEX('96_Raw_Phase4_Drivers'!$E$4:$G$180,MATCH("online_mix_2028",'96_Raw_Phase4_Drivers'!$B$4:$B$180,0),MATCH($D$3,'96_Raw_Phase4_Drivers'!$E$3:$G$3,0)) -> 18561.339 | J11: =J8*INDEX('96_Raw_Phase4_Drivers'!$E$4:$G$180,MATCH("online_mix_2029",'96_Raw_Phase4_Drivers'!$B$4:$B$180,0),MATCH($D$3,'96_Raw_Phase4_Drivers'!$E$3:$G$3,0)) -> 21317.751 | K11: =K8*INDEX('96_Raw_Phase4_Drivers'!$E$4:$G$180,MATCH("online_mix_2030",'96_Raw_Phase4_Drivers'!$B$4:$B$180,0),MATCH($D$3,'96_Raw_Phase4_Drivers'!$E$3:$G$3,0)) -> 24050.74
A12: GROUP SUMMARY | B12: Online / Super App Mix | C12: % | D12: =IFERROR(D11/D8,"") -> 0.05900159 | E12: =IFERROR(E11/E8,"") -> 0.064568895 | F12: =IFERROR(F11/F8,"") -> 0.075796814 | G12: =IFERROR(G11/G8,"") -> 0.07 | H12: =IFERROR(H11/H8,"") -> 0.075 | I12: =IFERROR(I11/I8,"") -> 0.08 | J12: =IFERROR(J11/J8,"") -> 0.085 | K12: =IFERROR(K11/K8,"") -> 0.09
A14: REVENUE BY CHAIN
A15: REVENUE BY CHAIN | B15: TGDD / TopZone Revenue | C15: VND bn | D15: ='06_Revenue_Drivers_Hist'!H13 -> 37300 | E15: ='06_Revenue_Drivers_Hist'!I13 -> 10872 | F15: =F8*INDEX('96_Raw_Phase4_Drivers'!$E$4:$G$180,MATCH("tgd_mix_5m_2026",'96_Raw_Phase4_Drivers'!$B$4:$B$180,0),MATCH($D$3,'96_Raw_Phase4_Drivers'!$E$3:$G$3,0)) -> 17810.775 | G15: =(G8*INDEX('96_Raw_Phase4_Drivers'!$E$4:$G$180,MATCH("core_revenue_mix_2026",'96_Raw_Phase4_Drivers'!$B$4:$B$180,0),MATCH($D$3,'96_Raw_Phase4_Drivers'!$E$3:$G$3,0)))*INDEX('96_Raw_Phase4_Drivers'!$E$4:$G$180,MATCH("tgd_mix_5m_2026",'96_Raw_Phase4_Drivers'!$B$4:$B$180,0),MATCH($D$3,'96_Raw_Phase4_Drivers'!$E$3:$G$3,0))/(INDEX('96_Raw_Phase4_Drivers'!$E$4:$G$180,MATCH("tgd_mix_5m_2026",'96_Raw_Phase4_Drivers'!$B$4:$B$180,0),MATCH($D$3,'96_Raw_Phase4_Drivers'!$E$3:$G$3,0))+INDEX('96_Raw_Phase4_Drivers'!$E$4:$G$180,MATCH("dmx_mix_5m_2026",'96_Raw_Phase4_Drivers'!$B$4:$B$180,0),MATCH($D$3,'96_Raw_Phase4_Drivers'!$E$3:$G$3,0))) -> 39325.945 | H15: =H41*H48*12 -> 40898.983 | I15: =I41*I48*12 -> 42125.952 | J15: =J41*J48*12 -> 43389.731 | K15: =K41*K48*12 -> 44474.474
A16: REVENUE BY CHAIN | B16: DMX Revenue | C16: VND bn | D16: ='06_Revenue_Drivers_Hist'!H14 -> 68400 | E16: ='06_Revenue_Drivers_Hist'!I14 -> 21512 | F16: =F8*INDEX('96_Raw_Phase4_Drivers'!$E$4:$G$180,MATCH("dmx_mix_5m_2026",'96_Raw_Phase4_Drivers'!$B$4:$B$180,0),MATCH($D$3,'96_Raw_Phase4_Drivers'!$E$3:$G$3,0)) -> 36650.617 | G16: =(G8*INDEX('96_Raw_Phase4_Drivers'!$E$4:$G$180,MATCH("core_revenue_mix_2026",'96_Raw_Phase4_Drivers'!$B$4:$B$180,0),MATCH($D$3,'96_Raw_Phase4_Drivers'!$E$3:$G$3,0)))*INDEX('96_Raw_Phase4_Drivers'!$E$4:$G$180,MATCH("dmx_mix_5m_2026",'96_Raw_Phase4_Drivers'!$B$4:$B$180,0),MATCH($D$3,'96_Raw_Phase4_Drivers'!$E$3:$G$3,0))/(INDEX('96_Raw_Phase4_Drivers'!$E$4:$G$180,MATCH("tgd_mix_5m_2026",'96_Raw_Phase4_Drivers'!$B$4:$B$180,0),MATCH($D$3,'96_Raw_Phase4_Drivers'!$E$3:$G$3,0))+INDEX('96_Raw_Phase4_Drivers'!$E$4:$G$180,MATCH("dmx_mix_5m_2026",'96_Raw_Phase4_Drivers'!$B$4:$B$180,0),MATCH($D$3,'96_Raw_Phase4_Drivers'!$E$3:$G$3,0))) -> 80924.055 | H16: =H42*H49*12 -> 85693.976 | I16: =I42*I49*12 -> 89978.674 | J16: =J42*J49*12 -> 93577.821 | K16: =K42*K49*12 -> 96385.156
A17: REVENUE BY CHAIN | B17: BHX Revenue | C17: VND bn | D17: ='06_Revenue_Drivers_Hist'!H15 -> 46900 | E17: ='06_Revenue_Drivers_Hist'!I15 -> 13100 | F17: =F8*INDEX('96_Raw_Phase4_Drivers'!$E$4:$G$180,MATCH("bhx_mix_5m_2026",'96_Raw_Phase4_Drivers'!$B$4:$B$180,0),MATCH($D$3,'96_Raw_Phase4_Drivers'!$E$3:$G$3,0)) -> 23114.428 | G17: =G8*INDEX('96_Raw_Phase4_Drivers'!$E$4:$G$180,MATCH("bhx_revenue_mix_2026",'96_Raw_Phase4_Drivers'!$B$4:$B$180,0),MATCH($D$3,'96_Raw_Phase4_Drivers'!$E$3:$G$3,0)) -> 55500 | H17: =H43*H50*12 -> 73515.275 | I17: =I43*I50*12 -> 88192.612 | J17: =J43*J50*12 -> 101081.65 | K17: =K43*K50*12 -> 112697.2
A18: REVENUE BY CHAIN | B18: An Khang Revenue | C18: VND bn | D18: ='06_Revenue_Drivers_Hist'!H16 -> 2200 | F18: =D18/12*F7*(1+INDEX('96_Raw_Phase4_Drivers'!$E$4:$G$180,MATCH("ak_yoy_5m_2026",'96_Raw_Phase4_Drivers'!$B$4:$B$180,0),MATCH($D$3,'96_Raw_Phase4_Drivers'!$E$3:$G$3,0))) -> 1109.1667 | G18: =D18*(1+INDEX('96_Raw_Phase4_Drivers'!$E$4:$G$180,MATCH("ak_revenue_growth_2026",'96_Raw_Phase4_Drivers'!$B$4:$B$180,0),MATCH($D$3,'96_Raw_Phase4_Drivers'!$E$3:$G$3,0))) -> 2860 | H18: =H44*H51*12 -> 3525.2148 | I18: =I44*I51*12 -> 4060.056 | J18: =J44*J51*12 -> 4513.7511 | K18: =K44*K51*12 -> 4915.0472
A19: REVENUE BY CHAIN | B19: AVAKids Revenue | C19: VND bn | D19: ='06_Revenue_Drivers_Hist'!H17 -> 1400 | F19: =D19/12*F7*(1+INDEX('96_Raw_Phase4_Drivers'!$E$4:$G$180,MATCH("ava_yoy_5m_2026",'96_Raw_Phase4_Drivers'!$B$4:$B$180,0),MATCH($D$3,'96_Raw_Phase4_Drivers'!$E$3:$G$3,0))) -> 700 | G19: =D19*(1+INDEX('96_Raw_Phase4_Drivers'!$E$4:$G$180,MATCH("ava_revenue_growth_2026",'96_Raw_Phase4_Drivers'!$B$4:$B$180,0),MATCH($D$3,'96_Raw_Phase4_Drivers'!$E$3:$G$3,0))) -> 1680 | H19: =H45*H52*12 -> 1982.0225 | I19: =I45*I52*12 -> 2267.4337 | J19: =J45*J52*12 -> 2572.5066 | K19: =K45*K52*12 -> 2870.4886
A20: REVENUE BY CHAIN | B20: Other / Unallocated / Rounding | C20: VND bn | D20: ='06_Revenue_Drivers_Hist'!H19 -> -272 | E20: ='06_Revenue_Drivers_Hist'!I19 -> 978 | F20: =F8-SUM(F15:F19) -> -225.98667 | G20: =G8-SUM(G15:G19) -> 4710 | H20: =G20*(1+INDEX('96_Raw_Phase4_Drivers'!$E$4:$G$180,MATCH("other_growth_2027",'96_Raw_Phase4_Drivers'!$B$4:$B$180,0),MATCH($D$3,'96_Raw_Phase4_Drivers'!$E$3:$G$3,0))) -> 5086.8 | I20: =H20*(1+INDEX('96_Raw_Phase4_Drivers'!$E$4:$G$180,MATCH("other_growth_2028",'96_Raw_Phase4_Drivers'!$B$4:$B$180,0),MATCH($D$3,'96_Raw_Phase4_Drivers'!$E$3:$G$3,0))) -> 5392.008 | J20: =I20*(1+INDEX('96_Raw_Phase4_Drivers'!$E$4:$G$180,MATCH("other_growth_2029",'96_Raw_Phase4_Drivers'!$B$4:$B$180,0),MATCH($D$3,'96_Raw_Phase4_Drivers'!$E$3:$G$3,0))) -> 5661.6084 | K20: =J20*(1+INDEX('96_Raw_Phase4_Drivers'!$E$4:$G$180,MATCH("other_growth_2030",'96_Raw_Phase4_Drivers'!$B$4:$B$180,0),MATCH($D$3,'96_Raw_Phase4_Drivers'!$E$3:$G$3,0))) -> 5888.0727
A21: REVENUE BY CHAIN | B21: Revenue Check: Segment Sum - Total Revenue | C21: VND bn | D21: =SUM(D15:D20)-D8 -> 0 | E21: =SUM(E15:E20)-E8 -> 0 | F21: =SUM(F15:F20)-F8 -> 0 | G21: =SUM(G15:G20)-G8 -> 0 | H21: =SUM(H15:H20)-H8 -> 0 | I21: =SUM(I15:I20)-I8 -> 0 | J21: =SUM(J15:J20)-J8 -> 0 | K21: =SUM(K15:K20)-K8 -> 0
A23: REVENUE GROWTH BY CHAIN
A24: REVENUE GROWTH BY CHAIN | B24: TGDD / TopZone Growth | C24: % | D24: =IFERROR(D15/'06_Revenue_Drivers_Hist'!G13-1,"") -> 0.24333333 | F24: =IFERROR(F15/(D15/12*F$7)-1,"") -> 0.14600161 | G24: =IFERROR(G15/D15-1,"") -> 0.054314873 | H24: =IFERROR(H15/G15-1,"") -> 0.04 | I24: =IFERROR(I15/H15-1,"") -> 0.03 | J24: =IFERROR(J15/I15-1,"") -> 0.03 | K24: =IFERROR(K15/J15-1,"") -> 0.025
A25: REVENUE GROWTH BY CHAIN | B25: DMX Growth | C25: % | D25: =IFERROR(D16/'06_Revenue_Drivers_Hist'!G14-1,"") -> 0.14957983 | F25: =IFERROR(F16/(D16/12*F$7)-1,"") -> 0.28598656 | G25: =IFERROR(G16/D16-1,"") -> 0.18310022 | H25: =IFERROR(H16/G16-1,"") -> 0.05894317 | I25: =IFERROR(I16/H16-1,"") -> 0.05 | J25: =IFERROR(J16/I16-1,"") -> 0.04 | K25: =IFERROR(K16/J16-1,"") -> 0.03
A26: REVENUE GROWTH BY CHAIN | B26: BHX Growth | C26: % | D26: =IFERROR(D17/'06_Revenue_Drivers_Hist'!G15-1,"") -> 0.14111922 | F26: =IFERROR(F17/(D17/12*F$7)-1,"") -> 0.18282787 | G26: =IFERROR(G17/D17-1,"") -> 0.18336887 | H26: =IFERROR(H17/G17-1,"") -> 0.32459954 | I26: =IFERROR(I17/H17-1,"") -> 0.19965017 | J26: =IFERROR(J17/I17-1,"") -> 0.14614652 | K26: =IFERROR(K17/J17-1,"") -> 0.11491253
A27: REVENUE GROWTH BY CHAIN | B27: An Khang Growth | C27: % | D27: =IFERROR(D18/'06_Revenue_Drivers_Hist'!G16-1,"") -> -0.043478261 | F27: =IFERROR(F18/(D18/12*F$7)-1,"") -> 0.21 | G27: =IFERROR(G18/D18-1,"") -> 0.3 | H27: =IFERROR(H18/G18-1,"") -> 0.23259259 | I27: =IFERROR(I18/H18-1,"") -> 0.15171875 | J27: =IFERROR(J18/I18-1,"") -> 0.11174603 | K27: =IFERROR(K18/J18-1,"") -> 0.088905229
A28: REVENUE GROWTH BY CHAIN | B28: AVAKids Growth | C28: % | D28: =IFERROR(D19/'06_Revenue_Drivers_Hist'!G17-1,"") -> 0.16666667 | F28: =IFERROR(F19/(D19/12*F$7)-1,"") -> 0.2 | G28: =IFERROR(G19/D19-1,"") -> 0.2 | H28: =IFERROR(H19/G19-1,"") -> 0.17977528 | I28: =IFERROR(I19/H19-1,"") -> 0.144 | J28: =IFERROR(J19/I19-1,"") -> 0.13454545 | K28: =IFERROR(K19/J19-1,"") -> 0.11583333
A29: REVENUE GROWTH BY CHAIN | B29: Other Growth | C29: % | H29: =IFERROR(H20/G20-1,"") -> 0.08 | I29: =IFERROR(I20/H20-1,"") -> 0.06 | J29: =IFERROR(J20/I20-1,"") -> 0.05 | K29: =IFERROR(K20/J20-1,"") -> 0.04
A31: ENDING STORE COUNT BY CHAIN
A32: ENDING STORE COUNT BY CHAIN | B32: TGDD / TopZone Stores | C32: stores | D32: ='06_Revenue_Drivers_Hist'!H29 -> 1012 | E32: ='06_Revenue_Drivers_Hist'!I29 -> 1014 | F32: =IFERROR(INDEX('96_Raw_Phase4_Drivers'!$E$4:$G$180,MATCH("tgd_stores_5m_2026",'96_Raw_Phase4_Drivers'!$B$4:$B$180,0),MATCH($D$3,'96_Raw_Phase4_Drivers'!$E$3:$G$3,0)),"") -> 1012 | G32: =F32 -> 1012 | H32: =G32+INDEX('96_Raw_Phase4_Drivers'!$E$4:$G$180,MATCH("tgd_store_additions_2027",'96_Raw_Phase4_Drivers'!$B$4:$B$180,0),MATCH($D$3,'96_Raw_Phase4_Drivers'!$E$3:$G$3,0)) -> 1012 | I32: =H32+INDEX('96_Raw_Phase4_Drivers'!$E$4:$G$180,MATCH("tgd_store_additions_2028",'96_Raw_Phase4_Drivers'!$B$4:$B$180,0),MATCH($D$3,'96_Raw_Phase4_Drivers'!$E$3:$G$3,0)) -> 1012 | J32: =I32+INDEX('96_Raw_Phase4_Drivers'!$E$4:$G$180,MATCH("tgd_store_additions_2029",'96_Raw_Phase4_Drivers'!$B$4:$B$180,0),MATCH($D$3,'96_Raw_Phase4_Drivers'!$E$3:$G$3,0)) -> 1012 | K32: =J32+INDEX('96_Raw_Phase4_Drivers'!$E$4:$G$180,MATCH("tgd_store_additions_2030",'96_Raw_Phase4_Drivers'!$B$4:$B$180,0),MATCH($D$3,'96_Raw_Phase4_Drivers'!$E$3:$G$3,0)) -> 1012
A33: ENDING STORE COUNT BY CHAIN | B33: DMX Stores | C33: stores | D33: ='06_Revenue_Drivers_Hist'!H30 -> 2008 | E33: ='06_Revenue_Drivers_Hist'!I30 -> 2006 | F33: =IFERROR(INDEX('96_Raw_Phase4_Drivers'!$E$4:$G$180,MATCH("dmx_stores_5m_2026",'96_Raw_Phase4_Drivers'!$B$4:$B$180,0),MATCH($D$3,'96_Raw_Phase4_Drivers'!$E$3:$G$3,0)),"") -> 2004 | G33: =F33 -> 2004 | H33: =G33+INDEX('96_Raw_Phase4_Drivers'!$E$4:$G$180,MATCH("dmx_store_additions_2027",'96_Raw_Phase4_Drivers'!$B$4:$B$180,0),MATCH($D$3,'96_Raw_Phase4_Drivers'!$E$3:$G$3,0)) -> 2004 | I33: =H33+INDEX('96_Raw_Phase4_Drivers'!$E$4:$G$180,MATCH("dmx_store_additions_2028",'96_Raw_Phase4_Drivers'!$B$4:$B$180,0),MATCH($D$3,'96_Raw_Phase4_Drivers'!$E$3:$G$3,0)) -> 2004 | J33: =I33+INDEX('96_Raw_Phase4_Drivers'!$E$4:$G$180,MATCH("dmx_store_additions_2029",'96_Raw_Phase4_Drivers'!$B$4:$B$180,0),MATCH($D$3,'96_Raw_Phase4_Drivers'!$E$3:$G$3,0)) -> 2004 | K33: =J33+INDEX('96_Raw_Phase4_Drivers'!$E$4:$G$180,MATCH("dmx_store_additions_2030",'96_Raw_Phase4_Drivers'!$B$4:$B$180,0),MATCH($D$3,'96_Raw_Phase4_Drivers'!$E$3:$G$3,0)) -> 2004
A34: ENDING STORE COUNT BY CHAIN | B34: BHX Stores | C34: stores | D34: ='06_Revenue_Drivers_Hist'!H31 -> 2559 | E34: ='06_Revenue_Drivers_Hist'!I31 -> 2839 | F34: =IFERROR(INDEX('96_Raw_Phase4_Drivers'!$E$4:$G$180,MATCH("bhx_stores_5m_2026",'96_Raw_Phase4_Drivers'!$B$4:$B$180,0),MATCH($D$3,'96_Raw_Phase4_Drivers'!$E$3:$G$3,0)),"") -> 3051 | G34: =MAX(F34,D34+INDEX('96_Raw_Phase4_Drivers'!$E$4:$G$180,MATCH("bhx_new_stores_2026",'96_Raw_Phase4_Drivers'!$B$4:$B$180,0),MATCH($D$3,'96_Raw_Phase4_Drivers'!$E$3:$G$3,0))) -> 3559 | H34: =G34+INDEX('96_Raw_Phase4_Drivers'!$E$4:$G$180,MATCH("bhx_store_additions_2027",'96_Raw_Phase4_Drivers'!$B$4:$B$180,0),MATCH($D$3,'96_Raw_Phase4_Drivers'!$E$3:$G$3,0)) -> 4159 | I34: =H34+INDEX('96_Raw_Phase4_Drivers'!$E$4:$G$180,MATCH("bhx_store_additions_2028",'96_Raw_Phase4_Drivers'!$B$4:$B$180,0),MATCH($D$3,'96_Raw_Phase4_Drivers'!$E$3:$G$3,0)) -> 4659 | J34: =I34+INDEX('96_Raw_Phase4_Drivers'!$E$4:$G$180,MATCH("bhx_store_additions_2029",'96_Raw_Phase4_Drivers'!$B$4:$B$180,0),MATCH($D$3,'96_Raw_Phase4_Drivers'!$E$3:$G$3,0)) -> 5059 | K34: =J34+INDEX('96_Raw_Phase4_Drivers'!$E$4:$G$180,MATCH("bhx_store_additions_2030",'96_Raw_Phase4_Drivers'!$B$4:$B$180,0),MATCH($D$3,'96_Raw_Phase4_Drivers'!$E$3:$G$3,0)) -> 5359
A35: ENDING STORE COUNT BY CHAIN | B35: An Khang Stores | C35: stores | D35: ='06_Revenue_Drivers_Hist'!H32 -> 382 | E35: ='06_Revenue_Drivers_Hist'!I32 -> 409 | F35: =IFERROR(INDEX('96_Raw_Phase4_Drivers'!$E$4:$G$180,MATCH("ak_stores_5m_2026",'96_Raw_Phase4_Drivers'!$B$4:$B$180,0),MATCH($D$3,'96_Raw_Phase4_Drivers'!$E$3:$G$3,0)),"") -> 416 | G35: =MAX(F35,D35+INDEX('96_Raw_Phase4_Drivers'!$E$4:$G$180,MATCH("ak_new_stores_2026",'96_Raw_Phase4_Drivers'!$B$4:$B$180,0),MATCH($D$3,'96_Raw_Phase4_Drivers'!$E$3:$G$3,0))) -> 482 | H35: =G35+INDEX('96_Raw_Phase4_Drivers'!$E$4:$G$180,MATCH("ak_store_additions_2027",'96_Raw_Phase4_Drivers'!$B$4:$B$180,0),MATCH($D$3,'96_Raw_Phase4_Drivers'!$E$3:$G$3,0)) -> 542 | I35: =H35+INDEX('96_Raw_Phase4_Drivers'!$E$4:$G$180,MATCH("ak_store_additions_2028",'96_Raw_Phase4_Drivers'!$B$4:$B$180,0),MATCH($D$3,'96_Raw_Phase4_Drivers'!$E$3:$G$3,0)) -> 592 | J35: =I35+INDEX('96_Raw_Phase4_Drivers'!$E$4:$G$180,MATCH("ak_store_additions_2029",'96_Raw_Phase4_Drivers'!$B$4:$B$180,0),MATCH($D$3,'96_Raw_Phase4_Drivers'!$E$3:$G$3,0)) -> 632 | K35: =J35+INDEX('96_Raw_Phase4_Drivers'!$E$4:$G$180,MATCH("ak_store_additions_2030",'96_Raw_Phase4_Drivers'!$B$4:$B$180,0),MATCH($D$3,'96_Raw_Phase4_Drivers'!$E$3:$G$3,0)) -> 662
A36: ENDING STORE COUNT BY CHAIN | B36: AVAKids Stores | C36: stores | D36: ='06_Revenue_Drivers_Hist'!H33 -> 83 | E36: ='06_Revenue_Drivers_Hist'!I33 -> 95 | F36: =IFERROR(INDEX('96_Raw_Phase4_Drivers'!$E$4:$G$180,MATCH("ava_stores_5m_2026",'96_Raw_Phase4_Drivers'!$B$4:$B$180,0),MATCH($D$3,'96_Raw_Phase4_Drivers'!$E$3:$G$3,0)),"") -> 95 | G36: =MAX(F36,D36) -> 95 | H36: =G36+INDEX('96_Raw_Phase4_Drivers'!$E$4:$G$180,MATCH("ava_store_additions_2027",'96_Raw_Phase4_Drivers'!$B$4:$B$180,0),MATCH($D$3,'96_Raw_Phase4_Drivers'!$E$3:$G$3,0)) -> 105 | I36: =H36+INDEX('96_Raw_Phase4_Drivers'!$E$4:$G$180,MATCH("ava_store_additions_2028",'96_Raw_Phase4_Drivers'!$B$4:$B$180,0),MATCH($D$3,'96_Raw_Phase4_Drivers'!$E$3:$G$3,0)) -> 115 | J36: =I36+INDEX('96_Raw_Phase4_Drivers'!$E$4:$G$180,MATCH("ava_store_additions_2029",'96_Raw_Phase4_Drivers'!$B$4:$B$180,0),MATCH($D$3,'96_Raw_Phase4_Drivers'!$E$3:$G$3,0)) -> 125 | K36: =J36+INDEX('96_Raw_Phase4_Drivers'!$E$4:$G$180,MATCH("ava_store_additions_2030",'96_Raw_Phase4_Drivers'!$B$4:$B$180,0),MATCH($D$3,'96_Raw_Phase4_Drivers'!$E$3:$G$3,0)) -> 135
A37: ENDING STORE COUNT BY CHAIN | B37: EraBlue Stores (supplemental) | C37: stores | D37: ='06_Revenue_Drivers_Hist'!H34 -> 181 | E37: ='06_Revenue_Drivers_Hist'!I34 -> 212 | F37: =IFERROR(INDEX('96_Raw_Phase4_Drivers'!$E$4:$G$180,MATCH("erablue_stores_5m_2026",'96_Raw_Phase4_Drivers'!$B$4:$B$180,0),MATCH($D$3,'96_Raw_Phase4_Drivers'!$E$3:$G$3,0)),"") -> 245 | G37: =IFERROR(INDEX('96_Raw_Phase4_Drivers'!$E$4:$G$180,MATCH("erablue_target_stores_2026",'96_Raw_Phase4_Drivers'!$B$4:$B$180,0),MATCH($D$3,'96_Raw_Phase4_Drivers'!$E$3:$G$3,0)),"") -> 300 | H37: =G37+INDEX('96_Raw_Phase4_Drivers'!$E$4:$G$180,MATCH("erablue_store_additions_2027",'96_Raw_Phase4_Drivers'!$B$4:$B$180,0),MATCH($D$3,'96_Raw_Phase4_Drivers'!$E$3:$G$3,0)) -> 420 | I37: =H37+INDEX('96_Raw_Phase4_Drivers'!$E$4:$G$180,MATCH("erablue_store_additions_2028",'96_Raw_Phase4_Drivers'!$B$4:$B$180,0),MATCH($D$3,'96_Raw_Phase4_Drivers'!$E$3:$G$3,0)) -> 550 | J37: =I37+INDEX('96_Raw_Phase4_Drivers'!$E$4:$G$180,MATCH("erablue_store_additions_2029",'96_Raw_Phase4_Drivers'!$B$4:$B$180,0),MATCH($D$3,'96_Raw_Phase4_Drivers'!$E$3:$G$3,0)) -> 700 | K37: =J37+INDEX('96_Raw_Phase4_Drivers'!$E$4:$G$180,MATCH("erablue_store_additions_2030",'96_Raw_Phase4_Drivers'!$B$4:$B$180,0),MATCH($D$3,'96_Raw_Phase4_Drivers'!$E$3:$G$3,0)) -> 850
A38: ENDING STORE COUNT BY CHAIN | B38: Total Stores - Modeled Chains | C38: stores | D38: =SUM(D32:D37) -> 6225 | E38: =SUM(E32:E37) -> 6575 | F38: =SUM(F32:F37) -> 6823 | G38: =SUM(G32:G37) -> 7452 | H38: =SUM(H32:H37) -> 8242 | I38: =SUM(I32:I37) -> 8932 | J38: =SUM(J32:J37) -> 9532 | K38: =SUM(K32:K37) -> 10022
A40: AVERAGE STORE COUNT
A41: AVERAGE STORE COUNT | B41: TGDD / TopZone Average Stores | C41: stores | D41: =IFERROR(D15/D48/D7,"") -> 1016.5 | E41: =AVERAGE(D32,E32) -> 1013 | F41: =AVERAGE(D32,F32) -> 1012 | G41: =AVERAGE(D32,G32) -> 1012 | H41: =AVERAGE(G32,H32) -> 1012 | I41: =AVERAGE(H32,I32) -> 1012 | J41: =AVERAGE(I32,J32) -> 1012 | K41: =AVERAGE(J32,K32) -> 1012
A42: AVERAGE STORE COUNT | B42: DMX Average Stores | C42: stores | D42: =IFERROR(D16/D49/D7,"") -> 2017 | E42: =AVERAGE(D33,E33) -> 2007 | F42: =AVERAGE(D33,F33) -> 2006 | G42: =AVERAGE(D33,G33) -> 2006 | H42: =AVERAGE(G33,H33) -> 2004 | I42: =AVERAGE(H33,I33) -> 2004 | J42: =AVERAGE(I33,J33) -> 2004 | K42: =AVERAGE(J33,K33) -> 2004
A43: AVERAGE STORE COUNT | B43: BHX Average Stores | C43: stores | D43: =IFERROR(D17/D50/D7,"") -> 2164.5 | E43: =AVERAGE(D34,E34) -> 2699 | F43: =AVERAGE(D34,F34) -> 2805 | G43: =AVERAGE(D34,G34) -> 3059 | H43: =AVERAGE(G34,H34) -> 3859 | I43: =AVERAGE(H34,I34) -> 4409 | J43: =AVERAGE(I34,J34) -> 4859 | K43: =AVERAGE(J34,K34) -> 5209
A44: AVERAGE STORE COUNT | B44: An Khang Average Stores | C44: stores | D44: =IFERROR(D18/D51/D7,"") -> 354 | E44: =AVERAGE(D35,E35) -> 395.5 | F44: =AVERAGE(D35,F35) -> 399 | G44: =AVERAGE(D35,G35) -> 432 | H44: =AVERAGE(G35,H35) -> 512 | I44: =AVERAGE(H35,I35) -> 567 | J44: =AVERAGE(I35,J35) -> 612 | K44: =AVERAGE(J35,K35) -> 647
A45: AVERAGE STORE COUNT | B45: AVAKids Average Stores | C45: stores | D45: =IFERROR(D19/D52/D7,"") -> 72.5 | E45: =AVERAGE(D36,E36) -> 89 | F45: =AVERAGE(D36,F36) -> 89 | G45: =AVERAGE(D36,G36) -> 89 | H45: =AVERAGE(G36,H36) -> 100 | I45: =AVERAGE(H36,I36) -> 110 | J45: =AVERAGE(I36,J36) -> 120 | K45: =AVERAGE(J36,K36) -> 130
A47: REVENUE / STORE / MONTH
A48: REVENUE / STORE / MONTH | B48: TGDD / TopZone Rev/Store/Month | C48: VND bn/store/month | D48: ='06_Revenue_Drivers_Hist'!H37 -> 3.0578783 | E48: =IF(E15="","",IFERROR(E15/E41/E7,"")) -> 3.5774926 | F48: =IF(F15="","",IFERROR(F15/F41/F7,"")) -> 3.519916 | G48: =IF(G15="","",IFERROR(G15/G41/G7,"")) -> 3.2383024 | H48: =G48*(1+INDEX('96_Raw_Phase4_Drivers'!$E$4:$G$180,MATCH("tgd_rpsm_growth_2027",'96_Raw_Phase4_Drivers'!$B$4:$B$180,0),MATCH($D$3,'96_Raw_Phase4_Drivers'!$E$3:$G$3,0))) -> 3.3678345 | I48: =H48*(1+INDEX('96_Raw_Phase4_Drivers'!$E$4:$G$180,MATCH("tgd_rpsm_growth_2028",'96_Raw_Phase4_Drivers'!$B$4:$B$180,0),MATCH($D$3,'96_Raw_Phase4_Drivers'!$E$3:$G$3,0))) -> 3.4688696 | J48: =I48*(1+INDEX('96_Raw_Phase4_Drivers'!$E$4:$G$180,MATCH("tgd_rpsm_growth_2029",'96_Raw_Phase4_Drivers'!$B$4:$B$180,0),MATCH($D$3,'96_Raw_Phase4_Drivers'!$E$3:$G$3,0))) -> 3.5729357 | K48: =J48*(1+INDEX('96_Raw_Phase4_Drivers'!$E$4:$G$180,MATCH("tgd_rpsm_growth_2030",'96_Raw_Phase4_Drivers'!$B$4:$B$180,0),MATCH($D$3,'96_Raw_Phase4_Drivers'!$E$3:$G$3,0))) -> 3.662259
A49: REVENUE / STORE / MONTH | B49: DMX Rev/Store/Month | C49: VND bn/store/month | D49: ='06_Revenue_Drivers_Hist'!H38 -> 2.8259792 | E49: =IF(E16="","",IFERROR(E16/E42/E7,"")) -> 3.5728284 | F49: =IF(F16="","",IFERROR(F16/F42/F7,"")) -> 3.6540994 | G49: =IF(G16="","",IFERROR(G16/G42/G7,"")) -> 3.3617504 | H49: =G49*(1+INDEX('96_Raw_Phase4_Drivers'!$E$4:$G$180,MATCH("dmx_rpsm_growth_2027",'96_Raw_Phase4_Drivers'!$B$4:$B$180,0),MATCH($D$3,'96_Raw_Phase4_Drivers'!$E$3:$G$3,0))) -> 3.5634554 | I49: =H49*(1+INDEX('96_Raw_Phase4_Drivers'!$E$4:$G$180,MATCH("dmx_rpsm_growth_2028",'96_Raw_Phase4_Drivers'!$B$4:$B$180,0),MATCH($D$3,'96_Raw_Phase4_Drivers'!$E$3:$G$3,0))) -> 3.7416282 | J49: =I49*(1+INDEX('96_Raw_Phase4_Drivers'!$E$4:$G$180,MATCH("dmx_rpsm_growth_2029",'96_Raw_Phase4_Drivers'!$B$4:$B$180,0),MATCH($D$3,'96_Raw_Phase4_Drivers'!$E$3:$G$3,0))) -> 3.8912933 | K49: =J49*(1+INDEX('96_Raw_Phase4_Drivers'!$E$4:$G$180,MATCH("dmx_rpsm_growth_2030",'96_Raw_Phase4_Drivers'!$B$4:$B$180,0),MATCH($D$3,'96_Raw_Phase4_Drivers'!$E$3:$G$3,0))) -> 4.0080321
A50: REVENUE / STORE / MONTH | B50: BHX Rev/Store/Month | C50: VND bn/store/month | D50: ='06_Revenue_Drivers_Hist'!H39 -> 1.8056518 | E50: =IF(E17="","",IFERROR(E17/E43/E7,"")) -> 1.6178832 | F50: =IF(F17="","",IFERROR(F17/F43/F7,"")) -> 1.6480876 | G50: =IF(G17="","",IFERROR(G17/G43/G7,"")) -> 1.511932 | H50: =G50*(1+INDEX('96_Raw_Phase4_Drivers'!$E$4:$G$180,MATCH("bhx_rpsm_growth_2027",'96_Raw_Phase4_Drivers'!$B$4:$B$180,0),MATCH($D$3,'96_Raw_Phase4_Drivers'!$E$3:$G$3,0))) -> 1.5875286 | I50: =H50*(1+INDEX('96_Raw_Phase4_Drivers'!$E$4:$G$180,MATCH("bhx_rpsm_growth_2028",'96_Raw_Phase4_Drivers'!$B$4:$B$180,0),MATCH($D$3,'96_Raw_Phase4_Drivers'!$E$3:$G$3,0))) -> 1.666905 | J50: =I50*(1+INDEX('96_Raw_Phase4_Drivers'!$E$4:$G$180,MATCH("bhx_rpsm_growth_2029",'96_Raw_Phase4_Drivers'!$B$4:$B$180,0),MATCH($D$3,'96_Raw_Phase4_Drivers'!$E$3:$G$3,0))) -> 1.7335812 | K50: =J50*(1+INDEX('96_Raw_Phase4_Drivers'!$E$4:$G$180,MATCH("bhx_rpsm_growth_2030",'96_Raw_Phase4_Drivers'!$B$4:$B$180,0),MATCH($D$3,'96_Raw_Phase4_Drivers'!$E$3:$G$3,0))) -> 1.8029245
A51: REVENUE / STORE / MONTH | B51: An Khang Rev/Store/Month | C51: VND bn/store/month | D51: ='06_Revenue_Drivers_Hist'!H40 -> 0.51789077 | E51: =IF(E18="","",IFERROR(E18/E44/E7,"")) | F51: =IF(F18="","",IFERROR(F18/F44/F7,"")) -> 0.55597327 | G51: =IF(G18="","",IFERROR(G18/G44/G7,"")) -> 0.55169753 | H51: =G51*(1+INDEX('96_Raw_Phase4_Drivers'!$E$4:$G$180,MATCH("ak_rpsm_growth_2027",'96_Raw_Phase4_Drivers'!$B$4:$B$180,0),MATCH($D$3,'96_Raw_Phase4_Drivers'!$E$3:$G$3,0))) -> 0.57376543 | I51: =H51*(1+INDEX('96_Raw_Phase4_Drivers'!$E$4:$G$180,MATCH("ak_rpsm_growth_2028",'96_Raw_Phase4_Drivers'!$B$4:$B$180,0),MATCH($D$3,'96_Raw_Phase4_Drivers'!$E$3:$G$3,0))) -> 0.59671605 | J51: =I51*(1+INDEX('96_Raw_Phase4_Drivers'!$E$4:$G$180,MATCH("ak_rpsm_growth_2029",'96_Raw_Phase4_Drivers'!$B$4:$B$180,0),MATCH($D$3,'96_Raw_Phase4_Drivers'!$E$3:$G$3,0))) -> 0.61461753 | K51: =J51*(1+INDEX('96_Raw_Phase4_Drivers'!$E$4:$G$180,MATCH("ak_rpsm_growth_2030",'96_Raw_Phase4_Drivers'!$B$4:$B$180,0),MATCH($D$3,'96_Raw_Phase4_Drivers'!$E$3:$G$3,0))) -> 0.63305606
A52: REVENUE / STORE / MONTH | B52: AVAKids Rev/Store/Month | C52: VND bn/store/month | D52: ='06_Revenue_Drivers_Hist'!H41 -> 1.6091954 | E52: =IF(E19="","",IFERROR(E19/E45/E7,"")) | F52: =IF(F19="","",IFERROR(F19/F45/F7,"")) -> 1.5730337 | G52: =IF(G19="","",IFERROR(G19/G45/G7,"")) -> 1.5730337 | H52: =G52*(1+INDEX('96_Raw_Phase4_Drivers'!$E$4:$G$180,MATCH("ava_rpsm_growth_2027",'96_Raw_Phase4_Drivers'!$B$4:$B$180,0),MATCH($D$3,'96_Raw_Phase4_Drivers'!$E$3:$G$3,0))) -> 1.6516854 | I52: =H52*(1+INDEX('96_Raw_Phase4_Drivers'!$E$4:$G$180,MATCH("ava_rpsm_growth_2028",'96_Raw_Phase4_Drivers'!$B$4:$B$180,0),MATCH($D$3,'96_Raw_Phase4_Drivers'!$E$3:$G$3,0))) -> 1.7177528 | J52: =I52*(1+INDEX('96_Raw_Phase4_Drivers'!$E$4:$G$180,MATCH("ava_rpsm_growth_2029",'96_Raw_Phase4_Drivers'!$B$4:$B$180,0),MATCH($D$3,'96_Raw_Phase4_Drivers'!$E$3:$G$3,0))) -> 1.7864629 | K52: =J52*(1+INDEX('96_Raw_Phase4_Drivers'!$E$4:$G$180,MATCH("ava_rpsm_growth_2030",'96_Raw_Phase4_Drivers'!$B$4:$B$180,0),MATCH($D$3,'96_Raw_Phase4_Drivers'!$E$3:$G$3,0))) -> 1.8400568
A63: MODEL CHECKS
A64: MODEL CHECKS | B64: Segment Revenue Check | C64: VND bn | D64: =D21 -> 0 | E64: =E21 -> 0 | F64: =F21 -> 0 | G64: =G21 -> 0 | H64: =H21 -> 0 | I64: =I21 -> 0 | J64: =J21 -> 0 | K64: =K21 -> 0
A65: MODEL CHECKS | B65: 2026 Scenario Target Check | C65: VND bn | G65: =G8-INDEX('96_Raw_Phase4_Drivers'!$E$4:$G$180,MATCH("group_revenue_target_2026",'96_Raw_Phase4_Drivers'!$B$4:$B$180,0),MATCH($D$3,'96_Raw_Phase4_Drivers'!$E$3:$G$3,0)) -> 0
A66: MODEL CHECKS | B66: 2026 Core Mix Check | C66: ppt | G66: =(G15+G16)/G8-INDEX('96_Raw_Phase4_Drivers'!$E$4:$G$180,MATCH("core_revenue_mix_2026",'96_Raw_Phase4_Drivers'!$B$4:$B$180,0),MATCH($D$3,'96_Raw_Phase4_Drivers'!$E$3:$G$3,0)) -> 0
A67: MODEL CHECKS | B67: 2026 BHX Mix Check | C67: ppt | G67: =G17/G8-INDEX('96_Raw_Phase4_Drivers'!$E$4:$G$180,MATCH("bhx_revenue_mix_2026",'96_Raw_Phase4_Drivers'!$B$4:$B$180,0),MATCH($D$3,'96_Raw_Phase4_Drivers'!$E$3:$G$3,0)) -> 0
A68: MODEL CHECKS | B68: 2026E vs 5M Annualized Run-rate | C68: % | G68: =IFERROR(G8/(F8/F7*12)-1,"") -> -0.026221487
A69: MODEL CHECKS | B69: Model Status | C69: status | G69: =IF(AND(ABS(G64)<0.1,ABS(G65)<0.1,ABS(G66)<0.001,ABS(G67)<0.001),"OK","CHECK") -> OK
A72: FORECAST ASSUMPTION CHECK
A73: Section | B73: Driver | C73: Unit | D73: Historical CAGR / Avg | E73: 2027E | F73: 2028E | G73: 2029E | H73: 2030E | I73: Forecast Avg | J73: Gap vs History | K73: Tolerance | L73: Status
A74: RPSM GROWTH CHECK | B74: TGDD / TopZone RPSM growth | C74: % | D74: ='06_Revenue_Drivers_Hist'!K37 -> 0.030198273 | E74: =IFERROR(H48/G48-1,"") -> 0.04 | F74: =IFERROR(I48/H48-1,"") -> 0.03 | G74: =IFERROR(J48/I48-1,"") -> 0.03 | H74: =IFERROR(K48/J48-1,"") -> 0.025 | I74: =IFERROR(AVERAGE(E74:H74),"") -> 0.03125 | J74: =IFERROR(I74-D74,"") -> 0.0010517274 | K74: 0.03 | L74: =IF(COUNT(D74,I74,K74)<3,"NM",IF(ABS(J74)<=K74,"OK","CHECK")) -> OK
A75: RPSM GROWTH CHECK | B75: DMX RPSM growth | C75: % | D75: ='06_Revenue_Drivers_Hist'!K38 -> 0.01877468 | E75: =IFERROR(H49/G49-1,"") -> 0.06 | F75: =IFERROR(I49/H49-1,"") -> 0.05 | G75: =IFERROR(J49/I49-1,"") -> 0.04 | H75: =IFERROR(K49/J49-1,"") -> 0.03 | I75: =IFERROR(AVERAGE(E75:H75),"") -> 0.045 | J75: =IFERROR(I75-D75,"") -> 0.02622532 | K75: 0.03 | L75: =IF(COUNT(D75,I75,K75)<3,"NM",IF(ABS(J75)<=K75,"OK","CHECK")) -> OK
A76: RPSM GROWTH CHECK | B76: BHX RPSM growth | C76: % | D76: ='06_Revenue_Drivers_Hist'!K39 -> 0.12786242 | E76: =IFERROR(H50/G50-1,"") -> 0.05 | F76: =IFERROR(I50/H50-1,"") -> 0.05 | G76: =IFERROR(J50/I50-1,"") -> 0.04 | H76: =IFERROR(K50/J50-1,"") -> 0.04 | I76: =IFERROR(AVERAGE(E76:H76),"") -> 0.045 | J76: =IFERROR(I76-D76,"") -> -0.082862424 | K76: 0.05 | L76: =IF(COUNT(D76,I76,K76)<3,"NM",IF(ABS(J76)<=K76,"OK","CHECK")) -> CHECK
A77: RPSM GROWTH CHECK | B77: An Khang RPSM growth | C77: % | D77: ='06_Revenue_Drivers_Hist'!K40 -> 0.11989151 | E77: =IFERROR(H51/G51-1,"") -> 0.04 | F77: =IFERROR(I51/H51-1,"") -> 0.04 | G77: =IFERROR(J51/I51-1,"") -> 0.03 | H77: =IFERROR(K51/J51-1,"") -> 0.03 | I77: =IFERROR(AVERAGE(E77:H77),"") -> 0.035 | J77: =IFERROR(I77-D77,"") -> -0.084891511 | K77: 0.05 | L77: =IF(COUNT(D77,I77,K77)<3,"NM",IF(ABS(J77)<=K77,"OK","CHECK")) -> CHECK
A78: RPSM GROWTH CHECK | B78: AVAKids RPSM growth | C78: % | D78: ='06_Revenue_Drivers_Hist'!K41 -> 0.0098640661 | E78: =IFERROR(H52/G52-1,"") -> 0.05 | F78: =IFERROR(I52/H52-1,"") -> 0.04 | G78: =IFERROR(J52/I52-1,"") -> 0.04 | H78: =IFERROR(K52/J52-1,"") -> 0.03 | I78: =IFERROR(AVERAGE(E78:H78),"") -> 0.04 | J78: =IFERROR(I78-D78,"") -> 0.030135934 | K78: 0.05 | L78: =IF(COUNT(D78,I78,K78)<3,"NM",IF(ABS(J78)<=K78,"OK","CHECK")) -> OK
A80: STORE EXPANSION CHECK
A81: Section | B81: Driver | C81: Unit | D81: Historical Avg Additions | E81: 2027E Additions | F81: 2028E Additions | G81: 2029E Additions | H81: 2030E Additions | I81: Forecast Avg Additions | J81: Gap vs History | K81: Tolerance | L81: Status
A82: STORE EXPANSION CHECK | B82: TGDD / TopZone net store additions | C82: stores | D82: =IFERROR(AVERAGE('06_Revenue_Drivers_Hist'!E29-'06_Revenue_Drivers_Hist'!D29,'06_Revenue_Drivers_Hist'!F29-'06_Revenue_Drivers_Hist'!E29,'06_Revenue_Drivers_Hist'!G29-'06_Revenue_Drivers_Hist'!F29,'06_Revenue_Drivers_Hist'!H29-'06_Revenue_Drivers_Hist'!G29),"") -> 10.5 | E82: =IFERROR(H32-G32,"") -> 0 | F82: =IFERROR(I32-H32,"") -> 0 | G82: =IFERROR(J32-I32,"") -> 0 | H82: =IFERROR(K32-J32,"") -> 0 | I82: =IFERROR(AVERAGE(E82:H82),"") -> 0 | J82: =IFERROR(I82-D82,"") -> -10.5 | K82: 50 | L82: =IF(COUNT(D82,I82,K82)<3,"NM",IF(ABS(J82)<=K82,"OK","CHECK")) -> OK
A83: STORE EXPANSION CHECK | B83: DMX net store additions | C83: stores | D83: =IFERROR(AVERAGE('06_Revenue_Drivers_Hist'!E30-'06_Revenue_Drivers_Hist'!D30,'06_Revenue_Drivers_Hist'!F30-'06_Revenue_Drivers_Hist'!E30,'06_Revenue_Drivers_Hist'!G30-'06_Revenue_Drivers_Hist'!F30,'06_Revenue_Drivers_Hist'!H30-'06_Revenue_Drivers_Hist'!G30),"") -> 4 | E83: =IFERROR(H33-G33,"") -> 0 | F83: =IFERROR(I33-H33,"") -> 0 | G83: =IFERROR(J33-I33,"") -> 0 | H83: =IFERROR(K33-J33,"") -> 0 | I83: =IFERROR(AVERAGE(E83:H83),"") -> 0 | J83: =IFERROR(I83-D83,"") -> -4 | K83: 50 | L83: =IF(COUNT(D83,I83,K83)<3,"NM",IF(ABS(J83)<=K83,"OK","CHECK")) -> OK
A84: STORE EXPANSION CHECK | B84: BHX net store additions | C84: stores | D84: =IFERROR(AVERAGE('06_Revenue_Drivers_Hist'!E31-'06_Revenue_Drivers_Hist'!D31,'06_Revenue_Drivers_Hist'!F31-'06_Revenue_Drivers_Hist'!E31,'06_Revenue_Drivers_Hist'!G31-'06_Revenue_Drivers_Hist'!F31,'06_Revenue_Drivers_Hist'!H31-'06_Revenue_Drivers_Hist'!G31),"") -> 113.25 | E84: =IFERROR(H34-G34,"") -> 600 | F84: =IFERROR(I34-H34,"") -> 500 | G84: =IFERROR(J34-I34,"") -> 400 | H84: =IFERROR(K34-J34,"") -> 300 | I84: =IFERROR(AVERAGE(E84:H84),"") -> 450 | J84: =IFERROR(I84-D84,"") -> 336.75 | K84: 250 | L84: =IF(COUNT(D84,I84,K84)<3,"NM",IF(ABS(J84)<=K84,"OK","CHECK")) -> CHECK
A85: STORE EXPANSION CHECK | B85: An Khang net store additions | C85: stores | D85: =IFERROR(AVERAGE('06_Revenue_Drivers_Hist'!E32-'06_Revenue_Drivers_Hist'!D32,'06_Revenue_Drivers_Hist'!F32-'06_Revenue_Drivers_Hist'!E32,'06_Revenue_Drivers_Hist'!G32-'06_Revenue_Drivers_Hist'!F32,'06_Revenue_Drivers_Hist'!H32-'06_Revenue_Drivers_Hist'!G32),"") -> 51 | E85: =IFERROR(H35-G35,"") -> 60 | F85: =IFERROR(I35-H35,"") -> 50 | G85: =IFERROR(J35-I35,"") -> 40 | H85: =IFERROR(K35-J35,"") -> 30 | I85: =IFERROR(AVERAGE(E85:H85),"") -> 45 | J85: =IFERROR(I85-D85,"") -> -6 | K85: 75 | L85: =IF(COUNT(D85,I85,K85)<3,"NM",IF(ABS(J85)<=K85,"OK","CHECK")) -> OK
A86: STORE EXPANSION CHECK | B86: AVAKids net store additions | C86: stores | D86: =IFERROR(AVERAGE('06_Revenue_Drivers_Hist'!E33-'06_Revenue_Drivers_Hist'!D33,'06_Revenue_Drivers_Hist'!F33-'06_Revenue_Drivers_Hist'!E33,'06_Revenue_Drivers_Hist'!G33-'06_Revenue_Drivers_Hist'!F33,'06_Revenue_Drivers_Hist'!H33-'06_Revenue_Drivers_Hist'!G33),"") -> 20.75 | E86: =IFERROR(H36-G36,"") -> 10 | F86: =IFERROR(I36-H36,"") -> 10 | G86: =IFERROR(J36-I36,"") -> 10 | H86: =IFERROR(K36-J36,"") -> 10 | I86: =IFERROR(AVERAGE(E86:H86),"") -> 10 | J86: =IFERROR(I86-D86,"") -> -10.75 | K86: 30 | L86: =IF(COUNT(D86,I86,K86)<3,"NM",IF(ABS(J86)<=K86,"OK","CHECK")) -> OK
A87: STORE EXPANSION CHECK | B87: EraBlue net store additions | C87: stores | D87: =IFERROR(AVERAGE('06_Revenue_Drivers_Hist'!E34-'06_Revenue_Drivers_Hist'!D34,'06_Revenue_Drivers_Hist'!F34-'06_Revenue_Drivers_Hist'!E34,'06_Revenue_Drivers_Hist'!G34-'06_Revenue_Drivers_Hist'!F34,'06_Revenue_Drivers_Hist'!H34-'06_Revenue_Drivers_Hist'!G34),"") -> 45.25 | E87: =IFERROR(H37-G37,"") -> 120 | F87: =IFERROR(I37-H37,"") -> 130 | G87: =IFERROR(J37-I37,"") -> 150 | H87: =IFERROR(K37-J37,"") -> 150 | I87: =IFERROR(AVERAGE(E87:H87),"") -> 137.5 | J87: =IFERROR(I87-D87,"") -> 92.25 | K87: 100 | L87: =IF(COUNT(D87,I87,K87)<3,"NM",IF(ABS(J87)<=K87,"OK","CHECK")) -> OK
A89: ASSUMPTION CHECK SUMMARY | B89: Total CHECK flags | C89: count | D89: =COUNTIF(L74:L78,"CHECK")+COUNTIF(L82:L87,"CHECK") -> 3 | L89: =IF(D89=0,"OK","REVIEW") -> REVIEW

Sheet 08_P5_Assumptions
A1: MWG - Assumptions
A2: Group-level 3-statement assumptions. Green = linked historical data; Blue = visible analyst input; Black = formulas. Forecast revenue links to segment driver model.
A4: Section | B4: Line Item | C4: Unit | D4: 2021A | E4: 2022A | F4: 2023A | G4: 2024A | H4: 2025A | I4: 2026E | J4: 2027E | K4: 2028E | L4: 2029E | M4: 2030E
A5: REVENUE, MARGIN AND CAPITAL ALLOCATION
A6: Revenue | B6: Revenue | C6: VND bn | D6: ='03_Historical_FS'!D7 -> 122958.11 | E6: ='03_Historical_FS'!E7 -> 133404.78 | F6: ='03_Historical_FS'!F7 -> 118279.79 | G6: ='03_Historical_FS'!G7 -> 134341.15 | H6: ='03_Historical_FS'!H7 -> 155928.15 | I6: ='07_Revenue_Drivers'!G8 -> 185000 | J6: ='07_Revenue_Drivers'!H8 -> 210702.27 | K6: ='07_Revenue_Drivers'!I8 -> 232016.74 | L6: ='07_Revenue_Drivers'!J8 -> 250797.07 | M6: ='07_Revenue_Drivers'!K8 -> 267230.44
A7: Revenue | B7: Revenue Growth | C7: % | E7: =IFERROR(E6/D6-1,"") -> 0.084961226 | F7: =IFERROR(F6/E6-1,"") -> -0.11337667 | G7: =IFERROR(G6/F6-1,"") -> 0.13579128 | H7: =IFERROR(H6/G6-1,"") -> 0.16068786 | I7: =IFERROR(I6/H6-1,"") -> 0.18644392 | J7: =IFERROR(J6/I6-1,"") -> 0.13893119 | K7: =IFERROR(K6/J6-1,"") -> 0.10115916 | L7: =IFERROR(L6/K6-1,"") -> 0.08094389 | M7: =IFERROR(M6/L6-1,"") -> 0.065524566
A8: Margin | B8: Gross Margin | C8: % | D8: ='03_Historical_FS'!D10 -> 0.22472802 | E8: ='03_Historical_FS'!E10 -> 0.23134136 | F8: ='03_Historical_FS'!F10 -> 0.1904012 | G8: ='03_Historical_FS'!G10 -> 0.20469684 | H8: ='03_Historical_FS'!H10 -> 0.19882156 | I8: 0.205 | J8: 0.208 | K8: 0.21 | L8: 0.211 | M8: 0.212
A9: Opex | B9: Selling Expenses / Revenue | C9: % | D9: =IFERROR('03_Historical_FS'!D14/'03_Historical_FS'!D7,"") -> 0.14569331 | E9: =IFERROR('03_Historical_FS'!E14/'03_Historical_FS'!E7,"") -> 0.16743657 | F9: =IFERROR('03_Historical_FS'!F14/'03_Historical_FS'!F7,"") -> 0.17684096 | G9: =IFERROR('03_Historical_FS'!G14/'03_Historical_FS'!G7,"") -> 0.14775694 | H9: =IFERROR('03_Historical_FS'!H14/'03_Historical_FS'!H7,"") -> 0.12397315 | I9: 0.122 | J9: 0.12 | K9: 0.118 | L9: 0.116 | M9: 0.115
A10: Opex | B10: G&A Expenses / Revenue | C10: % | D10: =IFERROR('03_Historical_FS'!D15/'03_Historical_FS'!D7,"") -> 0.031095063 | E10: =IFERROR('03_Historical_FS'!E15/'03_Historical_FS'!E7,"") -> 0.014100152 | F10: =IFERROR('03_Historical_FS'!F15/'03_Historical_FS'!F7,"") -> 0.0098719458 | G10: =IFERROR('03_Historical_FS'!G15/'03_Historical_FS'!G7,"") -> 0.026542631 | H10: =IFERROR('03_Historical_FS'!H15/'03_Historical_FS'!H7,"") -> 0.029475593 | I10: 0.028 | J10: 0.027 | K10: 0.026 | L10: 0.025 | M10: 0.025
A11: Finance | B11: Financial Income / Revenue | C11: % | D11: =IFERROR('03_Historical_FS'!D11/'03_Historical_FS'!D7,"") -> 0.010474755 | E11: =IFERROR('03_Historical_FS'!E11/'03_Historical_FS'!E7,"") -> 0.0098432554 | F11: =IFERROR('03_Historical_FS'!F11/'03_Historical_FS'!F7,"") -> 0.018320659 | G11: =IFERROR('03_Historical_FS'!G11/'03_Historical_FS'!G7,"") -> 0.017690057 | H11: =IFERROR('03_Historical_FS'!H11/'03_Historical_FS'!H7,"") -> 0.019928081 | I11: 0.017 | J11: 0.016 | K11: 0.015 | L11: 0.014 | M11: 0.013
A12: Finance | B12: Interest Rate on Average Debt | C12: % | D12: =IFERROR('03_Historical_FS'!D13/'03_Historical_FS'!D50,"") -> 0.027362956 | E12: =IFERROR('03_Historical_FS'!E13/AVERAGE('03_Historical_FS'!D50,'03_Historical_FS'!E50),"") -> 0.066064381 | F12: =IFERROR('03_Historical_FS'!F13/AVERAGE('03_Historical_FS'!E50,'03_Historical_FS'!F50),"") -> 0.069429638 | G12: =IFERROR('03_Historical_FS'!G13/AVERAGE('03_Historical_FS'!F50,'03_Historical_FS'!G50),"") -> 0.043394333 | H12: =IFERROR('03_Historical_FS'!H13/AVERAGE('03_Historical_FS'!G50,'03_Historical_FS'!H50),"") -> 0.0513942 | I12: 0.052 | J12: 0.052 | K12: 0.051 | L12: 0.05 | M12: 0.05
A13: Other | B13: Other Profit / Revenue | C13: % | D13: =IFERROR('03_Historical_FS'!D19/'03_Historical_FS'!D7,"") -> 4.8608688e-05 | E13: =IFERROR('03_Historical_FS'!E19/'03_Historical_FS'!E7,"") -> -0.0038854555 | F13: =IFERROR('03_Historical_FS'!F19/'03_Historical_FS'!F7,"") -> -0.0030214459 | G13: =IFERROR('03_Historical_FS'!G19/'03_Historical_FS'!G7,"") -> -0.0029870401 | H13: =IFERROR('03_Historical_FS'!H19/'03_Historical_FS'!H7,"") -> -0.00019889229 | I13: 0 | J13: 0 | K13: 0 | L13: 0 | M13: 0
A14: Tax | B14: Effective Tax Rate | C14: % | D14: =IFERROR('03_Historical_FS'!D23/'03_Historical_FS'!D20,"") -> 0.24262331 | E14: =IFERROR('03_Historical_FS'!E23/'03_Historical_FS'!E20,"") -> 0.32274212 | F14: =IFERROR('03_Historical_FS'!F23/'03_Historical_FS'!F20,"") -> 0.75666085 | G14: =IFERROR('03_Historical_FS'!G23/'03_Historical_FS'!G20,"") -> 0.22638384 | H14: =IFERROR('03_Historical_FS'!H23/'03_Historical_FS'!H20,"") -> 0.18075205 | I14: 0.2 | J14: 0.2 | K14: 0.2 | L14: 0.2 | M14: 0.2
A15: Minority Interest | B15: Minority Interest / NPAT | C15: % | D15: =IFERROR('03_Historical_FS'!D25/'03_Historical_FS'!D24,"") -> 0.00052176557 | E15: =IFERROR('03_Historical_FS'!E25/'03_Historical_FS'!E24,"") -> 0.00047575179 | F15: =IFERROR('03_Historical_FS'!F25/'03_Historical_FS'!F24,"") -> 0.00095193234 | G15: =IFERROR('03_Historical_FS'!G25/'03_Historical_FS'!G24,"") -> 0.0030589085 | H15: =IFERROR('03_Historical_FS'!H25/'03_Historical_FS'!H24,"") -> 0.0054989665 | I15: 0.006 | J15: 0.0065 | K15: 0.007 | L15: 0.0075 | M15: 0.008
A16: Capital Return | B16: Dividend Payout Ratio | C16: % | D16: =IFERROR(ABS('03_Historical_FS'!D63)/'03_Historical_FS'!D26,"") -> 0.048892801 | E16: =IFERROR(ABS('03_Historical_FS'!E63)/'03_Historical_FS'!E26,"") -> 0.17851149 | F16: =IFERROR(ABS('03_Historical_FS'!F63)/'03_Historical_FS'!F26,"") -> 4.3614402 | G16: =IFERROR(ABS('03_Historical_FS'!G63)/'03_Historical_FS'!G26,"") -> 0.19639536 | H16: =IFERROR(ABS('03_Historical_FS'!H63)/'03_Historical_FS'!H26,"") -> 0.21019525 | I16: 0.2 | J16: 0.2 | K16: 0.2 | L16: 0.2 | M16: 0.2
A19: WORKING CAPITAL AND BALANCE SHEET SUPPORT
A20: Working Capital | B20: Inventory Days | C20: days | D20: ='05_Ratio_Analysis'!D21 -> 111.68037 | E20: ='05_Ratio_Analysis'!E21 -> 97.642744 | F20: ='05_Ratio_Analysis'!F21 -> 90.565287 | G20: ='05_Ratio_Analysis'!G21 -> 75.27546 | H20: ='05_Ratio_Analysis'!H21 -> 72.329495 | I20: 73 | J20: 72 | K20: 70 | L20: 69 | M20: 68
A21: Working Capital | B21: Receivable Days | C21: days | D21: ='05_Ratio_Analysis'!D22 -> 9.3867298 | E21: ='05_Ratio_Analysis'!E22 -> 8.4310058 | F21: ='05_Ratio_Analysis'!F22 -> 12.589978 | G21: ='05_Ratio_Analysis'!G22 -> 18.998027 | H21: ='05_Ratio_Analysis'!H22 -> 22.248027 | I21: 18 | J21: 17 | K21: 16 | L21: 15 | M21: 15
A22: Working Capital | B22: Payable Days | C22: days | D22: ='05_Ratio_Analysis'!D23 -> 46.635955 | E22: ='05_Ratio_Analysis'!E23 -> 37.242252 | F22: ='05_Ratio_Analysis'!F23 -> 31.775584 | G22: ='05_Ratio_Analysis'!G23 -> 29.220489 | H22: ='05_Ratio_Analysis'!H23 -> 32.567772 | I22: 33 | J22: 34 | K22: 34 | L22: 34 | M22: 34
A23: Debt | B23: Total Debt / Revenue | C23: % | D23: =IFERROR('03_Historical_FS'!D50/'03_Historical_FS'!D7,"") -> 0.20045424 | E23: =IFERROR('03_Historical_FS'!E50/'03_Historical_FS'!E7,"") -> 0.12435378 | F23: =IFERROR('03_Historical_FS'!F50/'03_Historical_FS'!F7,"") -> 0.2123253 | G23: =IFERROR('03_Historical_FS'!G50/'03_Historical_FS'!G7,"") -> 0.20321581 | H23: =IFERROR('03_Historical_FS'!H50/'03_Historical_FS'!H7,"") -> 0.19195343 | I23: 0.19 | J23: 0.18 | K23: 0.17 | L23: 0.16 | M23: 0.15
A24: Current Assets | B24: Other Current Assets / Revenue | C24: % | D24: =IFERROR('03_Historical_FS'!D33/'03_Historical_FS'!D7,"") -> 0.010143792 | E24: =IFERROR('03_Historical_FS'!E33/'03_Historical_FS'!E7,"") -> 0.0056252998 | F24: =IFERROR('03_Historical_FS'!F33/'03_Historical_FS'!F7,"") -> 0.0056183401 | G24: =IFERROR('03_Historical_FS'!G33/'03_Historical_FS'!G7,"") -> 0.0040499635 | H24: =IFERROR('03_Historical_FS'!H33/'03_Historical_FS'!H7,"") -> 0.0056293045 | I24: 0.006 | J24: 0.006 | K24: 0.006 | L24: 0.006 | M24: 0.006
A25: Current Liabilities | B25: Other Current Liabilities / Revenue | C25: % | D25: =IFERROR(('03_Historical_FS'!D41-'03_Historical_FS'!D39-'03_Historical_FS'!D40)/'03_Historical_FS'!D7,"") -> 0.046893287 | E25: =IFERROR(('03_Historical_FS'!E41-'03_Historical_FS'!E39-'03_Historical_FS'!E40)/'03_Historical_FS'!E7,"") -> 0.049220862 | F25: =IFERROR(('03_Historical_FS'!F41-'03_Historical_FS'!F39-'03_Historical_FS'!F40)/'03_Historical_FS'!F7,"") -> 0.031363338 | G25: =IFERROR(('03_Historical_FS'!G41-'03_Historical_FS'!G39-'03_Historical_FS'!G40)/'03_Historical_FS'!G7,"") -> 0.043443993 | H25: =IFERROR(('03_Historical_FS'!H41-'03_Historical_FS'!H39-'03_Historical_FS'!H40)/'03_Historical_FS'!H7,"") -> 0.049539867 | I25: 0.05 | J25: 0.05 | K25: 0.048 | L25: 0.047 | M25: 0.046
A26: Long-term Assets | B26: Long-term Investments / Revenue | C26: % | D26: =IFERROR('03_Historical_FS'!D36/'03_Historical_FS'!D7,"") -> 0 | E26: =IFERROR('03_Historical_FS'!E36/'03_Historical_FS'!E7,"") -> 0.0017318333 | F26: =IFERROR('03_Historical_FS'!F36/'03_Historical_FS'!F7,"") -> 0.0063124247 | G26: =IFERROR('03_Historical_FS'!G36/'03_Historical_FS'!G7,"") -> 0.0018016504 | H26: =IFERROR('03_Historical_FS'!H36/'03_Historical_FS'!H7,"") -> 0.020113851 | I26: 0.018 | J26: 0.017 | K26: 0.016 | L26: 0.015 | M26: 0.015
A27: Long-term Assets | B27: Other Long-term Assets / Revenue | C27: % | D27: =IFERROR('03_Historical_FS'!D37/'03_Historical_FS'!D7,"") -> 0.006562325 | E27: =IFERROR('03_Historical_FS'!E37/'03_Historical_FS'!E7,"") -> 0.0050267321 | F27: =IFERROR('03_Historical_FS'!F37/'03_Historical_FS'!F7,"") -> 0.0038220184 | G27: =IFERROR('03_Historical_FS'!G37/'03_Historical_FS'!G7,"") -> 0.0026682398 | H27: =IFERROR('03_Historical_FS'!H37/'03_Historical_FS'!H7,"") -> 0.003301141 | I27: 0.003 | J27: 0.003 | K27: 0.003 | L27: 0.003 | M27: 0.003
A28: Long-term Liabilities | B28: Other LT Liabilities / Revenue | C28: % | D28: =IFERROR(('03_Historical_FS'!D43-'03_Historical_FS'!D42)/'03_Historical_FS'!D7,"") -> 0 | E28: =IFERROR(('03_Historical_FS'!E43-'03_Historical_FS'!E42)/'03_Historical_FS'!E7,"") -> 0 | F28: =IFERROR(('03_Historical_FS'!F43-'03_Historical_FS'!F42)/'03_Historical_FS'!F7,"") -> 9.8807329e-06 | G28: =IFERROR(('03_Historical_FS'!G43-'03_Historical_FS'!G42)/'03_Historical_FS'!G7,"") -> 0 | H28: =IFERROR(('03_Historical_FS'!H43-'03_Historical_FS'!H42)/'03_Historical_FS'!H7,"") -> 0 | I28: 0.001 | J28: 0.001 | K28: 0.001 | L28: 0.001 | M28: 0.001
A31: CAPEX AND D&A
A32: Capex | B32: Capex / Revenue | C32: % | D32: =IFERROR(ABS('03_Historical_FS'!D59)/'03_Historical_FS'!D7,"") -> 0.040476198 | E32: =IFERROR(ABS('03_Historical_FS'!E59)/'03_Historical_FS'!E7,"") -> 0.033472261 | F32: =IFERROR(ABS('03_Historical_FS'!F59)/'03_Historical_FS'!F7,"") -> 0.00442496 | G32: =IFERROR(ABS('03_Historical_FS'!G59)/'03_Historical_FS'!G7,"") -> 0.0022610185 | H32: =IFERROR(ABS('03_Historical_FS'!H59)/'03_Historical_FS'!H7,"") -> 0.005697893 | I32: 0.012 | J32: 0.012 | K32: 0.011 | L32: 0.01 | M32: 0.01
A33: D&A | B33: D&A / Revenue | C33: % | D33: =IFERROR('03_Historical_FS'!D55/'03_Historical_FS'!D7,"") -> 0.02375373 | E33: =IFERROR('03_Historical_FS'!E55/'03_Historical_FS'!E7,"") -> 0.026538215 | F33: =IFERROR('03_Historical_FS'!F55/'03_Historical_FS'!F7,"") -> 0.028333786 | G33: =IFERROR('03_Historical_FS'!G55/'03_Historical_FS'!G7,"") -> 0.021686721 | H33: =IFERROR('03_Historical_FS'!H55/'03_Historical_FS'!H7,"") -> 0.012126625 | I33: 0.0115 | J33: 0.011 | K33: 0.0105 | L33: 0.01 | M33: 0.0095

Sheet 09_Working_Capital
C1: MWG - Working Capital Schedule
C2: Forecast receivables, inventory and payables from explicit days assumptions. Historical values link to 03_Historical_FS / 05_Ratio_Analysis.
A4: Section | B4: Line Item | C4: Unit | D4: 2021A | E4: 2022A | F4: 2023A | G4: 2024A | H4: 2025A | I4: 2026E | J4: 2027E | K4: 2028E | L4: 2029E | M4: 2030E | N4: Method / Source | O4: Notes
A5: WORKING CAPITAL SCHEDULE
A6: Input | B6: Revenue | C6: VND bn | D6: ='03_Historical_FS'!D7 -> 122958.11 | E6: ='03_Historical_FS'!E7 -> 133404.78 | F6: ='03_Historical_FS'!F7 -> 118279.79 | G6: ='03_Historical_FS'!G7 -> 134341.15 | H6: ='03_Historical_FS'!H7 -> 155928.15 | I6: ='08_P5_Assumptions'!I6 -> 185000 | J6: ='08_P5_Assumptions'!J6 -> 210702.27 | K6: ='08_P5_Assumptions'!K6 -> 232016.74 | L6: ='08_P5_Assumptions'!L6 -> 250797.07 | M6: ='08_P5_Assumptions'!M6 -> 267230.44 | N6: Linked | O6: Historical FS / assumptions.
A7: Input | B7: COGS | C7: VND bn | D7: ='03_Historical_FS'!D8 -> 95325.974 | E7: ='03_Historical_FS'!E8 -> 102542.74 | F7: ='03_Historical_FS'!F8 -> 95759.175 | G7: ='03_Historical_FS'!G8 -> 106841.94 | H7: ='03_Historical_FS'!H8 -> 124926.27 | I7: =I6*(1-'08_P5_Assumptions'!I8) -> 147075 | J7: =J6*(1-'08_P5_Assumptions'!J8) -> 166876.2 | K7: =K6*(1-'08_P5_Assumptions'!K8) -> 183293.22 | L7: =L6*(1-'08_P5_Assumptions'!L8) -> 197878.89 | M7: =M6*(1-'08_P5_Assumptions'!M8) -> 210577.59 | N7: Linked / formula | O7: Forecast COGS = Revenue x (1 - Gross Margin).
A8: Days | B8: Inventory Days | C8: days | D8: ='05_Ratio_Analysis'!D21 -> 111.68037 | E8: ='05_Ratio_Analysis'!E21 -> 97.642744 | F8: ='05_Ratio_Analysis'!F21 -> 90.565287 | G8: ='05_Ratio_Analysis'!G21 -> 75.27546 | H8: ='05_Ratio_Analysis'!H21 -> 72.329495 | I8: ='08_P5_Assumptions'!I20 -> 73 | J8: ='08_P5_Assumptions'!J20 -> 72 | K8: ='08_P5_Assumptions'!K20 -> 70 | L8: ='08_P5_Assumptions'!L20 -> 69 | M8: ='08_P5_Assumptions'!M20 -> 68 | N8: Linked | O8: Assumption sheet.
A9: Days | B9: Receivable Days | C9: days | D9: ='05_Ratio_Analysis'!D22 -> 9.3867298 | E9: ='05_Ratio_Analysis'!E22 -> 8.4310058 | F9: ='05_Ratio_Analysis'!F22 -> 12.589978 | G9: ='05_Ratio_Analysis'!G22 -> 18.998027 | H9: ='05_Ratio_Analysis'!H22 -> 22.248027 | I9: ='08_P5_Assumptions'!I21 -> 18 | J9: ='08_P5_Assumptions'!J21 -> 17 | K9: ='08_P5_Assumptions'!K21 -> 16 | L9: ='08_P5_Assumptions'!L21 -> 15 | M9: ='08_P5_Assumptions'!M21 -> 15 | N9: Linked | O9: Assumption sheet.
A10: Days | B10: Payable Days | C10: days | D10: ='05_Ratio_Analysis'!D23 -> 46.635955 | E10: ='05_Ratio_Analysis'!E23 -> 37.242252 | F10: ='05_Ratio_Analysis'!F23 -> 31.775584 | G10: ='05_Ratio_Analysis'!G23 -> 29.220489 | H10: ='05_Ratio_Analysis'!H23 -> 32.567772 | I10: ='08_P5_Assumptions'!I22 -> 33 | J10: ='08_P5_Assumptions'!J22 -> 34 | K10: ='08_P5_Assumptions'!K22 -> 34 | L10: ='08_P5_Assumptions'!L22 -> 34 | M10: ='08_P5_Assumptions'!M22 -> 34 | N10: Linked | O10: Assumption sheet.
A11: Balance | B11: Receivables | C11: VND bn | D11: ='03_Historical_FS'!D31 -> 3162.122 | E11: ='03_Historical_FS'!E31 -> 3000.8175 | F11: ='03_Historical_FS'!F31 -> 5158.8533 | G11: ='03_Historical_FS'!G31 -> 8825.8962 | H11: ='03_Historical_FS'!H31 -> 10182.836 | I11: =I6*I9/365 -> 9123.2877 | J11: =J6*J9/365 -> 9813.5304 | K11: =K6*K9/365 -> 10170.597 | L11: =L6*L9/365 -> 10306.729 | M11: =M6*M9/365 -> 10982.073 | N11: Historical link / formula | O11: Revenue x receivable days / 365.
A12: Balance | B12: Inventory | C12: VND bn | D12: ='03_Historical_FS'!D32 -> 29167.232 | E12: ='03_Historical_FS'!E32 -> 25696.078 | F12: ='03_Historical_FS'!F32 -> 21824.236 | G12: ='03_Historical_FS'!G32 -> 22244.676 | H12: ='03_Historical_FS'!H32 -> 27266.852 | I12: =I7*I8/365 -> 29415 | J12: =J7*J8/365 -> 32918.045 | K12: =K7*K8/365 -> 35152.125 | L12: =L7*L8/365 -> 37407.242 | M12: =M7*M8/365 -> 39230.893 | N12: Historical link / formula | O12: COGS x inventory days / 365.
A13: Balance | B13: Trade Payables | C13: VND bn | D13: ='03_Historical_FS'!D39 -> 12179.775 | E13: ='03_Historical_FS'!E39 -> 8745.8273 | F13: ='03_Historical_FS'!F39 -> 7927.0697 | G13: ='03_Historical_FS'!G39 -> 9179.6361 | H13: ='03_Historical_FS'!H39 -> 13113.9 | I13: =I7*I10/365 -> 13297.192 | J13: =J7*J10/365 -> 15544.632 | K13: =K7*K10/365 -> 17073.889 | L13: =L7*L10/365 -> 18432.554 | M13: =M7*M10/365 -> 19615.447 | N13: Historical link / formula | O13: COGS x payable days / 365.
A14: Balance | B14: Net Working Capital | C14: VND bn | D14: ='03_Historical_FS'!D52 -> 20149.579 | E14: ='03_Historical_FS'!E52 -> 19951.068 | F14: ='03_Historical_FS'!F52 -> 19056.019 | G14: ='03_Historical_FS'!G52 -> 21890.936 | H14: ='03_Historical_FS'!H52 -> 24335.788 | I14: =I11+I12-I13 -> 25241.096 | J14: =J11+J12-J13 -> 27186.943 | K14: =K11+K12-K13 -> 28248.832 | L14: =L11+L12-L13 -> 29281.417 | M14: =M11+M12-M13 -> 30597.52 | N14: Formula | O14: Receivables + Inventory - Trade Payables.
A15: Cash Flow | B15: Change in Net Working Capital | C15: VND bn | E15: =E14-D14 -> -198.51162 | F15: =F14-E14 -> -895.04863 | G15: =G14-F14 -> 2834.9173 | H15: =H14-G14 -> 2444.8518 | I15: =I14-H14 -> 905.30761 | J15: =J14-I14 -> 1945.8469 | K15: =K14-J14 -> 1061.8894 | L15: =L14-K14 -> 1032.585 | M15: =M14-L14 -> 1316.1024 | N15: Formula | O15: Positive value is cash outflow in CFO.
A16: Days | B16: Cash Conversion Cycle | C16: days | D16: =D8+D9-D10 -> 74.431142 | E16: =E8+E9-E10 -> 68.831498 | F16: =F8+F9-F10 -> 71.379681 | G16: =G8+G9-G10 -> 65.052998 | H16: =H8+H9-H10 -> 62.00975 | I16: =I8+I9-I10 -> 58 | J16: =J8+J9-J10 -> 55 | K16: =K8+K9-K10 -> 52 | ... M16: =M8+M9-M10 -> 49 | N16: Formula | O16: Inventory days + receivable days - payable days.

Sheet 10_Debt_Cash_Interest
A1: MWG - Debt, Cash and Interest Schedule
A2: Forecast debt using debt/revenue ratio and interest using implied borrowing cost. Liquid funds link from the balance sheet.
A4: Section | B4: Line Item | C4: Unit | D4: 2021A | E4: 2022A | F4: 2023A | G4: 2024A | H4: 2025A | I4: 2026E | J4: 2027E | K4: 2028E | L4: 2029E | M4: 2030E | N4: Method / Source | O4: Notes
A5: DEBT, CASH AND INTEREST
A6: Input | B6: Revenue | C6: VND bn | D6: ='03_Historical_FS'!D7 -> 122958.11 | E6: ='03_Historical_FS'!E7 -> 133404.78 | F6: ='03_Historical_FS'!F7 -> 118279.79 | G6: ='03_Historical_FS'!G7 -> 134341.15 | H6: ='03_Historical_FS'!H7 -> 155928.15 | I6: ='08_P5_Assumptions'!I6 -> 185000 | J6: ='08_P5_Assumptions'!J6 -> 210702.27 | K6: ='08_P5_Assumptions'!K6 -> 232016.74 | L6: ='08_P5_Assumptions'!L6 -> 250797.07 | M6: ='08_P5_Assumptions'!M6 -> 267230.44 | N6: Linked | O6: Historical FS / assumptions.
A7: Debt | B7: Total Debt | C7: VND bn | D7: ='03_Historical_FS'!D50 -> 24647.474 | E7: ='03_Historical_FS'!E50 -> 16589.389 | F7: ='03_Historical_FS'!F50 -> 25113.792 | G7: ='03_Historical_FS'!G50 -> 27300.247 | H7: ='03_Historical_FS'!H50 -> 29930.943 | I7: =I6*'08_P5_Assumptions'!I23 -> 35150 | J7: =J6*'08_P5_Assumptions'!J23 -> 37926.409 | K7: =K6*'08_P5_Assumptions'!K23 -> 39442.845 | L7: =L6*'08_P5_Assumptions'!L23 -> 40127.532 | M7: =M6*'08_P5_Assumptions'!M23 -> 40084.566 | N7: Historical link / formula | O7: Forecast = revenue x debt/revenue.
A8: Debt | B8: Debt / Revenue | C8: % | D8: =IFERROR(D7/D6,"") -> 0.20045424 | E8: =IFERROR(E7/E6,"") -> 0.12435378 | F8: =IFERROR(F7/F6,"") -> 0.2123253 | G8: =IFERROR(G7/G6,"") -> 0.20321581 | H8: =IFERROR(H7/H6,"") -> 0.19195343 | I8: =IFERROR(I7/I6,"") -> 0.19 | J8: =IFERROR(J7/J6,"") -> 0.18 | K8: =IFERROR(K7/K6,"") -> 0.17 | ... M8: =IFERROR(M7/M6,"") -> 0.15 | N8: Formula | O8: Debt intensity.
A9: Debt | B9: Average Debt | C9: VND bn | D9: =D7 -> 24647.474 | E9: =AVERAGE(D7,E7) -> 20618.431 | F9: =AVERAGE(E7,F7) -> 20851.59 | G9: =AVERAGE(F7,G7) -> 26207.019 | H9: =AVERAGE(G7,H7) -> 28615.595 | I9: =AVERAGE(H7,I7) -> 32540.471 | J9: =AVERAGE(I7,J7) -> 36538.204 | K9: =AVERAGE(J7,K7) -> 38684.627 | L9: =AVERAGE(K7,L7) -> 39785.188 | M9: =AVERAGE(L7,M7) -> 40106.049 | N9: Formula | O9: Average current and prior year debt.
A10: Interest | B10: Interest Rate | C10: % | D10: ='08_P5_Assumptions'!D12 -> 0.027362956 | E10: ='08_P5_Assumptions'!E12 -> 0.066064381 | F10: ='08_P5_Assumptions'!F12 -> 0.069429638 | G10: ='08_P5_Assumptions'!G12 -> 0.043394333 | H10: ='08_P5_Assumptions'!H12 -> 0.0513942 | I10: ='08_P5_Assumptions'!I12 -> 0.052 | J10: ='08_P5_Assumptions'!J12 -> 0.052 | K10: ='08_P5_Assumptions'!K12 -> 0.051 | ... M10: ='08_P5_Assumptions'!M12 -> 0.05 | N10: Linked | O10: Assumption sheet.
A11: Interest | B11: Interest Expense | C11: VND bn | D11: ='03_Historical_FS'!D13 -> 674.42775 | E11: ='03_Historical_FS'!E13 -> 1362.1439 | F11: ='03_Historical_FS'!F13 -> 1447.7184 | G11: ='03_Historical_FS'!G13 -> 1137.2361 | H11: ='03_Historical_FS'!H13 -> 1470.6756 | I11: =I9*I10 -> 1692.1045 | J11: =J9*J10 -> 1899.9866 | K11: =K9*K10 -> 1972.916 | L11: =L9*L10 -> 1989.2594 | M11: =M9*M10 -> 2005.3024 | N11: Historical link / formula | O11: Forecast = average debt x interest rate.
A12: Finance Income | B12: Financial Income / Revenue | C12: % | D12: ='08_P5_Assumptions'!D11 -> 0.010474755 | E12: ='08_P5_Assumptions'!E11 -> 0.0098432554 | F12: ='08_P5_Assumptions'!F11 -> 0.018320659 | G12: ='08_P5_Assumptions'!G11 -> 0.017690057 | H12: ='08_P5_Assumptions'!H11 -> 0.019928081 | I12: ='08_P5_Assumptions'!I11 -> 0.017 | J12: ='08_P5_Assumptions'!J11 -> 0.016 | K12: ='08_P5_Assumptions'!K11 -> 0.015 | ... M12: ='08_P5_Assumptions'!M11 -> 0.013 | N12: Linked | O12: Assumption sheet.
A13: Finance Income | B13: Financial Income | C13: VND bn | D13: ='03_Historical_FS'!D11 -> 1287.956 | E13: ='03_Historical_FS'!E11 -> 1313.1373 | F13: ='03_Historical_FS'!F11 -> 2166.9637 | G13: ='03_Historical_FS'!G11 -> 2376.5026 | H13: ='03_Historical_FS'!H11 -> 3107.3487 | I13: =I6*I12 -> 3145 | J13: =J6*J12 -> 3371.2363 | K13: =K6*K12 -> 3480.251 | L13: =L6*L12 -> 3511.159 | M13: =M6*M12 -> 3473.9957 | N13: Historical link / formula | O13: Forecast = revenue x financial income/revenue.
A14: Liquidity | B14: Cash + Short-term Investments | C14: VND bn | D14: ='03_Historical_FS'!D29+'03_Historical_FS'!D30 -> 18378.642 | E14: ='03_Historical_FS'!E29+'03_Historical_FS'!E30 -> 15130.27 | F14: ='03_Historical_FS'!F29+'03_Historical_FS'!F30 -> 24302.713 | G14: ='03_Historical_FS'!G29+'03_Historical_FS'!G30 -> 34221.773 | H14: ='03_Historical_FS'!H29+'03_Historical_FS'!H30 -> 38874.196 | I14: ='13_Balance_Sheet'!I6 -> 52287.348 | J14: ='13_Balance_Sheet'!J6 -> 62917.078 | K14: ='13_Balance_Sheet'!K6 -> 74340.382 | L14: ='13_Balance_Sheet'!L6 -> 86675.829 | M14: ='13_Balance_Sheet'!M6 -> 98590.767 | N14: Linked | O14: Balance sheet liquid funds plug.
A15: Liquidity | B15: Net Debt | C15: VND bn | D15: =D7-D14 -> 6268.8322 | E15: =E7-E14 -> 1459.1185 | F15: =F7-F14 -> 811.07889 | G15: =G7-G14 -> -6921.5266 | H15: =H7-H14 -> -8943.2529 | I15: =I7-I14 -> -17137.348 | J15: =J7-J14 -> -24990.669 | K15: =K7-K14 -> -34897.537 | ... M15: =M7-M14 -> -58506.201 | N15: Formula | O15: Total debt - cash and short-term investments.

Sheet 11_Capex_DA
A1: MWG - Capex and D&A Schedule
A2: Forecast capex and depreciation from visible revenue-based assumptions. Fixed assets roll forward from 2025 actual.
A4: Section | B4: Line Item | C4: Unit | D4: 2021A | E4: 2022A | F4: 2023A | G4: 2024A | H4: 2025A | I4: 2026E | J4: 2027E | K4: 2028E | L4: 2029E | M4: 2030E | N4: Method / Source | O4: Notes
A5: CAPEX AND FIXED ASSET ROLL-FORWARD
A6: Input | B6: Revenue | C6: VND bn | D6: ='03_Historical_FS'!D7 -> 122958.11 | E6: ='03_Historical_FS'!E7 -> 133404.78 | F6: ='03_Historical_FS'!F7 -> 118279.79 | G6: ='03_Historical_FS'!G7 -> 134341.15 | H6: ='03_Historical_FS'!H7 -> 155928.15 | I6: ='08_P5_Assumptions'!I6 -> 185000 | J6: ='08_P5_Assumptions'!J6 -> 210702.27 | K6: ='08_P5_Assumptions'!K6 -> 232016.74 | L6: ='08_P5_Assumptions'!L6 -> 250797.07 | M6: ='08_P5_Assumptions'!M6 -> 267230.44 | N6: Linked | O6: Historical FS / assumptions.
A7: Input | B7: Capex / Revenue | C7: % | D7: =IFERROR(ABS('03_Historical_FS'!D59)/'03_Historical_FS'!D7,"") -> 0.040476198 | E7: =IFERROR(ABS('03_Historical_FS'!E59)/'03_Historical_FS'!E7,"") -> 0.033472261 | F7: =IFERROR(ABS('03_Historical_FS'!F59)/'03_Historical_FS'!F7,"") -> 0.00442496 | G7: =IFERROR(ABS('03_Historical_FS'!G59)/'03_Historical_FS'!G7,"") -> 0.0022610185 | H7: =IFERROR(ABS('03_Historical_FS'!H59)/'03_Historical_FS'!H7,"") -> 0.005697893 | I7: ='08_P5_Assumptions'!I32 -> 0.012 | J7: ='08_P5_Assumptions'!J32 -> 0.012 | K7: ='08_P5_Assumptions'!K32 -> 0.011 | L7: ='08_P5_Assumptions'!L32 -> 0.01 | M7: ='08_P5_Assumptions'!M32 -> 0.01 | N7: Linked | O7: Assumption sheet.
A8: Cash Flow | B8: Capex (Positive Outflow) | C8: VND bn | D8: =ABS('03_Historical_FS'!D59) -> 4976.8766 | E8: =ABS('03_Historical_FS'!E59) -> 4465.3595 | F8: =ABS('03_Historical_FS'!F59) -> 523.38333 | G8: =ABS('03_Historical_FS'!G59) -> 303.74783 | H8: =ABS('03_Historical_FS'!H59) -> 888.46189 | I8: =I6*I7 -> 2220 | J8: =J6*J7 -> 2528.4272 | K8: =K6*K7 -> 2552.1841 | L8: =L6*L7 -> 2507.9707 | M8: =M6*M7 -> 2672.3044 | N8: Historical link / formula | O8: Positive presentation; cash flow sheet shows it as outflow.
A9: Input | B9: D&A / Revenue | C9: % | D9: =IFERROR('03_Historical_FS'!D55/'03_Historical_FS'!D7,"") -> 0.02375373 | E9: =IFERROR('03_Historical_FS'!E55/'03_Historical_FS'!E7,"") -> 0.026538215 | F9: =IFERROR('03_Historical_FS'!F55/'03_Historical_FS'!F7,"") -> 0.028333786 | G9: =IFERROR('03_Historical_FS'!G55/'03_Historical_FS'!G7,"") -> 0.021686721 | H9: =IFERROR('03_Historical_FS'!H55/'03_Historical_FS'!H7,"") -> 0.012126625 | I9: ='08_P5_Assumptions'!I33 -> 0.0115 | J9: ='08_P5_Assumptions'!J33 -> 0.011 | K9: ='08_P5_Assumptions'!K33 -> 0.0105 | L9: ='08_P5_Assumptions'!L33 -> 0.01 | M9: ='08_P5_Assumptions'!M33 -> 0.0095 | N9: Linked | O9: Assumption sheet.
A10: P&L | B10: D&A | C10: VND bn | D10: ='03_Historical_FS'!D55 -> 2920.7136 | E10: ='03_Historical_FS'!E55 -> 3540.3247 | F10: ='03_Historical_FS'!F55 -> 3351.3143 | G10: ='03_Historical_FS'!G55 -> 2913.4191 | H10: ='03_Historical_FS'!H55 -> 1890.8821 | I10: =I6*I9 -> 2127.5 | J10: =J6*J9 -> 2317.725 | K10: =K6*K9 -> 2436.1757 | L10: =L6*L9 -> 2507.9707 | M10: =M6*M9 -> 2538.6892 | N10: Historical link / formula | O10: Revenue x D&A / revenue.
A11: Balance | B11: Beginning Fixed Assets | C11: VND bn | E11: =D12 -> 9647.1689 | F11: =E12 -> 9727.5029 | G11: =F12 -> 6500.1356 | H11: =G12 -> 3586.6287 | I11: =H12 -> 2598.1892 | J11: =I12 -> 2690.6892 | K11: =J12 -> 2901.3915 | L11: =K12 -> 3017.3999 | M11: =L12 -> 3017.3999 | N11: Formula | O11: Prior year ending fixed assets.
A12: Balance | B12: Ending Fixed Assets | C12: VND bn | D12: ='03_Historical_FS'!D35 -> 9647.1689 | E12: ='03_Historical_FS'!E35 -> 9727.5029 | F12: ='03_Historical_FS'!F35 -> 6500.1356 | G12: ='03_Historical_FS'!G35 -> 3586.6287 | H12: ='03_Historical_FS'!H35 -> 2598.1892 | I12: =I11+I8-I10 -> 2690.6892 | J12: =J11+J8-J10 -> 2901.3915 | K12: =K11+K8-K10 -> 3017.3999 | L12: =L11+L8-L10 -> 3017.3999 | M12: =M11+M8-M10 -> 3151.0151 | N12: Historical link / roll-forward | O12: Forecast = beginning fixed assets + capex - D&A.
A13: Check | B13: Historical Fixed Asset Check | C13: VND bn | D13: =D12-'03_Historical_FS'!D35 -> 0 | E13: =E12-'03_Historical_FS'!E35 -> 0 | F13: =F12-'03_Historical_FS'!F35 -> 0 | G13: =G12-'03_Historical_FS'!G35 -> 0 | H13: =H12-'03_Historical_FS'!H35 -> 0 | I13: =I12-I12 -> 0 | J13: =J12-J12 -> 0 | K13: =K12-K12 -> 0 | L13: =L12-L12 -> 0 | M13: =M12-M12 -> 0 | N13: Formula | O13: Historical only: ending fixed assets - raw historical fixed assets.

Sheet 12_Income_Statement
A1: MWG - Forecast Income Statement
A2: Integrated group-level income statement. Historical data links to 03_Historical_FS; 2026E-2030E flows from assumptions and schedules.
A4: Section | B4: Line Item | C4: Unit | D4: 2021A | E4: 2022A | F4: 2023A | G4: 2024A | H4: 2025A | I4: 2026E | J4: 2027E | K4: 2028E | L4: 2029E | M4: 2030E | N4: Method / Source | O4: Notes
A5: INCOME STATEMENT
A6: Revenue | B6: Revenue | C6: VND bn | D6: ='03_Historical_FS'!D7 -> 122958.11 | E6: ='03_Historical_FS'!E7 -> 133404.78 | F6: ='03_Historical_FS'!F7 -> 118279.79 | G6: ='03_Historical_FS'!G7 -> 134341.15 | H6: ='03_Historical_FS'!H7 -> 155928.15 | I6: ='08_P5_Assumptions'!I6 -> 185000 | J6: ='08_P5_Assumptions'!J6 -> 210702.27 | K6: ='08_P5_Assumptions'!K6 -> 232016.74 | L6: ='08_P5_Assumptions'!L6 -> 250797.07 | M6: ='08_P5_Assumptions'!M6 -> 267230.44 | N6: Linked
A7: Revenue | B7: Revenue Growth | C7: % | E7: =IFERROR(E6/D6-1,"") -> 0.084961226 | F7: =IFERROR(F6/E6-1,"") -> -0.11337667 | G7: =IFERROR(G6/F6-1,"") -> 0.13579128 | H7: =IFERROR(H6/G6-1,"") -> 0.16068786 | I7: =IFERROR(I6/H6-1,"") -> 0.18644392 | J7: =IFERROR(J6/I6-1,"") -> 0.13893119 | K7: =IFERROR(K6/J6-1,"") -> 0.10115916 | L7: =IFERROR(L6/K6-1,"") -> 0.08094389 | M7: =IFERROR(M6/L6-1,"") -> 0.065524566 | N7: Formula | O7: Implied growth.
A8: Gross Profit | B8: Gross Profit | C8: VND bn | D8: ='03_Historical_FS'!D9 -> 27632.132 | E8: ='03_Historical_FS'!E9 -> 30862.042 | F8: ='03_Historical_FS'!F9 -> 22520.613 | G8: ='03_Historical_FS'!G9 -> 27499.21 | H8: ='03_Historical_FS'!H9 -> 31001.877 | I8: =I6*I9 -> 37925 | J8: =J6*J9 -> 43826.072 | K8: =K6*K9 -> 48723.514 | L8: =L6*L9 -> 52918.182 | M8: =M6*M9 -> 56652.854 | N8: Historical link / formula | O8: Revenue x gross margin.
A9: Gross Profit | B9: Gross Margin | C9: % | D9: ='03_Historical_FS'!D10 -> 0.22472802 | E9: ='03_Historical_FS'!E10 -> 0.23134136 | F9: ='03_Historical_FS'!F10 -> 0.1904012 | G9: ='03_Historical_FS'!G10 -> 0.20469684 | H9: ='03_Historical_FS'!H10 -> 0.19882156 | I9: ='08_P5_Assumptions'!I8 -> 0.205 | J9: ='08_P5_Assumptions'!J8 -> 0.208 | K9: ='08_P5_Assumptions'!K8 -> 0.21 | L9: ='08_P5_Assumptions'!L8 -> 0.211 | M9: ='08_P5_Assumptions'!M8 -> 0.212 | N9: Linked | O9: Assumption sheet.
A10: COGS | B10: COGS | C10: VND bn | D10: ='03_Historical_FS'!D8 -> 95325.974 | E10: ='03_Historical_FS'!E8 -> 102542.74 | F10: ='03_Historical_FS'!F8 -> 95759.175 | G10: ='03_Historical_FS'!G8 -> 106841.94 | H10: ='03_Historical_FS'!H8 -> 124926.27 | I10: =I6-I8 -> 147075 | J10: =J6-J8 -> 166876.2 | K10: =K6-K8 -> 183293.22 | L10: =L6-L8 -> 197878.89 | M10: =M6-M8 -> 210577.59 | N10: Historical link / formula | O10: Revenue - gross profit.
A11: Opex | B11: Selling Expenses | C11: VND bn | D11: ='03_Historical_FS'!D14 -> 17914.173 | E11: ='03_Historical_FS'!E14 -> 22336.838 | F11: ='03_Historical_FS'!F14 -> 20916.711 | G11: ='03_Historical_FS'!G14 -> 19849.838 | H11: ='03_Historical_FS'!H14 -> 19330.904 | I11: =I6*'08_P5_Assumptions'!I9 -> 22570 | J11: =J6*'08_P5_Assumptions'!J9 -> 25284.272 | K11: =K6*'08_P5_Assumptions'!K9 -> 27377.975 | L11: =L6*'08_P5_Assumptions'!L9 -> 29092.46 | M11: =M6*'08_P5_Assumptions'!M9 -> 30731.501 | N11: Historical link / formula | O11: Revenue x selling expense ratio.
A12: Opex | B12: Selling Expenses / Revenue | C12: % | D12: =IFERROR(D11/D6,"") -> 0.14569331 | E12: =IFERROR(E11/E6,"") -> 0.16743657 | F12: =IFERROR(F11/F6,"") -> 0.17684096 | G12: =IFERROR(G11/G6,"") -> 0.14775694 | H12: =IFERROR(H11/H6,"") -> 0.12397315 | I12: =IFERROR(I11/I6,"") -> 0.122 | J12: =IFERROR(J11/J6,"") -> 0.12 | K12: =IFERROR(K11/K6,"") -> 0.118 | ... M12: =IFERROR(M11/M6,"") -> 0.115 | N12: Formula | O12: Check ratio.
A13: Opex | B13: G&A Expenses | C13: VND bn | D13: ='03_Historical_FS'!D15 -> 3823.3901 | E13: ='03_Historical_FS'!E15 -> 1881.0276 | F13: ='03_Historical_FS'!F15 -> 1167.6517 | G13: ='03_Historical_FS'!G15 -> 3565.7676 | H13: ='03_Historical_FS'!H15 -> 4596.0745 | I13: =I6*'08_P5_Assumptions'!I10 -> 5180 | J13: =J6*'08_P5_Assumptions'!J10 -> 5688.9613 | K13: =K6*'08_P5_Assumptions'!K10 -> 6032.4351 | L13: =L6*'08_P5_Assumptions'!L10 -> 6269.9268 | M13: =M6*'08_P5_Assumptions'!M10 -> 6680.7611 | N13: Historical link / formula | O13: Revenue x G&A ratio.
A14: Opex | B14: G&A Expenses / Revenue | C14: % | D14: =IFERROR(D13/D6,"") -> 0.031095063 | E14: =IFERROR(E13/E6,"") -> 0.014100152 | F14: =IFERROR(F13/F6,"") -> 0.0098719458 | G14: =IFERROR(G13/G6,"") -> 0.026542631 | H14: =IFERROR(H13/H6,"") -> 0.029475593 | I14: =IFERROR(I13/I6,"") -> 0.028 | J14: =IFERROR(J13/J6,"") -> 0.027 | K14: =IFERROR(K13/K6,"") -> 0.026 | ... M14: =IFERROR(M13/M6,"") -> 0.025 | N14: Formula | O14: Check ratio.
A15: EBIT | B15: EBIT | C15: VND bn | D15: ='03_Historical_FS'!D17 -> 6465.6069 | E15: ='03_Historical_FS'!E17 -> 6574.6937 | F15: ='03_Historical_FS'!F17 -> 1047.0684 | G15: ='03_Historical_FS'!G17 -> 5227.0454 | H15: ='03_Historical_FS'!H17 -> 8664.0805 | I15: =I8-I11-I13 -> 10175 | J15: =J8-J11-J13 -> 12852.838 | K15: =K8-K11-K13 -> 15313.105 | L15: =L8-L11-L13 -> 17555.795 | M15: =M8-M11-M13 -> 19240.592 | N15: Historical link / formula | O15: Gross profit - selling expenses - G&A expenses.
A16: EBIT | B16: EBIT Margin | C16: % | D16: =IFERROR(D15/D6,"") -> 0.05258382 | E16: =IFERROR(E15/E6,"") -> 0.049283795 | F16: =IFERROR(F15/F6,"") -> 0.0088524706 | G16: =IFERROR(G15/G6,"") -> 0.038908743 | H16: =IFERROR(H15/H6,"") -> 0.055564571 | I16: =IFERROR(I15/I6,"") -> 0.055 | J16: =IFERROR(J15/J6,"") -> 0.061 | K16: =IFERROR(K15/K6,"") -> 0.066 | ... M16: =IFERROR(M15/M6,"") -> 0.072 | N16: Formula | O16: EBIT / revenue.
A17: Finance | B17: Financial Income | C17: VND bn | D17: ='03_Historical_FS'!D11 -> 1287.956 | E17: ='03_Historical_FS'!E11 -> 1313.1373 | F17: ='03_Historical_FS'!F11 -> 2166.9637 | G17: ='03_Historical_FS'!G11 -> 2376.5026 | H17: ='03_Historical_FS'!H11 -> 3107.3487 | I17: ='10_Debt_Cash_Interest'!I13 -> 3145 | J17: ='10_Debt_Cash_Interest'!J13 -> 3371.2363 | K17: ='10_Debt_Cash_Interest'!K13 -> 3480.251 | L17: ='10_Debt_Cash_Interest'!L13 -> 3511.159 | M17: ='10_Debt_Cash_Interest'!M13 -> 3473.9957 | N17: Historical link / schedule | O17: Debt/cash/interest schedule.
A18: Finance | B18: Interest Expense | C18: VND bn | D18: ='03_Historical_FS'!D13 -> 674.42775 | E18: ='03_Historical_FS'!E13 -> 1362.1439 | F18: ='03_Historical_FS'!F13 -> 1447.7184 | G18: ='03_Historical_FS'!G13 -> 1137.2361 | H18: ='03_Historical_FS'!H13 -> 1470.6756 | I18: ='10_Debt_Cash_Interest'!I11 -> 1692.1045 | J18: ='10_Debt_Cash_Interest'!J11 -> 1899.9866 | K18: ='10_Debt_Cash_Interest'!K11 -> 1972.916 | L18: ='10_Debt_Cash_Interest'!L11 -> 1989.2594 | M18: ='10_Debt_Cash_Interest'!M11 -> 2005.3024 | N18: Historical link / schedule | O18: Debt/cash/interest schedule.
A19: Other | B19: Other Profit | C19: VND bn | D19: ='03_Historical_FS'!D19 -> 5.9768322 | E19: ='03_Historical_FS'!E19 -> -518.33833 | F19: ='03_Historical_FS'!F19 -> -357.37599 | G19: ='03_Historical_FS'!G19 -> -401.28241 | H19: ='03_Historical_FS'!H19 -> -31.012906 | I19: =I6*'08_P5_Assumptions'!I13 -> 0 | J19: =J6*'08_P5_Assumptions'!J13 -> 0 | K19: =K6*'08_P5_Assumptions'!K13 -> 0 | L19: =L6*'08_P5_Assumptions'!L13 -> 0 | M19: =M6*'08_P5_Assumptions'!M13 -> 0 | N19: Historical link / formula | O19: Revenue x other profit / revenue.
A20: PBT | B20: Profit Before Tax | C20: VND bn | D20: ='03_Historical_FS'!D20 -> 6471.5838 | E20: ='03_Historical_FS'!E20 -> 6056.3554 | F20: ='03_Historical_FS'!F20 -> 689.69237 | G20: ='03_Historical_FS'!G20 -> 4825.763 | H20: ='03_Historical_FS'!H20 -> 8633.0676 | I20: =I15+I17-I18+I19 -> 11627.895 | J20: =J15+J17-J18+J19 -> 14324.088 | K20: =K15+K17-K18+K19 -> 16820.44 | L20: =L15+L17-L18+L19 -> 19077.695 | M20: =M15+M17-M18+M19 -> 20709.285 | N20: Historical link / formula | O20: EBIT + financial income - interest expense + other profit.
A21: Tax | B21: Tax Expense | C21: VND bn | D21: ='03_Historical_FS'!D23 -> 1570.1571 | E21: ='03_Historical_FS'!E23 -> 1954.6409 | F21: ='03_Historical_FS'!F23 -> 521.86321 | G21: ='03_Historical_FS'!G23 -> 1092.4748 | H21: ='03_Historical_FS'!H23 -> 1560.4447 | I21: =I20*'08_P5_Assumptions'!I14 -> 2325.5791 | J21: =J20*'08_P5_Assumptions'!J14 -> 2864.8176 | K21: =K20*'08_P5_Assumptions'!K14 -> 3364.0879 | L21: =L20*'08_P5_Assumptions'!L14 -> 3815.5389 | M21: =M20*'08_P5_Assumptions'!M14 -> 4141.857 | N21: Historical link / formula | O21: PBT x effective tax rate.
A22: Tax | B22: Effective Tax Rate | C22: % | D22: =IFERROR(D21/D20,"") -> 0.24262331 | E22: =IFERROR(E21/E20,"") -> 0.32274212 | F22: =IFERROR(F21/F20,"") -> 0.75666085 | G22: =IFERROR(G21/G20,"") -> 0.22638384 | H22: =IFERROR(H21/H20,"") -> 0.18075205 | I22: =IFERROR(I21/I20,"") -> 0.2 | J22: =IFERROR(J21/J20,"") -> 0.2 | K22: =IFERROR(K21/K20,"") -> 0.2 | ... M22: =IFERROR(M21/M20,"") -> 0.2 | N22: Formula | O22: Tax / PBT.
A23: NPAT | B23: NPAT | C23: VND bn | D23: ='03_Historical_FS'!D24 -> 4901.4267 | E23: ='03_Historical_FS'!E24 -> 4101.7144 | F23: ='03_Historical_FS'!F24 -> 167.82915 | G23: ='03_Historical_FS'!G24 -> 3733.2882 | H23: ='03_Historical_FS'!H24 -> 7072.6229 | I23: =I20-I21 -> 9302.3164 | J23: =J20-J21 -> 11459.271 | K23: =K20-K21 -> 13456.352 | L23: =L20-L21 -> 15262.156 | M23: =M20-M21 -> 16567.428 | N23: Historical link / formula | O23: PBT - tax.
A24: NPAT | B24: Minority Interest | C24: VND bn | D24: ='03_Historical_FS'!D25 -> 2.5573957 | E24: ='03_Historical_FS'!E25 -> 1.951398 | F24: ='03_Historical_FS'!F25 -> 0.159762 | G24: ='03_Historical_FS'!G25 -> 11.419787 | H24: ='03_Historical_FS'!H25 -> 38.892116 | I24: =I23*'08_P5_Assumptions'!I15 -> 55.813898 | J24: =J23*'08_P5_Assumptions'!J15 -> 74.485258 | K24: =K23*'08_P5_Assumptions'!K15 -> 94.194462 | L24: =L23*'08_P5_Assumptions'!L15 -> 114.46617 | M24: =M23*'08_P5_Assumptions'!M15 -> 132.53942 | N24: Historical link / formula | O24: NPAT x minority interest ratio.
A25: NPATMI | B25: NPATMI | C25: VND bn | D25: ='03_Historical_FS'!D26 -> 4898.8693 | E25: ='03_Historical_FS'!E26 -> 4099.763 | F25: ='03_Historical_FS'!F26 -> 167.66939 | G25: ='03_Historical_FS'!G26 -> 3721.8684 | H25: ='03_Historical_FS'!H26 -> 7033.7308 | I25: =I23-I24 -> 9246.5025 | J25: =J23-J24 -> 11384.785 | K25: =K23-K24 -> 13362.157 | L25: =L23-L24 -> 15147.69 | M25: =M23-M24 -> 16434.889 | N25: Historical link / formula | O25: NPAT - minority interest.
A26: NPATMI | B26: NPATMI Margin | C26: % | D26: =IFERROR(D25/D6,"") -> 0.039841776 | E26: =IFERROR(E25/E6,"") -> 0.030731756 | F26: =IFERROR(F25/F6,"") -> 0.0014175659 | G26: =IFERROR(G25/G6,"") -> 0.027704604 | H26: =IFERROR(H25/H6,"") -> 0.045108795 | I26: =IFERROR(I25/I6,"") -> 0.049981095 | J26: =IFERROR(J25/J6,"") -> 0.054032571 | K26: =IFERROR(K25/K6,"") -> 0.057591351 | ... M26: =IFERROR(M25/M6,"") -> 0.06150081 | N26: Formula | O26: NPATMI / revenue.
A27: D&A | B27: D&A | C27: VND bn | D27: ='03_Historical_FS'!D55 -> 2920.7136 | E27: ='03_Historical_FS'!E55 -> 3540.3247 | F27: ='03_Historical_FS'!F55 -> 3351.3143 | G27: ='03_Historical_FS'!G55 -> 2913.4191 | H27: ='03_Historical_FS'!H55 -> 1890.8821 | I27: ='11_Capex_DA'!I10 -> 2127.5 | J27: ='11_Capex_DA'!J10 -> 2317.725 | K27: ='11_Capex_DA'!K10 -> 2436.1757 | L27: ='11_Capex_DA'!L10 -> 2507.9707 | M27: ='11_Capex_DA'!M10 -> 2538.6892 | N27: Schedule | O27: Capex and D&A schedule.
A28: EBITDA | B28: EBITDA | C28: VND bn | D28: ='03_Historical_FS'!D69 -> 9386.3205 | E28: ='03_Historical_FS'!E69 -> 10115.018 | F28: ='03_Historical_FS'!F69 -> 4398.3826 | G28: ='03_Historical_FS'!G69 -> 8140.4645 | H28: ='03_Historical_FS'!H69 -> 10554.963 | I28: =I15+I27 -> 12302.5 | J28: =J15+J27 -> 15170.563 | K28: =K15+K27 -> 17749.28 | L28: =L15+L27 -> 20063.766 | M28: =M15+M27 -> 21779.281 | N28: Formula | O28: EBIT + D&A.

Sheet 13_Balance_Sheet
A1: MWG - Forecast Balance Sheet
A4: Section | B4: Line Item | C4: Unit | D4: 2021A | E4: 2022A | F4: 2023A | G4: 2024A | H4: 2025A | I4: 2026E | J4: 2027E | K4: 2028E | L4: 2029E | M4: 2030E | N4: Method / Source | O4: Notes
A5: BALANCE SHEET
A6: Current Assets | B6: Cash + Short-term Investments | C6: VND bn | D6: ='03_Historical_FS'!D29+'03_Historical_FS'!D30 -> 18378.642 | E6: ='03_Historical_FS'!E29+'03_Historical_FS'!E30 -> 15130.27 | F6: ='03_Historical_FS'!F29+'03_Historical_FS'!F30 -> 24302.713 | G6: ='03_Historical_FS'!G29+'03_Historical_FS'!G30 -> 34221.773 | H6: ='03_Historical_FS'!H29+'03_Historical_FS'!H30 -> 38874.196 | I6: =I27-(I9+I10+I11+I13+I14+I15) -> 52287.348 | J6: =J27-(J9+J10+J11+J13+J14+J15) -> 62917.078 | K6: =K27-(K9+K10+K11+K13+K14+K15) -> 74340.382 | L6: =L27-(L9+L10+L11+L13+L14+L15) -> 86675.829 | M6: =M27-(M9+M10+M11+M13+M14+M15) -> 98590.767 | N6: Historical link / plug | O6: Forecast balancing item for liquid funds; used for net debt.
A7: Current Assets | B7: Cash & Cash Equivalents | C7: VND bn | D7: ='03_Historical_FS'!D29 -> 4142.0158 | E7: ='03_Historical_FS'!E29 -> 5061.0205 | F7: ='03_Historical_FS'!F29 -> 5365.7049 | G7: ='03_Historical_FS'!G29 -> 4897.3315 | H7: ='03_Historical_FS'!H29 -> 4999.9257 | I7: =I6*'03_Historical_FS'!$H$29/('03_Historical_FS'!$H$29+'03_Historical_FS'!$H$30) -> 6725.1001 | J7: =J6*'03_Historical_FS'!$H$29/('03_Historical_FS'!$H$29+'03_Historical_FS'!$H$30) -> 8092.2758 | K7: =K6*'03_Historical_FS'!$H$29/('03_Historical_FS'!$H$29+'03_Historical_FS'!$H$30) -> 9561.5196 | L7: =L6*'03_Historical_FS'!$H$29/('03_Historical_FS'!$H$29+'03_Historical_FS'!$H$30) -> 11148.082 | M7: =M6*'03_Historical_FS'!$H$29/('03_Historical_FS'!$H$29+'03_Historical_FS'!$H$30) -> 12680.558 | N7: Historical link / split | O7: Forecast informational split using 2025 cash/liquid funds mix.
A8: Current Assets | B8: Short-term Financial Investments | C8: VND bn | D8: ='03_Historical_FS'!D30 -> 14236.626 | E8: ='03_Historical_FS'!E30 -> 10069.25 | F8: ='03_Historical_FS'!F30 -> 18937.008 | G8: ='03_Historical_FS'!G30 -> 29324.442 | H8: ='03_Historical_FS'!H30 -> 33874.27 | I8: =I6-I7 -> 45562.248 | J8: =J6-J7 -> 54824.802 | K8: =K6-K7 -> 64778.862 | L8: =L6-L7 -> 75527.748 | M8: =M6-M7 -> 85910.209 | N8: Historical link / split | O8: Forecast informational split; row 6 is the model driver.
A9: Current Assets | B9: Receivables | C9: VND bn | D9: ='03_Historical_FS'!D31 -> 3162.122 | E9: ='03_Historical_FS'!E31 -> 3000.8175 | F9: ='03_Historical_FS'!F31 -> 5158.8533 | G9: ='03_Historical_FS'!G31 -> 8825.8962 | H9: ='03_Historical_FS'!H31 -> 10182.836 | I9: ='09_Working_Capital'!I11 -> 9123.2877 | J9: ='09_Working_Capital'!J11 -> 9813.5304 | K9: ='09_Working_Capital'!K11 -> 10170.597 | L9: ='09_Working_Capital'!L11 -> 10306.729 | M9: ='09_Working_Capital'!M11 -> 10982.073 | N9: Working capital schedule | O9: Revenue x receivable days.
A10: Current Assets | B10: Inventory | C10: VND bn | D10: ='03_Historical_FS'!D32 -> 29167.232 | E10: ='03_Historical_FS'!E32 -> 25696.078 | F10: ='03_Historical_FS'!F32 -> 21824.236 | G10: ='03_Historical_FS'!G32 -> 22244.676 | H10: ='03_Historical_FS'!H32 -> 27266.852 | I10: ='09_Working_Capital'!I12 -> 29415 | J10: ='09_Working_Capital'!J12 -> 32918.045 | K10: ='09_Working_Capital'!K12 -> 35152.125 | L10: ='09_Working_Capital'!L12 -> 37407.242 | M10: ='09_Working_Capital'!M12 -> 39230.893 | N10: Working capital schedule | O10: COGS x inventory days.
A11: Current Assets | B11: Other Current Assets | C11: VND bn | D11: ='03_Historical_FS'!D33 -> 1247.2614 | E11: ='03_Historical_FS'!E33 -> 750.44187 | F11: ='03_Historical_FS'!F33 -> 664.53608 | G11: ='03_Historical_FS'!G33 -> 544.07677 | H11: ='03_Historical_FS'!H33 -> 877.76701 | I11: ='08_P5_Assumptions'!I6*'08_P5_Assumptions'!I24 -> 1110 | J11: ='08_P5_Assumptions'!J6*'08_P5_Assumptions'!J24 -> 1264.2136 | K11: ='08_P5_Assumptions'!K6*'08_P5_Assumptions'!K24 -> 1392.1004 | L11: ='08_P5_Assumptions'!L6*'08_P5_Assumptions'!L24 -> 1504.7824 | M11: ='08_P5_Assumptions'!M6*'08_P5_Assumptions'!M24 -> 1603.3827 | N11: Historical link / formula | O11: Revenue x assumption.
A12: Current Assets | B12: Total Current Assets | C12: VND bn | D12: ='03_Historical_FS'!D34 -> 51955.258 | E12: ='03_Historical_FS'!E34 -> 44577.607 | F12: ='03_Historical_FS'!F34 -> 51950.338 | G12: ='03_Historical_FS'!G34 -> 65836.423 | H12: ='03_Historical_FS'!H34 -> 77201.651 | I12: =I6+I9+I10+I11 -> 91935.636 | J12: =J6+J9+J10+J11 -> 106912.87 | K12: =K6+K9+K10+K11 -> 121055.2 | L12: =L6+L9+L10+L11 -> 135894.58 | M12: =M6+M9+M10+M11 -> 150407.12 | N12: Formula | O12: Liquid funds + receivables + inventory + other current assets.
A13: Long-term Assets | B13: Fixed Assets | C13: VND bn | D13: ='03_Historical_FS'!D35 -> 9647.1689 | E13: ='03_Historical_FS'!E35 -> 9727.5029 | F13: ='03_Historical_FS'!F35 -> 6500.1356 | G13: ='03_Historical_FS'!G35 -> 3586.6287 | H13: ='03_Historical_FS'!H35 -> 2598.1892 | I13: ='11_Capex_DA'!I12 -> 2690.6892 | J13: ='11_Capex_DA'!J12 -> 2901.3915 | K13: ='11_Capex_DA'!K12 -> 3017.3999 | L13: ='11_Capex_DA'!L12 -> 3017.3999 | M13: ='11_Capex_DA'!M12 -> 3151.0151 | N13: Capex schedule | O13: Fixed asset roll-forward.
A14: Long-term Assets | B14: Long-term Financial Investments | C14: VND bn | D14: ='03_Historical_FS'!D36 -> 0 | E14: ='03_Historical_FS'!E36 -> 231.03484 | F14: ='03_Historical_FS'!F36 -> 746.63225 | G14: ='03_Historical_FS'!G36 -> 242.0358 | H14: ='03_Historical_FS'!H36 -> 3136.3156 | I14: ='08_P5_Assumptions'!I6*'08_P5_Assumptions'!I26 -> 3330 | J14: ='08_P5_Assumptions'!J6*'08_P5_Assumptions'!J26 -> 3581.9386 | K14: ='08_P5_Assumptions'!K6*'08_P5_Assumptions'!K26 -> 3712.2678 | L14: ='08_P5_Assumptions'!L6*'08_P5_Assumptions'!L26 -> 3761.9561 | M14: ='08_P5_Assumptions'!M6*'08_P5_Assumptions'!M26 -> 4008.4566 | N14: Historical link / formula | O14: Revenue x assumption.
A15: Long-term Assets | B15: Other Long-term Assets | C15: VND bn | D15: ='03_Historical_FS'!D37 -> 806.89105 | E15: ='03_Historical_FS'!E37 -> 670.59008 | F15: ='03_Historical_FS'!F37 -> 452.06753 | G15: ='03_Historical_FS'!G37 -> 358.45441 | H15: ='03_Historical_FS'!H37 -> 514.74079 | I15: ='08_P5_Assumptions'!I6*'08_P5_Assumptions'!I27 -> 555 | J15: ='08_P5_Assumptions'!J6*'08_P5_Assumptions'!J27 -> 632.10681 | K15: ='08_P5_Assumptions'!K6*'08_P5_Assumptions'!K27 -> 696.05021 | L15: ='08_P5_Assumptions'!L6*'08_P5_Assumptions'!L27 -> 752.39122 | M15: ='08_P5_Assumptions'!M6*'08_P5_Assumptions'!M27 -> 801.69133 | N15: Historical link / formula | O15: Revenue x assumption.
A16: Assets | B16: Total Assets | C16: VND bn | D16: ='03_Historical_FS'!D38 -> 62971.405 | E16: ='03_Historical_FS'!E38 -> 55834.096 | F16: ='03_Historical_FS'!F38 -> 60111.237 | G16: ='03_Historical_FS'!G38 -> 70437.776 | H16: ='03_Historical_FS'!H38 -> 83945.62 | I16: =I12+I13+I14+I15 -> 98511.325 | J16: =J12+J13+J14+J15 -> 114028.3 | K16: =K12+K13+K14+K15 -> 128480.92 | L16: =L12+L13+L14+L15 -> 143426.33 | M16: =M12+M13+M14+M15 -> 158368.28 | N16: Formula | O16: Total current assets + long-term assets.
A17: Liabilities | B17: Trade Payables | C17: VND bn | D17: ='03_Historical_FS'!D39 -> 12179.775 | E17: ='03_Historical_FS'!E39 -> 8745.8273 | F17: ='03_Historical_FS'!F39 -> 7927.0697 | G17: ='03_Historical_FS'!G39 -> 9179.6361 | H17: ='03_Historical_FS'!H39 -> 13113.9 | I17: ='09_Working_Capital'!I13 -> 13297.192 | J17: ='09_Working_Capital'!J13 -> 15544.632 | K17: ='09_Working_Capital'!K13 -> 17073.889 | L17: ='09_Working_Capital'!L13 -> 18432.554 | M17: ='09_Working_Capital'!M13 -> 19615.447 | N17: Working capital schedule | O17: COGS x payable days.
A18: Liabilities | B18: Total Debt | C18: VND bn | D18: ='03_Historical_FS'!D50 -> 24647.474 | E18: ='03_Historical_FS'!E50 -> 16589.389 | F18: ='03_Historical_FS'!F50 -> 25113.792 | G18: ='03_Historical_FS'!G50 -> 27300.247 | H18: ='03_Historical_FS'!H50 -> 29930.943 | I18: ='10_Debt_Cash_Interest'!I7 -> 35150 | J18: ='10_Debt_Cash_Interest'!J7 -> 37926.409 | K18: ='10_Debt_Cash_Interest'!K7 -> 39442.845 | L18: ='10_Debt_Cash_Interest'!L7 -> 40127.532 | M18: ='10_Debt_Cash_Interest'!M7 -> 40084.566 | N18: Debt schedule | O18: Short-term + long-term debt shown as total debt at group level.
A19: Liabilities | B19: Other Current Liabilities | C19: VND bn | D19: ='03_Historical_FS'!D41-'03_Historical_FS'!D39-'03_Historical_FS'!D40 -> 5765.9098 | E19: ='03_Historical_FS'!E41-'03_Historical_FS'!E39-'03_Historical_FS'!E40 -> 6566.2981 | F19: ='03_Historical_FS'!F41-'03_Historical_FS'!F39-'03_Historical_FS'!F40 -> 3709.649 | G19: ='03_Historical_FS'!G41-'03_Historical_FS'!G39-'03_Historical_FS'!G40 -> 5836.3161 | H19: ='03_Historical_FS'!H41-'03_Historical_FS'!H39-'03_Historical_FS'!H40 -> 7724.6596 | I19: ='08_P5_Assumptions'!I6*'08_P5_Assumptions'!I25 -> 9250 | J19: ='08_P5_Assumptions'!J6*'08_P5_Assumptions'!J25 -> 10535.114 | K19: ='08_P5_Assumptions'!K6*'08_P5_Assumptions'!K25 -> 11136.803 | L19: ='08_P5_Assumptions'!L6*'08_P5_Assumptions'!L25 -> 11787.462 | M19: ='08_P5_Assumptions'!M6*'08_P5_Assumptions'!M25 -> 12292.6 | N19: Historical implied / formula | O19: Current liabilities excluding trade payables and debt.
A20: Liabilities | B20: Other Long-term Liabilities | C20: VND bn | D20: ='03_Historical_FS'!D43-'03_Historical_FS'!D42 -> 0 | E20: ='03_Historical_FS'!E43-'03_Historical_FS'!E42 -> 0 | F20: ='03_Historical_FS'!F43-'03_Historical_FS'!F42 -> 1.168691 | G20: ='03_Historical_FS'!G43-'03_Historical_FS'!G42 -> 0 | H20: ='03_Historical_FS'!H43-'03_Historical_FS'!H42 -> 0 | I20: ='08_P5_Assumptions'!I6*'08_P5_Assumptions'!I28 -> 185 | J20: ='08_P5_Assumptions'!J6*'08_P5_Assumptions'!J28 -> 210.70227 | K20: ='08_P5_Assumptions'!K6*'08_P5_Assumptions'!K28 -> 232.01674 | L20: ='08_P5_Assumptions'!L6*'08_P5_Assumptions'!L28 -> 250.79707 | M20: ='08_P5_Assumptions'!M6*'08_P5_Assumptions'!M28 -> 267.23044 | N20: Historical implied / formula | O20: Long-term liabilities excluding long-term debt.
A21: Liabilities | B21: Total Liabilities | C21: VND bn | D21: ='03_Historical_FS'!D44 -> 42593.159 | E21: ='03_Historical_FS'!E44 -> 31901.514 | F21: ='03_Historical_FS'!F44 -> 36751.679 | G21: ='03_Historical_FS'!G44 -> 42316.199 | H21: ='03_Historical_FS'!H44 -> 50769.502 | I21: =I17+I18+I19+I20 -> 57882.192 | J21: =J17+J18+J19+J20 -> 64216.857 | K21: =K17+K18+K19+K20 -> 67885.554 | L21: =L17+L18+L19+L20 -> 70598.345 | M21: =M17+M18+M19+M20 -> 72259.844 | N21: Formula | O21: Payables + debt + other liabilities.
A22: Equity | B22: Share Capital | C22: VND bn | D22: ='03_Historical_FS'!D45 -> 7130.655 | E22: ='03_Historical_FS'!E45 -> 14638.793 | F22: ='03_Historical_FS'!F45 -> 14633.767 | G22: ='03_Historical_FS'!G45 -> 14622.442 | H22: ='03_Historical_FS'!H45 -> 14696.932 | I22: ='03_Historical_FS'!H45 -> 14696.932 | J22: =I22 -> 14696.932 | K22: =J22 -> 14696.932 | L22: =K22 -> 14696.932 | M22: =L22 -> 14696.932 | N22: Historical link / carry | O22: Forecast assumes no new shares at this stage.
A23: Equity | B23: Retained Earnings | C23: VND bn | D23: ='03_Historical_FS'!D46 -> 12674.574 | E23: ='03_Historical_FS'!E46 -> 8723.9342 | F23: ='03_Historical_FS'!F46 -> 8160.3236 | G23: ='03_Historical_FS'!G46 -> 12582.145 | H23: ='03_Historical_FS'!H46 -> 18068.195 | I23: =H23+'12_Income_Statement'!I25-('12_Income_Statement'!I25*'08_P5_Assumptions'!I16) -> 25465.397 | J23: =I23+'12_Income_Statement'!J25-('12_Income_Statement'!J25*'08_P5_Assumptions'!J16) -> 34573.225 | K23: =J23+'12_Income_Statement'!K25-('12_Income_Statement'!K25*'08_P5_Assumptions'!K16) -> 45262.951 | L23: =K23+'12_Income_Statement'!L25-('12_Income_Statement'!L25*'08_P5_Assumptions'!L16) -> 57381.102 | M23: =L23+'12_Income_Statement'!M25-('12_Income_Statement'!M25*'08_P5_Assumptions'!M16) -> 70529.013 | N23: Historical link / roll-forward | O23: Prior retained earnings + NPATMI - dividends.
A24: Equity | B24: Other Equity / Reserves | C24: VND bn | D24: ='03_Historical_FS'!D48-'03_Historical_FS'!D45-'03_Historical_FS'!D46-'03_Historical_FS'!D47 -> 561.17886 | E24: ='03_Historical_FS'!E48-'03_Historical_FS'!E45-'03_Historical_FS'!E46-'03_Historical_FS'!E47 -> 555.3464 | F24: ='03_Historical_FS'!F48-'03_Historical_FS'!F45-'03_Historical_FS'!F46-'03_Historical_FS'!F47 -> 552.06618 | G24: ='03_Historical_FS'!G48-'03_Historical_FS'!G45-'03_Historical_FS'!G46-'03_Historical_FS'!G47 -> 552.96914 | H24: ='03_Historical_FS'!H48-'03_Historical_FS'!H45-'03_Historical_FS'!H46-'03_Historical_FS'!H47 -> -165.35996 | I24: =H24 -> -165.35996 | J24: =I24 -> -165.35996 | K24: =J24 -> -165.35996 | L24: =K24 -> -165.35996 | M24: =L24 -> -165.35996 | N24: Historical implied / carry | O24: Total equity less share capital, retained earnings and minority interest.
A25: Equity | B25: Minority Interest - BS | C25: VND bn | D25: ='03_Historical_FS'!D47 -> 11.838029 | E25: ='03_Historical_FS'!E47 -> 14.508097 | F25: ='03_Historical_FS'!F47 -> 13.40103 | G25: ='03_Historical_FS'!G47 -> 364.02065 | H25: ='03_Historical_FS'!H47 -> 576.35099 | I25: =H25+'12_Income_Statement'!I24 -> 632.16489 | J25: =I25+'12_Income_Statement'!J24 -> 706.65014 | K25: =J25+'12_Income_Statement'!K24 -> 800.84461 | L25: =K25+'12_Income_Statement'!L24 -> 915.31077 | M25: =L25+'12_Income_Statement'!M24 -> 1047.8502 | N25: Historical link / roll-forward | O25: Prior minority interest + current period minority interest.
A26: Equity | B26: Total Equity | C26: VND bn | D26: ='03_Historical_FS'!D48 -> 20378.246 | E26: ='03_Historical_FS'!E48 -> 23932.582 | F26: ='03_Historical_FS'!F48 -> 23359.558 | G26: ='03_Historical_FS'!G48 -> 28121.577 | H26: ='03_Historical_FS'!H48 -> 33176.117 | I26: =I22+I23+I24+I25 -> 40629.133 | J26: =J22+J23+J24+J25 -> 49811.447 | K26: =K22+K23+K24+K25 -> 60595.367 | L26: =L22+L23+L24+L25 -> 72827.985 | M26: =M22+M23+M24+M25 -> 86108.435 | N26: Formula | O26: Share capital + retained earnings + other equity + minority interest.
A27: Capital | B27: Total Liabilities + Equity | C27: VND bn | D27: ='03_Historical_FS'!D49 -> 62971.405 | E27: ='03_Historical_FS'!E49 -> 55834.096 | F27: ='03_Historical_FS'!F49 -> 60111.237 | G27: ='03_Historical_FS'!G49 -> 70437.776 | H27: ='03_Historical_FS'!H49 -> 83945.62 | I27: =I21+I26 -> 98511.325 | J27: =J21+J26 -> 114028.3 | K27: =K21+K26 -> 128480.92 | L27: =L21+L26 -> 143426.33 | M27: =M21+M26 -> 158368.28 | N27: Formula | O27: Total liabilities + total equity.
A28: Check | B28: Balance Sheet Check | C28: VND bn | D28: ='03_Historical_FS'!D73 -> -3.6379788e-12 | E28: ='03_Historical_FS'!E73 -> 0 | F28: ='03_Historical_FS'!F73 -> 1.0000003e-06 | G28: ='03_Historical_FS'!G73 -> 0 | H28: ='03_Historical_FS'!H73 -> 0 | I28: =I16-I27 -> 0 | J28: =J16-J27 -> 0 | K28: =K16-K27 -> 0 | L28: =L16-L27 -> 0 | M28: =M16-M27 -> 0 | N28: Formula | O28: Total assets - liabilities - equity; must be zero.
A29: Debt | B29: Net Debt | C29: VND bn | D29: ='03_Historical_FS'!D51 -> 6268.8322 | E29: ='03_Historical_FS'!E51 -> 1459.1185 | F29: ='03_Historical_FS'!F51 -> 811.07889 | G29: ='03_Historical_FS'!G51 -> -6921.5266 | H29: ='03_Historical_FS'!H51 -> -8943.2529 | I29: =I18-I6 -> -17137.348 | J29: =J18-J6 -> -24990.669 | K29: =K18-K6 -> -34897.537 | L29: =L18-L6 -> -46548.298 | M29: =M18-M6 -> -58506.201 | N29: Formula | O29: Total debt - cash and short-term investments.

Sheet 14_Cash_Flow
A1: MWG - Forecast Cash Flow Statement
A2: Cash flow forecast tied to the balance sheet liquid funds line
A4: Section | B4: Line Item | C4: Unit | D4: 2021A | E4: 2022A | F4: 2023A | G4: 2024A | H4: 2025A | I4: 2026E | J4: 2027E | K4: 2028E | L4: 2029E | M4: 2030E | N4: Method / Source | O4: Notes
A5: CASH FLOW STATEMENT
A6: Operating | B6: NPAT | C6: VND bn | D6: ='03_Historical_FS'!D24 -> 4901.4267 | E6: ='03_Historical_FS'!E24 -> 4101.7144 | F6: ='03_Historical_FS'!F24 -> 167.82915 | G6: ='03_Historical_FS'!G24 -> 3733.2882 | H6: ='03_Historical_FS'!H24 -> 7072.6229 | I6: ='12_Income_Statement'!I23 -> 9302.3164 | J6: ='12_Income_Statement'!J23 -> 11459.271 | K6: ='12_Income_Statement'!K23 -> 13456.352 | L6: ='12_Income_Statement'!L23 -> 15262.156 | M6: ='12_Income_Statement'!M23 -> 16567.428 | N6: Income statement | O6: Net profit after tax.
A7: Operating | B7: D&A | C7: VND bn | D7: ='03_Historical_FS'!D55 -> 2920.7136 | E7: ='03_Historical_FS'!E55 -> 3540.3247 | F7: ='03_Historical_FS'!F55 -> 3351.3143 | G7: ='03_Historical_FS'!G55 -> 2913.4191 | H7: ='03_Historical_FS'!H55 -> 1890.8821 | I7: ='11_Capex_DA'!I10 -> 2127.5 | J7: ='11_Capex_DA'!J10 -> 2317.725 | K7: ='11_Capex_DA'!K10 -> 2436.1757 | L7: ='11_Capex_DA'!L10 -> 2507.9707 | M7: ='11_Capex_DA'!M10 -> 2538.6892 | N7: Capex schedule | O7: Non-cash depreciation and amortization.
A8: Operating | B8: Change in Net Working Capital | C8: VND bn | E8: ='09_Working_Capital'!E15 -> -198.51162 | F8: ='09_Working_Capital'!F15 -> -895.04863 | G8: ='09_Working_Capital'!G15 -> 2834.9173 | H8: ='09_Working_Capital'!H15 -> 2444.8518 | I8: ='09_Working_Capital'!I15 -> 905.30761 | J8: ='09_Working_Capital'!J15 -> 1945.8469 | K8: ='09_Working_Capital'!K15 -> 1061.8894 | L8: ='09_Working_Capital'!L15 -> 1032.585 | M8: ='09_Working_Capital'!M15 -> 1316.1024 | N8: Working capital schedule | O8: Positive value is cash outflow.
A9: Operating | B9: CFO (Simplified) | C9: VND bn | D9: =D6+D7-D8 -> 7822.1403 | E9: =E6+E7-E8 -> 7840.5508 | F9: =F6+F7-F8 -> 4414.1921 | G9: =G6+G7-G8 -> 3811.79 | H9: =H6+H7-H8 -> 6518.6532 | I9: =I6+I7-I8 -> 10524.509 | J9: =J6+J7-J8 -> 11831.149 | K9: =K6+K7-K8 -> 14830.638 | ... M9: =M6+M7-M8 -> 17790.015 | N9: Formula | O9: NPAT + D&A - change in NWC.
A10: Investing | B10: Capex | C10: VND bn | D10: ='03_Historical_FS'!D59 -> -4976.8766 | E10: ='03_Historical_FS'!E59 -> -4465.3595 | F10: ='03_Historical_FS'!F59 -> -523.38333 | G10: ='03_Historical_FS'!G59 -> -303.74783 | H10: ='03_Historical_FS'!H59 -> -888.46189 | I10: =-'11_Capex_DA'!I8 -> -2220 | J10: =-'11_Capex_DA'!J8 -> -2528.4272 | K10: =-'11_Capex_DA'!K8 -> -2552.1841 | L10: =-'11_Capex_DA'!L8 -> -2507.9707 | M10: =-'11_Capex_DA'!M8 -> -2672.3044 | N10: Capex schedule | O10: Negative cash outflow.
A11: Investing | B11: CFI before Liquid Investment Movement | C11: VND bn | D11: ='03_Historical_FS'!D60 -> -11254.87 | E11: ='03_Historical_FS'!E60 -> 1549.1114 | F11: ='03_Historical_FS'!F60 -> -10831.295 | G11: ='03_Historical_FS'!G60 -> -11743.286 | H11: ='03_Historical_FS'!H60 -> -6660.7754 | I11: =I10 -> -2220 | J11: =J10 -> -2528.4272 | K11: =K10 -> -2552.1841 | L11: =L10 -> -2507.9707 | M11: =M10 -> -2672.3044 | N11: Formula | O11: Capex only for forecast; official CFI has more detail historically.
A12: Financing | B12: Debt Movement | C12: VND bn | D12: ='03_Historical_FS'!D61+'03_Historical_FS'!D62 -> 7891.0773 | E12: ='13_Balance_Sheet'!E18-'13_Balance_Sheet'!D18 -> -8058.0856 | F12: ='13_Balance_Sheet'!F18-'13_Balance_Sheet'!E18 -> 8524.4032 | G12: ='13_Balance_Sheet'!G18-'13_Balance_Sheet'!F18 -> 2186.4549 | H12: ='13_Balance_Sheet'!H18-'13_Balance_Sheet'!G18 -> 2630.6962 | I12: ='13_Balance_Sheet'!I18-'13_Balance_Sheet'!H18 -> 5219.057 | J12: ='13_Balance_Sheet'!J18-'13_Balance_Sheet'!I18 -> 2776.4086 | K12: ='13_Balance_Sheet'!K18-'13_Balance_Sheet'!J18 -> 1516.4365 | L12: ='13_Balance_Sheet'!L18-'13_Balance_Sheet'!K18 -> 684.68658 | M12: ='13_Balance_Sheet'!M18-'13_Balance_Sheet'!L18 -> -42.965324 | N12: Formula | O12: Current debt - prior debt.
A13: Financing | B13: Dividends Paid | C13: VND bn | D13: ='03_Historical_FS'!D63 -> -239.51944 | E13: ='03_Historical_FS'!E63 -> -731.85482 | F13: ='03_Historical_FS'!F63 -> -731.28002 | G13: ='03_Historical_FS'!G63 -> -730.95769 | H13: ='03_Historical_FS'!H63 -> -1478.4568 | I13: =-'12_Income_Statement'!I25*'08_P5_Assumptions'!I16 -> -1849.3005 | J13: =-'12_Income_Statement'!J25*'08_P5_Assumptions'!J16 -> -2276.9571 | K13: =-'12_Income_Statement'!K25*'08_P5_Assumptions'!K16 -> -2672.4314 | L13: =-'12_Income_Statement'!L25*'08_P5_Assumptions'!L16 -> -3029.5379 | M13: =-'12_Income_Statement'!M25*'08_P5_Assumptions'!M16 -> -3286.9777 | N13: Formula | O13: Negative outflow; forecast uses dividend payout ratio.
A14: Financing | B14: CFF | C14: VND bn | D14: ='03_Historical_FS'!D64 -> 7877.4909 | E14: ='03_Historical_FS'!E64 -> -8606.3435 | F14: ='03_Historical_FS'!F64 -> 7699.7831 | G14: ='03_Historical_FS'!G64 -> 2757.4755 | H14: ='03_Historical_FS'!H64 -> 667.17175 | I14: =I12+I13 -> 3369.7565 | J14: =J12+J13 -> 499.45156 | K14: =K12+K13 -> -1155.995 | L14: =L12+L13 -> -2344.8513 | M14: =M12+M13 -> -3329.9431 | N14: Formula | O14: Debt movement + dividends.
A15: Liquidity | B15: Net Change in Liquid Funds | C15: VND bn | E15: =E17-E16 -> -3248.3719 | F15: =F17-F16 -> 9172.4428 | G15: =G17-G16 -> 9919.0604 | H15: =H17-H16 -> 4652.4225 | I15: =I17-I16 -> 13413.152 | J15: =J17-J16 -> 10629.73 | K15: =K17-K16 -> 11423.304 | L15: =L17-L16 -> 12335.448 | M15: =M17-M16 -> 11914.938 | N15: Formula | O15: Ending liquid funds - beginning liquid funds.
A16: Liquidity | B16: Beginning Liquid Funds | C16: VND bn | E16: ='13_Balance_Sheet'!D6 -> 18378.642 | F16: ='13_Balance_Sheet'!E6 -> 15130.27 | G16: ='13_Balance_Sheet'!F6 -> 24302.713 | H16: ='13_Balance_Sheet'!G6 -> 34221.773 | I16: ='13_Balance_Sheet'!H6 -> 38874.196 | J16: ='13_Balance_Sheet'!I6 -> 52287.348 | K16: ='13_Balance_Sheet'!J6 -> 62917.078 | L16: ='13_Balance_Sheet'!K6 -> 74340.382 | M16: ='13_Balance_Sheet'!L6 -> 86675.829 | N16: Formula | O16: Prior period cash + short-term investments.
A17: Liquidity | B17: Ending Liquid Funds | C17: VND bn | D17: ='13_Balance_Sheet'!D6 -> 18378.642 | E17: ='13_Balance_Sheet'!E6 -> 15130.27 | F17: ='13_Balance_Sheet'!F6 -> 24302.713 | G17: ='13_Balance_Sheet'!G6 -> 34221.773 | H17: ='13_Balance_Sheet'!H6 -> 38874.196 | I17: ='13_Balance_Sheet'!I6 -> 52287.348 | J17: ='13_Balance_Sheet'!J6 -> 62917.078 | K17: ='13_Balance_Sheet'!K6 -> 74340.382 | ... M17: ='13_Balance_Sheet'!M6 -> 98590.767 | N17: Balance sheet | O17: Cash + short-term financial investments.
A18: Liquidity | B18: Other / Liquid Investment Movement | C18: VND bn | D18: =D15-D9-D11-D14 -> -4444.7616 | E18: =E15-E9-E11-E14 -> -4031.6906 | F18: =F15-F9-F11-F14 -> 7889.7623 | G18: =G15-G9-G11-G14 -> 15093.08 | H18: =H15-H9-H11-H14 -> 4127.373 | I18: =I15-I9-I11-I14 -> 1738.887 | J18: =J15-J9-J11-J14 -> 827.55675 | K18: =K15-K9-K11-K14 -> 300.84491 | ... M18: =M15-M9-M11-M14 -> 127.17042 | N18: Formula | O18: Balancing line for cash-like investments and public-data gaps.
A19: Check | B19: Cash Flow Tie Check | C19: VND bn | D19: =D16+D15-D17 -> -18378.642 | E19: =E16+E15-E17 -> 0 | F19: =F16+F15-F17 -> 0 | G19: =G16+G15-G17 -> 0 | H19: =H16+H15-H17 -> 0 | I19: =I16+I15-I17 -> 0 | J19: =J16+J15-J17 -> 0 | K19: =K16+K15-K17 -> 0 | ... M19: =M16+M15-M17 -> 0 | N19: Formula | O19: Beginning liquid funds + net change - ending liquid funds; should be zero.
A20: FCFF | B20: FCFF | C20: VND bn | D20: ='12_Income_Statement'!D15*(1-'08_P5_Assumptions'!D14)+D7-ABS(D10)-D8 -> 2840.737 | E20: ='12_Income_Statement'!E15*(1-'08_P5_Assumptions'!E14)+E7-ABS(E10)-E8 -> 3726.24 | F20: ='12_Income_Statement'!F15*(1-'08_P5_Assumptions'!F14)+F7-ABS(F10)-F8 -> 3977.7723 | G20: ='12_Income_Statement'!G15*(1-'08_P5_Assumptions'!G14)+G7-ABS(G10)-G8 -> 3818.4808 | H20: ='12_Income_Statement'!H15*(1-'08_P5_Assumptions'!H14)+H7-ABS(H10)-H8 -> 5655.5986 | I20: ='12_Income_Statement'!I15*(1-'08_P5_Assumptions'!I14)+I7-ABS(I10)-I8 -> 7142.1924 | J20: ='12_Income_Statement'!J15*(1-'08_P5_Assumptions'!J14)+J7-ABS(J10)-J8 -> 8125.7216 | K20: ='12_Income_Statement'!K15*(1-'08_P5_Assumptions'!K14)+K7-ABS(K10)-K8 -> 11072.586 | ... M20: ='12_Income_Statement'!M15*(1-'08_P5_Assumptions'!M14)+M7-ABS(M10)-M8 -> 13942.756 | N20: Formula | O20: EBIT x (1-tax rate) + D&A - capex - change in NWC.
A21: FCFF | B21: FCFF Margin | C21: % | D21: =IFERROR(D20/'12_Income_Statement'!D6,"") -> 0.023103292 | E21: =IFERROR(E20/'12_Income_Statement'!E6,"") -> 0.027931833 | F21: =IFERROR(F20/'12_Income_Statement'!F6,"") -> 0.033630195 | G21: =IFERROR(G20/'12_Income_Statement'!G6,"") -> 0.028423761 | H21: =IFERROR(H20/'12_Income_Statement'!H6,"") -> 0.036270543 | I21: =IFERROR(I20/'12_Income_Statement'!I6,"") -> 0.038606445 | J21: =IFERROR(J20/'12_Income_Statement'!J6,"") -> 0.038564946 | K21: =IFERROR(K20/'12_Income_Statement'!K6,"") -> 0.047723221 | ... M21: =IFERROR(M20/'12_Income_Statement'!M6,"") -> 0.052175028 | N21: Formula | O21: FCFF / revenue.

Sheet 16_Trading_Comps
A1: MWG - Trading Comparables
A2: Current trading comps use latest available closing prices through 2026-06-26. LTM = FY2025 + Q1/2026 - Q1/2025. Green = linked to raw/API sheets or MWG model;
A4: Valuation Date | B4: 2026-06-26 | C4: Currency | D4: VND bn unless noted | E4: Peer Set | F4: MWG + FRT/DGW/PET + MSN proxy
A6: CURRENT TRADING COMPS - 2025A AND LTM
A7: Ticker | B7: Role | C7: Company | D7: Price Date | E7: Current Price VND | F7: Shares | G7: Market Cap VND bn | H7: Cash + STI VND bn | I7: Debt VND bn | J7: Net Debt 2026 Q1 VND bn | K7: EV VND bn | L7: Revenue 2025A | M7: EBITDA 2025A | N7: NPATMI 2025A | O7: Revenue LTM | P7: EBITDA LTM | Q7: NPATMI LTM | R7: Equity Latest | S7: P/E 2025A | T7: EV/EBITDA 2025A | U7: EV/Sales 2025A | V7: P/E LTM | W7: EV/EBITDA LTM | X7: EV/Sales LTM | Y7: P/B Latest | Z7: Source / Note
A8: ='100_Raw_Peer_Metrics'!A5 -> MWG | B8: ='100_Raw_Peer_Metrics'!B5 -> Target company | C8: ='100_Raw_Peer_Metrics'!D5 -> Thế giới di động | D8: ='100_Raw_Peer_Metrics'!F5 -> 2026-06-26 | E8: ='100_Raw_Peer_Metrics'!G5 -> 78500 | F8: ='100_Raw_Peer_Metrics'!H5 -> 1468423529 | G8: =IFERROR(E8*F8/1000000000,"") -> 115271.25 | H8: ='100_Raw_Peer_Metrics'!K5 -> 46384.806 | I8: ='100_Raw_Peer_Metrics'!L5 -> 28100.653 | J8: =IFERROR(I8-H8,"") -> -18284.153 | K8: =IFERROR(G8+J8,"") -> 96987.094 | L8: ='100_Raw_Peer_Metrics'!O5 -> 155928.15 | M8: ='100_Raw_Peer_Metrics'!P5 -> 8965.7815 | N8: ='100_Raw_Peer_Metrics'!Q5 -> 7033.7308 | O8: ='100_Raw_Peer_Metrics'!X5 -> 166255.14 | P8: ='100_Raw_Peer_Metrics'!Y5 -> 10170 | Q8: ='100_Raw_Peer_Metrics'!Z5 -> 8202.2245 | R8: ='100_Raw_Peer_Metrics'!AA5 -> 35933.342 | S8: =IFERROR(G8/N8,"") -> 16.388351 | T8: =IFERROR(K8/M8,"") -> 10.817472 | U8: =IFERROR(K8/L8,"") -> 0.62199864 | V8: =IFERROR(G8/Q8,"") -> 14.053657 | W8: =IFERROR(K8/P8,"") -> 9.5365875 | X8: =IFERROR(K8/O8,"") -> 0.58336298 | Y8: =IFERROR(G8/R8,"") -> 3.2079189 | Z8: ='100_Raw_Peer_Metrics'!AC5 -> MWG cash/debt links to 04A_Q1_Historical_FS; other metrics use vnstock Finance source=VCI
A9: ='100_Raw_Peer_Metrics'!A6 -> FRT | B9: ='100_Raw_Peer_Metrics'!B6 -> Core Vietnam retail peer | C9: ='100_Raw_Peer_Metrics'!D6 -> Bán lẻ FPT | D9: ='100_Raw_Peer_Metrics'!F6 -> 2026-06-26 | E9: ='100_Raw_Peer_Metrics'!G6 -> 124000 | F9: ='100_Raw_Peer_Metrics'!H6 -> 170301785 | G9: =IFERROR(E9*F9/1000000000,"") -> 21117.421 | H9: ='100_Raw_Peer_Metrics'!K6 -> 8649.1619 | I9: ='100_Raw_Peer_Metrics'!L6 -> 12381.418 | J9: =IFERROR(I9-H9,"") -> 3732.2558 | K9: =IFERROR(G9+J9,"") -> 24849.677 | L9: ='100_Raw_Peer_Metrics'!O6 -> 51082.868 | M9: ='100_Raw_Peer_Metrics'!P6 -> 1716.3106 | N9: ='100_Raw_Peer_Metrics'!Q6 -> 794.86494 | O9: ='100_Raw_Peer_Metrics'!X6 -> 54529.932 | P9: ='100_Raw_Peer_Metrics'!Y6 -> 1896.7749 | Q9: ='100_Raw_Peer_Metrics'!Z6 -> 914.25407 | R9: ='100_Raw_Peer_Metrics'!AA6 -> 5513.8732 | S9: =IFERROR(G9/N9,"") -> 26.567307 | T9: =IFERROR(K9/M9,"") -> 14.478543 | U9: =IFERROR(K9/L9,"") -> 0.48645814 | V9: =IFERROR(G9/Q9,"") -> 23.097979 | W9: =IFERROR(K9/P9,"") -> 13.101015 | X9: =IFERROR(K9/O9,"") -> 0.4557071 | Y9: =IFERROR(G9/R9,"") -> 3.8298707 | Z9: ='100_Raw_Peer_Metrics'!AC6 -> vnstock Finance source=VCI; formula pulls from Raw_Peer_IS/BS/CF
A10: ='100_Raw_Peer_Metrics'!A7 -> DGW | B10: ='100_Raw_Peer_Metrics'!B7 -> ICT distribution proxy | C10: ='100_Raw_Peer_Metrics'!D7 -> Thế Giới Số | D10: ='100_Raw_Peer_Metrics'!F7 -> 2026-06-26 | E10: ='100_Raw_Peer_Metrics'!G7 -> 39100 | F10: ='100_Raw_Peer_Metrics'!H7 -> 221168700 | G10: =IFERROR(E10*F10/1000000000,"") -> 8647.6962 | H10: ='100_Raw_Peer_Metrics'!K7 -> 2604.2485 | I10: ='100_Raw_Peer_Metrics'!L7 -> 2789.9615 | J10: =IFERROR(I10-H10,"") -> 185.71304 | K10: =IFERROR(G10+J10,"") -> 8833.4092 | L10: ='100_Raw_Peer_Metrics'!O7 -> 26631.546 | M10: ='100_Raw_Peer_Metrics'!P7 -> 768.96003 | N10: ='100_Raw_Peer_Metrics'!Q7 -> 547.33124 | O10: ='100_Raw_Peer_Metrics'!X7 -> 29612.412 | P10: ='100_Raw_Peer_Metrics'!Y7 -> 839.30248 | Q10: ='100_Raw_Peer_Metrics'!Z7 -> 641.62527 | R10: ='100_Raw_Peer_Metrics'!AA7 -> 3674.3533 | S10: =IFERROR(G10/N10,"") -> 15.799749 | T10: =IFERROR(K10/M10,"") -> 11.487475 | U10: =IFERROR(K10/L10,"") -> 0.33168969 | V10: =IFERROR(G10/Q10,"") -> 13.477799 | W10: =IFERROR(K10/P10,"") -> 10.524703 | X10: =IFERROR(K10/O10,"") -> 0.29830091 | Y10: =IFERROR(G10/R10,"") -> 2.3535288 | Z10: ='100_Raw_Peer_Metrics'!AC7 -> vnstock Finance source=VCI; formula pulls from Raw_Peer_IS/BS/CF
A11: ='100_Raw_Peer_Metrics'!A8 -> PET | B11: ='100_Raw_Peer_Metrics'!B8 -> ICT distribution proxy | C11: ='100_Raw_Peer_Metrics'!D8 -> Dịch vụ Tổng hợp Dầu khí | D11: ='100_Raw_Peer_Metrics'!F8 -> 2026-06-26 | E11: ='100_Raw_Peer_Metrics'!G8 -> 52900 | F11: ='100_Raw_Peer_Metrics'!H8 -> 106722131 | G11: =IFERROR(E11*F11/1000000000,"") -> 5645.6007 | H11: ='100_Raw_Peer_Metrics'!K8 -> 5521.3816 | I11: ='100_Raw_Peer_Metrics'!L8 -> 7222.3143 | J11: =IFERROR(I11-H11,"") -> 1700.9327 | K11: =IFERROR(G11+J11,"") -> 7346.5334 | L11: ='100_Raw_Peer_Metrics'!O8 -> 21815.238 | M11: ='100_Raw_Peer_Metrics'!P8 -> 385.7369 | N11: ='100_Raw_Peer_Metrics'!Q8 -> 258.13391 | O11: ='100_Raw_Peer_Metrics'!X8 -> 23927.604 | P11: ='100_Raw_Peer_Metrics'!Y8 -> 503.54124 | Q11: ='100_Raw_Peer_Metrics'!Z8 -> 294.29753 | R11: ='100_Raw_Peer_Metrics'!AA8 -> 2707.6212 | S11: =IFERROR(G11/N11,"") -> 21.870822 | T11: =IFERROR(K11/M11,"") -> 19.045451 | U11: =IFERROR(K11/L11,"") -> 0.33676155 | V11: =IFERROR(G11/Q11,"") -> 19.18331 | W11: =IFERROR(K11/P11,"") -> 14.589735 | X11: =IFERROR(K11/O11,"") -> 0.30703173 | Y11: =IFERROR(G11/R11,"") -> 2.0850777 | Z11: ='100_Raw_Peer_Metrics'!AC8 -> vnstock Finance source=VCI; formula pulls from Raw_Peer_IS/BS/CF
A12: ='100_Raw_Peer_Metrics'!A9 -> MSN | B12: ='100_Raw_Peer_Metrics'!B9 -> Modern grocery / consumer proxy | C12: ='100_Raw_Peer_Metrics'!D9 -> Tập đoàn Masan | D12: ='100_Raw_Peer_Metrics'!F9 -> 2026-06-26 | E12: ='100_Raw_Peer_Metrics'!G9 -> 71400 | F12: ='100_Raw_Peer_Metrics'!H9 -> 1460374611 | G12: =IFERROR(E12*F12/1000000000,"") -> 104270.75 | H12: ='100_Raw_Peer_Metrics'!K9 -> 16208.23 | I12: ='100_Raw_Peer_Metrics'!L9 -> 65037.166 | J12: =IFERROR(I12-H12,"") -> 48828.936 | K12: =IFERROR(G12+J12,"") -> 153099.68 | L12: ='100_Raw_Peer_Metrics'!O9 -> 81621.329 | M12: ='100_Raw_Peer_Metrics'!P9 -> 11092.993 | N12: ='100_Raw_Peer_Metrics'!Q9 -> 4108.306 | O12: ='100_Raw_Peer_Metrics'!X9 -> 86744.545 | P12: ='100_Raw_Peer_Metrics'!Y9 -> 11954.656 | Q12: ='100_Raw_Peer_Metrics'!Z9 -> 4960.6 | R12: ='100_Raw_Peer_Metrics'!AA9 -> 46262.607 | S12: =IFERROR(G12/N12,"") -> 25.380472 | T12: =IFERROR(K12/M12,"") -> 13.801477 | U12: =IFERROR(K12/L12,"") -> 1.8757313 | V12: =IFERROR(G12/Q12,"") -> 21.019785 | W12: =IFERROR(K12/P12,"") -> 12.806699 | X12: =IFERROR(K12/O12,"") -> 1.7649488 | Y12: =IFERROR(G12/R12,"") -> 2.2538883 | Z12: ='100_Raw_Peer_Metrics'!AC9 -> vnstock Finance source=VCI; formula pulls from Raw_Peer_IS/BS/CF
A14: Core Peer Median | B14: FRT/DGW/PET | C14: Excludes MWG and MSN proxy | S14: =IFERROR(MEDIAN(S9:S11),"") -> 21.870822 | T14: =IFERROR(MEDIAN(T9:T11),"") -> 14.478543 | U14: =IFERROR(MEDIAN(U9:U11),"") -> 0.33676155 | V14: =IFERROR(MEDIAN(V9:V11),"") -> 19.18331 | W14: =IFERROR(MEDIAN(W9:W11),"") -> 13.101015 | X14: =IFERROR(MEDIAN(X9:X11),"") -> 0.30703173 | Y14: =IFERROR(MEDIAN(Y9:Y11),"") -> 2.3535288
A15: Broader Proxy Median | B15: FRT/DGW/PET/MSN | C15: Excludes MWG | S15: =IFERROR(MEDIAN(S9:S12),"") -> 23.625647 | T15: =IFERROR(MEDIAN(T9:T12),"") -> 14.14001 | U15: =IFERROR(MEDIAN(U9:U12),"") -> 0.41160985 | V15: =IFERROR(MEDIAN(V9:V12),"") -> 20.101548 | W15: =IFERROR(MEDIAN(W9:W12),"") -> 12.953857 | X15: =IFERROR(MEDIAN(X9:X12),"") -> 0.38136941 | Y15: =IFERROR(MEDIAN(Y9:Y12),"") -> 2.3037085
A18: FORWARD MULTIPLES
A19: Ticker | B19: Role | C19: Revenue 2026E | D19: EBITDA 2026E | E19: NPATMI 2026E | F19: Revenue 2027E | G19: EBITDA 2027E | H19: NPATMI 2027E | I19: P/E 2026E | J19: EV/EBITDA 2026E | K19: EV/Sales 2026E | L19: P/E 2027E | M19: EV/EBITDA 2027E | N19: EV/Sales 2027E
A20: =A8 -> MWG | B20: =B8 -> Target company | C20: ='12_Income_Statement'!I6 -> 185000 | D20: ='12_Income_Statement'!I28 -> 12302.5 | E20: ='12_Income_Statement'!I25 -> 9246.5025 | F20: ='12_Income_Statement'!J6 -> 210702.27 | G20: ='12_Income_Statement'!J28 -> 15170.563 | H20: ='12_Income_Statement'!J25 -> 11384.785 | I20: =IFERROR(G8/E20,"") -> 12.46647 | J20: =IFERROR(K8/D20,"") -> 7.8835272 | K20: =IFERROR(K8/C20,"") -> 0.52425456 | L20: =IFERROR(G8/H20,"") -> 10.125026 | M20: =IFERROR(K8/G20,"") -> 6.3931109 | N20: =IFERROR(K8/F20,"") -> 0.46030398

Sheet 18_Beta_Calculation
A1: MWG - Beta Calculation
A2: Green = linked/API price data; Black = formulas. Base beta feeds 19_WACC
A4: Metric | B4: Unit | C4: Value | D4: Formula / Source
A5: Stock | B5: text | C5: MWG | D5: vnstock Quote.history source=VCI
A6: Market index | B6: text | C6: VNINDEX | D6: vnstock Quote.history source=VCI
A7: Frequency | B7: text | C7: Weekly Friday close | D7: Weekly close resampled to Friday
A8: Source | B8: text | C8: vnstock Quote.history source=VCI | D8: API pull timestamp: 2026-06-27 16:03:32 +07
A9: Price points | B9: count | C9: =COUNTA(A22:A129) -> 108 | D9: COUNTA(Date)
A10: Return observations | B10: count | C10: =COUNT(D23:D129) -> 107 | D10: COUNT(MWG weekly returns)
A11: Start date | B11: date | C11: =MIN(A23:A129) -> 45443 | D11: First return observation date
A12: End date | B12: date | C12: =MAX(A23:A129) -> 46199 | D12: Last return observation date
A13: Raw beta | B13: x | C13: =_xlfn.COVARIANCE.S(D23:D129,E23:E129)/_xlfn.VAR.S(E23:E129) -> 1.0381347 | D13: COVARIANCE.S(MWG return, VNINDEX return) / VAR.S(VNINDEX return)
A14: Rounded beta for WACC | B14: x | C14: =ROUND(C13,2) -> 1.04 | D14: ROUND(raw beta, 2)
A15: Correlation | B15: x | C15: =CORREL(D23:D129,E23:E129) -> 0.60442059 | D15: CORREL(MWG return, VNINDEX return)
A16: R-squared | B16: % | C16: =RSQ(D23:D129,E23:E129) -> 0.36532425 | D16: RSQ(MWG return, VNINDEX return)
A20: WEEKLY PRICE AND RETURN DATA
A21: Date | B21: MWG Price | C21: VNINDEX | D21: MWG Return | E21: VNINDEX Return | F21: Data Source | G21: Row Check
A22: 45436 | B22: 59.17 | C22: 1261.93 | F22: vnstock Quote.history source=VCI | G22: First price observation
A23: 45443 | B23: 62.2 | C23: 1261.72 | D23: =IFERROR(B23/B22-1,"") -> 0.051208383 | E23: =IFERROR(C23/C22-1,"") -> -0.00016641177 | F23: vnstock Quote.history source=VCI | G23: =IF(AND(ISNUMBER(D23),ISNUMBER(E23)),"OK","CHECK") -> OK
A24: 45450 | B24: 60.73 | C24: 1287.58 | D24: =IFERROR(B24/B23-1,"") -> -0.023633441 | E24: =IFERROR(C24/C23-1,"") -> 0.020495831 | F24: vnstock Quote.history source=VCI | G24: =IF(AND(ISNUMBER(D24),ISNUMBER(E24)),"OK","CHECK") -> OK
A25: 45457 | B25: 61.61 | C25: 1279.91 | D25: =IFERROR(B25/B24-1,"") -> 0.014490367 | E25: =IFERROR(C25/C24-1,"") -> -0.0059569114 | F25: vnstock Quote.history source=VCI | G25: =IF(AND(ISNUMBER(D25),ISNUMBER(E25)),"OK","CHECK") -> OK
A26: 45464 | B26: 62.1 | C26: 1282.02 | D26: =IFERROR(B26/B25-1,"") -> 0.0079532543 | E26: =IFERROR(C26/C25-1,"") -> 0.0016485534 | F26: vnstock Quote.history source=VCI | G26: =IF(AND(ISNUMBER(D26),ISNUMBER(E26)),"OK","CHECK") -> OK
A27: 45471 | B27: 61.51 | C27: 1245.32 | D27: =IFERROR(B27/B26-1,"") -> -0.0095008052 | E27: =IFERROR(C27/C26-1,"") -> -0.028626698 | F27: vnstock Quote.history source=VCI | G27: =IF(AND(ISNUMBER(D27),ISNUMBER(E27)),"OK","CHECK") -> OK
A28: 45478 | B28: 64.67 | C28: 1283.04 | D28: =IFERROR(B28/B27-1,"") -> 0.05137376 | E28: =IFERROR(C28/C27-1,"") -> 0.030289404 | F28: vnstock Quote.history source=VCI | G28: =IF(AND(ISNUMBER(D28),ISNUMBER(E28)),"OK","CHECK") -> OK
A29: 45485 | B29: 63.88 | C29: 1280.75 | D29: =IFERROR(B29/B28-1,"") -> -0.012215865 | E29: =IFERROR(C29/C28-1,"") -> -0.0017848235 | F29: vnstock Quote.history source=VCI | G29: =IF(AND(ISNUMBER(D29),ISNUMBER(E29)),"OK","CHECK") -> OK
A30: 45492 | B30: 64.67 | C30: 1264.78 | D30: =IFERROR(B30/B29-1,"") -> 0.012366938 | E30: =IFERROR(C30/C29-1,"") -> -0.012469256 | F30: vnstock Quote.history source=VCI | G30: =IF(AND(ISNUMBER(D30),ISNUMBER(E30)),"OK","CHECK") -> OK
A31: 45499 | B31: 60.13 | C31: 1242.11 | D31: =IFERROR(B31/B30-1,"") -> -0.070202567 | E31: =IFERROR(C31/C30-1,"") -> -0.017924066 | F31: vnstock Quote.history source=VCI | G31: =IF(AND(ISNUMBER(D31),ISNUMBER(E31)),"OK","CHECK") -> OK
A32: 45506 | B32: 62.01 | C32: 1236.6 | D32: =IFERROR(B32/B31-1,"") -> 0.031265591 | E32: =IFERROR(C32/C31-1,"") -> -0.004436 | F32: vnstock Quote.history source=VCI | G32: =IF(AND(ISNUMBER(D32),ISNUMBER(E32)),"OK","CHECK") -> OK
A33: 45513 | B33: 64.67 | C33: 1223.64 | D33: =IFERROR(B33/B32-1,"") -> 0.042896307 | E33: =IFERROR(C33/C32-1,"") -> -0.010480349 | F33: vnstock Quote.history source=VCI | G33: =IF(AND(ISNUMBER(D33),ISNUMBER(E33)),"OK","CHECK") -> OK
A34: 45520 | B34: 68.02 | C34: 1252.23 | D34: =IFERROR(B34/B33-1,"") -> 0.051801454 | E34: =IFERROR(C34/C33-1,"") -> 0.023364715 | F34: vnstock Quote.history source=VCI | G34: =IF(AND(ISNUMBER(D34),ISNUMBER(E34)),"OK","CHECK") -> OK
... A129: 46199 | B129: 78.5 | C129: 1871.91 | D129: =IFERROR(B129/B128-1,"") -> 0.0064102564 | E129: =IFERROR(C129/C128-1,"") -> 0.025968332 | F129: vnstock Quote.history source=VCI | G129: =IF(AND(ISNUMBER(D129),ISNUMBER(E129)),"OK","CHECK") -> OK

Sheet 19_WACC
A1: MWG - WACC Assumptions
A2: Valuation currency: VND. Green = linked workbook/API data; Blue = analyst input; Black = formulas. WACC will feed the next DCF sheet.
A4: Section | B4: Line Item | C4: Unit | D4: Bull | E4: Base | F4: Bear | G4: Method / Formula | H4: Source | I4: Note
A5: CAPM AND COST OF EQUITY
A6: CAPM | B6: Risk-free rate | C6: % | D6: =E6-0.005 -> 0.04 | E6: 0.045 | F6: =E6+0.005 -> 0.05 | G6: Vietnam 10Y government bond yield, rounded for model use. | H6: Trading Economics Vietnam 10Y; ADB AsianBondsOnline cross-check
A7: CAPM | B7: Mature market ERP | C7: % | D7: =E7 -> 0.0423 | E7: 0.0423 | F7: =E7 -> 0.0423 | G7: Damodaran mature market equity risk premium. | H7: Damodaran CompanyERP
A8: CAPM | B8: Vietnam country risk premium | C8: % | D8: =E8 -> 0.039 | E8: 0.039 | F8: =E8 -> 0.039 | G8: Damodaran Vietnam CRP based on sovereign rating/default spread. | H8: Damodaran country risk premiums
A9: CAPM | B9: Equity risk premium | C9: % | D9: =E9-0.005 -> 0.0763 | E9: =E7+E8 -> 0.0813 | F9: =E9+0.01 -> 0.0913 | G9: Base = mature market ERP + Vietnam CRP; Bull/Bear flex around base. | H9: Damodaran country risk premiums
A10: CAPM | B10: Beta | C10: x | D10: =E10-0.1 -> 0.94 | E10: ='18_Beta_Calculation'!C14 -> 1.04 | F10: =E10+0.1 -> 1.14 | G10: 2-year weekly beta from 18_Beta_Calculation: Cov(MWG return, VNINDEX return) / Var(VNINDEX return). | H10: 18_Beta_Calculation / vnstock Quote.history source=VCI
A11: CAPM | B11: Cost of Equity | C11: % | D11: =D6+D10*D9 -> 0.111722 | E11: =E6+E10*E9 -> 0.129552 | F11: =F6+F10*F9 -> 0.154082 | G11: Cost of Equity = Risk-free rate + Beta x ERP. | H11: Formula
A12: Check | B12: Cost of equity > risk-free? | C12: status | D12: =IF(D11>D6,"OK","CHECK") -> OK | E12: =IF(E11>E6,"OK","CHECK") -> OK | F12: =IF(F11>F6,"OK","CHECK") -> OK | G12: Cost of equity should exceed the risk-free rate. | H12: Formula
A14: DEBT, TAX AND CAPITAL STRUCTURE
A15: Debt | B15: Pre-tax cost of debt | C15: % | D15: =E15-0.005 -> 0.047 | E15: ='08_P5_Assumptions'!I12 -> 0.052 | F15: =E15+0.005 -> 0.057 | G15: implied borrowing cost; Bull/Bear flex +/-50 bps. | H15: 08_P5_Assumptions row Interest Rate on Average Debt
A16: Tax | B16: Effective tax rate | C16: % | D16: ='08_P5_Assumptions'!I14 -> 0.2 | E16: ='08_P5_Assumptions'!I14 -> 0.2 | F16: ='08_P5_Assumptions'!I14 -> 0.2 | G16: Linked to normalized 2026E tax rate | H16: 08_P5_Assumptions row Effective Tax Rate
A17: Debt | B17: After-tax cost of debt | C17: % | D17: =D15*(1-D16) -> 0.0376 | E17: =E15*(1-E16) -> 0.0416 | F17: =F15*(1-F16) -> 0.0456 | G17: After-tax cost of debt = pre-tax cost of debt x (1 - tax rate). | H17: Formula
A18: Capital Structure | B18: Market cap | C18: VND bn | D18: ='100_Raw_Peer_Metrics'!J5 -> 115271.25 | E18: ='100_Raw_Peer_Metrics'!J5 -> 115271.25 | F18: ='100_Raw_Peer_Metrics'!J5 -> 115271.25 | G18: Current share price x shares outstanding. | H18: 100_Raw_Peer_Metrics MWG row
A19: Capital Structure | B19: Gross debt | C19: VND bn | D19: ='100_Raw_Peer_Metrics'!L5 -> 28100.653 | E19: ='100_Raw_Peer_Metrics'!L5 -> 28100.653 | F19: ='100_Raw_Peer_Metrics'!L5 -> 28100.653 | G19: Short-term borrowings + long-term borrowings. | H19: 100_Raw_Peer_Metrics MWG row
A20: Capital Structure | B20: Total capital | C20: VND bn | D20: =D18+D19 -> 143371.9 | E20: =E18+E19 -> 143371.9 | F20: =F18+F19 -> 143371.9 | G20: Market cap + gross debt. | H20: Formula
A21: Capital Structure | B21: Equity weight | C21: % | D21: =IFERROR(D18/D20,"") -> 0.80400167 | E21: =IFERROR(E18/E20,"") -> 0.80400167 | F21: =IFERROR(F18/F20,"") -> 0.80400167 | G21: Market cap / total capital. | H21: Formula
A22: Capital Structure | B22: Debt weight | C22: % | D22: =IFERROR(D19/D20,"") -> 0.19599833 | E22: =IFERROR(E19/E20,"") -> 0.19599833 | F22: =IFERROR(F19/F20,"") -> 0.19599833 | G22: Gross debt / total capital. | H22: Formula
A23: WACC | B23: WACC | C23: % | D23: =D11*D21+D17*D22 -> 0.097194212 | E23: =E11*E21+E17*E22 -> 0.11231355 | F23: =F11*F21+F17*F22 -> 0.13281971 | G23: WACC = Cost of Equity x Equity Weight + After-tax Cost of Debt x Debt Weight. | H23: Formula
A24: WACC | B24: Rounded WACC for DCF | C24: % | D24: =ROUND(D23,3) -> 0.097 | E24: =ROUND(E23,3) -> 0.112 | F24: =ROUND(F23,3) -> 0.133 | G24: Rounded to nearest 10 bps for clean sensitivity tables. | H24: Formula
A26: BETA CALCULATION AUDIT
A27: Beta Audit | B27: Stock | C27: text | E27: ='18_Beta_Calculation'!C5 -> MWG | G27: Target stock used for beta. | H27: 18_Beta_Calculation / vnstock Quote.history source=VCI
A28: Beta Audit | B28: Market index | C28: text | E28: ='18_Beta_Calculation'!C6 -> VNINDEX | G28: Market index used as market proxy. | H28: 18_Beta_Calculation / vnstock Quote.history source=VCI
A29: Beta Audit | B29: Frequency | C29: text | E29: ='18_Beta_Calculation'!C7 -> Weekly Friday close | G29: Weekly Friday close. | H29: 18_Beta_Calculation / vnstock Quote.history source=VCI
A30: Beta Audit | B30: Start date | C30: date | E30: ='18_Beta_Calculation'!C11 -> 45443 | G30: First weekly observation. | H30: 18_Beta_Calculation / vnstock Quote.history source=VCI
A31: Beta Audit | B31: End date | C31: date | E31: ='18_Beta_Calculation'!C12 -> 46199 | G31: Last weekly observation. | H31: 18_Beta_Calculation / vnstock Quote.history source=VCI
A32: Beta Audit | B32: Observations | C32: count | E32: ='18_Beta_Calculation'!C10 -> 107 | G32: Number of weekly return observations. | H32: 18_Beta_Calculation / vnstock Quote.history source=VCI
A33: Beta Audit | B33: Raw beta | C33: x | E33: ='18_Beta_Calculation'!C13 -> 1.0381347 | G33: Raw beta linked from 18_Beta_Calculation. | H33: 18_Beta_Calculation / vnstock Quote.history source=VCI
A34: Beta Audit | B34: R-squared | C34: % | E34: ='18_Beta_Calculation'!C16 -> 0.36532425 | G34: R-squared linked from 18_Beta_Calculation. | H34: 18_Beta_Calculation / vnstock Quote.history source=VCI
A36: SOURCE LOG
A37: Source | B37: Vietnam 10Y government bond yield | C37: % | E37: 0.0452 | G37: Used as risk-free anchor; model rounds base to 4.5%. | H37: https://tradingeconomics.com/vietnam/government-bond-yield
A38: Source | B38: ADB cross-check | C38: % | G38: Cross-check for Vietnam local-currency government bond yields. | H38: https://asianbondsonline.adb.org/vietnam/
A39: Source | B39: Damodaran mature market ERP | C39: % | E39: 0.0423 | G39: Mature market ERP input. | H39: https://pages.stern.nyu.edu/~adamodar/pc/CompanyERP.xlsx
A40: Source | B40: Damodaran Vietnam CRP | C40: % | E40: 0.039 | G40: Vietnam Ba2; CRP 3.90%; total ERP 8.13%. | H40: https://pages.stern.nyu.edu/~adamodar/New_Home_Page/datafile/ctryprem.html
A41: Source | B41: Cost of debt / tax | C41: % | H41: 08_P5_Assumptions
A42: Source | B42: Capital structure | C42: VND bn | G42: Linked from 100_Raw_Peer_Metrics MWG row. | H42: 100_Raw_Peer_Metrics
A44: WACC CHECKS
A45: Check | B45: Weight sum | C45: % | D45: =D21+D22 -> 1 | E45: =E21+E22 -> 1 | F45: =F21+F22 -> 1 | G45: Equity weight + debt weight should equal 100%. | H45: Formula | I45: Weights must sum to 100%.
A46: Check | B46: WACC positive? | C46: status | D46: =IF(D23>0,"OK","CHECK") -> OK | E46: =IF(E23>0,"OK","CHECK") -> OK | F46: =IF(F23>0,"OK","CHECK") -> OK | G46: WACC must be positive. | H46: Formula | I46: A negative WACC is not valid.
A47: Check | B47: Base WACC > after-tax cost of debt? | C47: status | D47: =IF(D23>D17,"OK","CHECK") -> OK | E47: =IF(E23>E17,"OK","CHECK") -> OK | F47: =IF(F23>F17,"OK","CHECK") -> OK | G47: Equity risk should make WACC higher than after-tax debt cost. | H47: Formula | I47: If WACC is below after-tax debt cost, review the inputs.
A48: Check | B48: Beta observations | C48: status | D48: =IF(E32>=52,"OK","CHECK") -> OK | E48: =IF(E32>=52,"OK","CHECK") -> OK | F48: =IF(E32>=52,"OK","CHECK") -> OK | G48: At least 52 weekly observations. | H48: Formula | I48: Less than one year of data gives a weak beta.
A49: Status | B49: WACC sheet status | C49: status | D49: =IF(AND(ABS(D45-1)<0.001,ABS(E45-1)<0.001,ABS(F45-1)<0.001,D46="OK",E46="OK",F46="OK",D47="OK",E47="OK",F47="OK",D48="OK",E48="OK",F48="OK"),"OK","CHECK") -> OK | E49: =D49 -> OK | F49: =D49 -> OK | G49: All key checks OK. | H49: Formula | I49: Use WACC as a sensitivity input in the DCF.

Sheet 20_DCF
A1: MWG - FCFF DCF Valuation
A2: Valuation currency: VND. Unit: VND bn unless noted. Green = linked workbook/API data; Blue = visible analyst input; Black = formulas. DCF uses FCFF and end-of-year discount convention.
A4: VALUATION SUMMARY
A5: Section | B5: Line Item | C5: Unit | D5: Bull | E5: Base | F5: Bear | G5: Method / Formula | H5: Source
A6: Market Data | B6: Valuation Date | C6: date | D6: ='16_Trading_Comps'!$B$4 -> 2026-06-26 | E6: ='16_Trading_Comps'!$B$4 -> 2026-06-26 | F6: ='16_Trading_Comps'!$B$4 -> 2026-06-26 | G6: Linked | H6: 16_Trading_Comps
A7: Market Data | B7: Current Price | C7: VND/share | D7: ='16_Trading_Comps'!$E$8 -> 78500 | E7: ='16_Trading_Comps'!$E$8 -> 78500 | F7: ='16_Trading_Comps'!$E$8 -> 78500 | G7: Linked | H7: 16_Trading_Comps
A8: Market Data | B8: Diluted Shares Outstanding | C8: shares | D8: ='16_Trading_Comps'!$F$8 -> 1468423529 | E8: ='16_Trading_Comps'!$F$8 -> 1468423529 | F8: ='16_Trading_Comps'!$F$8 -> 1468423529 | G8: Linked | H8: 16_Trading_Comps
A9: Equity Bridge | B9: Net Debt / (Net Cash) | C9: VND bn | D9: ='16_Trading_Comps'!$J$8 -> -18284.153 | E9: ='16_Trading_Comps'!$J$8 -> -18284.153 | F9: ='16_Trading_Comps'!$J$8 -> -18284.153 | G9: Debt - cash & STI | H9: 16_Trading_Comps
A10: Equity Bridge | B10: Minority Interest | C10: VND bn | D10: ='13_Balance_Sheet'!$I$25 -> 632.16489 | E10: ='13_Balance_Sheet'!$I$25 -> 632.16489 | F10: ='13_Balance_Sheet'!$I$25 -> 632.16489 | G10: 2026E proxy | H10: 13_Balance_Sheet
A11: Discount Rate | B11: WACC | C11: % | D11: ='19_WACC'!$D$24 -> 0.097 | E11: ='19_WACC'!$E$24 -> 0.112 | F11: ='19_WACC'!$F$24 -> 0.133 | G11: Linked | H11: 19_WACC
A12: Terminal Value | B12: Terminal Growth | C12: % | D12: 0.035 | E12: 0.03 | F12: 0.025 | G12: Analyst input | H12: Analyst assumption
A13: DCF Output | B13: Enterprise Value | C13: VND bn | D13: =D52 -> 191456.55 | E13: =E52 -> 145226.08 | F13: =F52 -> 110200.84 | G13: PV FCFF + PV terminal value | H13: DCF mechanics below
A14: DCF Output | B14: Equity Value | C14: VND bn | D14: =D55 -> 209108.54 | E14: =E55 -> 162878.07 | F14: =F55 -> 127852.83 | G14: EV - net debt - minority interest | H14: DCF mechanics below
A15: DCF Output | B15: Target Price | C15: VND/share | D15: =D56 -> 142403.43 | E15: =E56 -> 110920.36 | F15: =F56 -> 87068.09 | G15: Equity value / shares | H15: DCF mechanics below
A16: DCF Output | B16: Upside / Downside | C16: % | D16: =D57 -> 0.81405639 | E16: =E57 -> 0.41299824 | F16: =F57 -> 0.10914764 | G16: Target price / current price - 1 | H16: DCF mechanics below
A19: FCFF BRIDG
A20: Section | B20: Line Item | C20: Unit | D20: 2026E | E20: 2027E | F20: 2028E | G20: 2029E | H20: 2030E | I20: Method / Formula | J20: Source
A21: Operating Forecast | B21: Revenue | C21: VND bn | D21: ='12_Income_Statement'!I6 -> 185000 | E21: ='12_Income_Statement'!J6 -> 210702.27 | F21: ='12_Income_Statement'!K6 -> 232016.74 | G21: ='12_Income_Statement'!L6 -> 250797.07 | H21: ='12_Income_Statement'!M6 -> 267230.44 | I21: Linked | J21: 12_Income_Statement
A22: Operating Forecast | B22: EBIT | C22: VND bn | D22: ='12_Income_Statement'!I15 -> 10175 | E22: ='12_Income_Statement'!J15 -> 12852.838 | F22: ='12_Income_Statement'!K15 -> 15313.105 | G22: ='12_Income_Statement'!L15 -> 17555.795 | H22: ='12_Income_Statement'!M15 -> 19240.592 | I22: Linked | J22: 12_Income_Statement
A23: Tax | B23: Effective Tax Rate | C23: % | D23: ='08_P5_Assumptions'!I14 -> 0.2 | E23: ='08_P5_Assumptions'!J14 -> 0.2 | F23: ='08_P5_Assumptions'!K14 -> 0.2 | G23: ='08_P5_Assumptions'!L14 -> 0.2 | H23: ='08_P5_Assumptions'!M14 -> 0.2 | I23: Linked | J23: 08_P5_Assumptions
A24: Tax | B24: NOPAT | C24: VND bn | D24: =D22*(1-D23) -> 8140 | E24: =E22*(1-E23) -> 10282.271 | F24: =F22*(1-F23) -> 12250.484 | G24: =G22*(1-G23) -> 14044.636 | H24: =H22*(1-H23) -> 15392.473 | I24: EBIT x (1 - tax rate) | J24: Formula
A25: Non-cash | B25: D&A | C25: VND bn | D25: ='14_Cash_Flow'!I7 -> 2127.5 | E25: ='14_Cash_Flow'!J7 -> 2317.725 | F25: ='14_Cash_Flow'!K7 -> 2436.1757 | G25: ='14_Cash_Flow'!L7 -> 2507.9707 | H25: ='14_Cash_Flow'!M7 -> 2538.6892 | I25: Linked | J25: 14_Cash_Flow
A26: Reinvestment | B26: Capex | C26: VND bn | D26: =-'14_Cash_Flow'!I10 -> 2220 | E26: =-'14_Cash_Flow'!J10 -> 2528.4272 | F26: =-'14_Cash_Flow'!K10 -> 2552.1841 | G26: =-'14_Cash_Flow'!L10 -> 2507.9707 | H26: =-'14_Cash_Flow'!M10 -> 2672.3044 | I26: Positive cash outflow | J26: 14_Cash_Flow
A27: Working Capital | B27: Change in NWC | C27: VND bn | D27: ='14_Cash_Flow'!I8 -> 905.30761 | E27: ='14_Cash_Flow'!J8 -> 1945.8469 | F27: ='14_Cash_Flow'!K8 -> 1061.8894 | G27: ='14_Cash_Flow'!L8 -> 1032.585 | H27: ='14_Cash_Flow'!M8 -> 1316.1024 | I27: Positive cash outflow | J27: 14_Cash_Flow
A28: FCFF | B28: Calculated FCFF | C28: VND bn | D28: =D24+D25-D26-D27 -> 7142.1924 | E28: =E24+E25-E26-E27 -> 8125.7216 | F28: =F24+F25-F26-F27 -> 11072.586 | G28: =G24+G25-G26-G27 -> 13012.051 | H28: =H24+H25-H26-H27 -> 13942.756 | I28: NOPAT + D&A - Capex - Change in NWC | J28: Formula
